Workbook

Sheet Proposal Form Tier 1
A1: Specific Criteria For the quote | B1: Quantity | E1: Instructions
A2: End-User Name | B2: Bank of America
A3: Number Of Controllers | B3: 9
C4: Chosen Tier Min QTY of Controllers | D4: Chosen Tier Max QTY of Controllers
A5: Annual Service Tier Level | B5: =_xlfn.XLOOKUP($B$3,Tiers_list!$D:$D,Tiers_list!$A:$A,,1) -> Tier - 1 - 10 | C5: =_xlfn.XLOOKUP('Proposal Form Tier 1'!$B$5,Tiers_list!$A:$A,Tiers_list!C:C,,0) -> 1 | D5: =_xlfn.XLOOKUP('Proposal Form Tier 1'!$B$5,Tiers_list!$A:$A,Tiers_list!D:D,,0) -> 10 | E5: =IF(B5<>"Tier - 1 - 10","This Sheet is intended for Tier 1. If controller over 10 use 'Basic Form Tier 2-12'","")
A6: Quantity of Annual Primary Production Instance(s) | B6: 1
A8: Quantity of Annual Primary Fail-Over Instance(s) | B8: 0
A9: Quantity of Annual DR Instance(s) | B9: 0
A10: Quantity of Annual DR Failover Instance(s) | B10: 1
A11: Total Quantity of Annual Fail-Over / DR Instance(s) | B11: =SUM(B8:B10) -> 1
A12: Percentage of Production cost to use for Failover and DR Instance(s) | B12: 0.5
A14: End-User Discount Rate | B14: =_xlfn.XLOOKUP(B2,End_user!A:A,End_user!B:B,0,0) -> 0
A15: Integrator Name | B15: Securitas Technology Co.
A16: Integrator Discount Rate | B16: =_xlfn.XLOOKUP(B15,'Integrator List'!A:A,'Integrator List'!B:B,0,0) -> 0.25
A19: Annual - Advanced Optional Micro Services | B19: Quantity | C19: Product Number | D19: UOM
A20: =_xlfn.XLOOKUP($C20,Tiers_list!$2:$2,Tiers_list!$1:$1,,0) -> ACS system data non cloud integration / parser to 3rd party systems ACS Event Messages, Credentials and User Logs Module | B20: 1 | C20: 200-50048 | D20: ea. | E20: Annual
A21: =_xlfn.XLOOKUP($C21,Tiers_list!$2:$2,Tiers_list!$1:$1,,0) -> ACS Job Scheduler Service Module | B21: 1 | C21: 200-50059 | D21: ea. | E21: Annual
A22: =_xlfn.XLOOKUP($C22,Tiers_list!$2:$2,Tiers_list!$1:$1,,0) -> AFH / Data Collection Service Module | B22: 1 | C22: 200-50060 | D22: ea. | E22: Annual
A23: =_xlfn.XLOOKUP($C23,Tiers_list!$2:$2,Tiers_list!$1:$1,,0) -> Remote ACS Hardware firmware updates Module | B23: 1 | C23: 200-50061 | D23: ea. | E23: Annual
A24: =_xlfn.XLOOKUP($C24,Tiers_list!$2:$2,Tiers_list!$1:$1,,0) -> Reader Credentials Accepted and Rejected Supervision Module | B24: 1 | C24: 200-50069 | D24: ea. | E24: Annual
A26: =_xlfn.XLOOKUP($C26,Tiers_list!$2:$2,Tiers_list!$1:$1,,0) -> ACS TLS 1.2/1.3 PCB | B26: =+B3 -> 9 | C26: 200-50070 | D26: ea. | E26: Annual
A27: =_xlfn.XLOOKUP($C27,Tiers_list!$2:$2,Tiers_list!$1:$1,,0) -> 24/7 ACS Enterprise Telephone Support | B27: 1 | C27: YEAR-ACS-RTS | D27: ea. | E27: Annual / Optional
A28: =_xlfn.XLOOKUP($C28,Tiers_list!$2:$2,Tiers_list!$1:$1,,0) -> Annual Remote Training ACS | B28: 1 | C28: 1000-30054 | D28: Required. Choose Qty of 10 hours slots | E28: Annual
A30: =_xlfn.XLOOKUP($C30,Tiers_list!$2:$2,Tiers_list!$1:$1,,0) -> ACS Enterprise - Tech Software License - Annual Software Assurance | B30: 0 | C30: 200-50007-NTS | D30: ea. | E30: Annual
A32: One-Time Required Hardware and Installation Service and support | B32: Quantity | C32: =+C19 -> Product Number | D32: UOM
A33: =_xlfn.XLOOKUP($C33,Tiers_list!$2:$2,Tiers_list!$1:$1,,0) -> TLS 1.2/1.3 PCB | B33: =+B26 -> 9 | C33: 200-10115-PCBA | D33: ea. | E33: One-Time
A34: =_xlfn.XLOOKUP($C34,Tiers_list!$2:$2,Tiers_list!$1:$1,,0) -> ACS Enterprise - Hardware - Controller Firmware Programmer KIT - No license Provided. | B34: 0 | C34: 200-50007-KT | D34: ea. | E34: One-Time
A36: Trip Charge | B36: =+IF(B15="Parabit Systems,Inc.",B3,0) -> 0 | C36: 1000-30052 | D36: ea. | E36: One-Time if Parabit is the Installer
A37: On-Site/Remote Low Voltage/Mechanical Tech Weekday Business Hours | B37: =+B36*2 -> 0 | C37: 1000-20000 | D37: ea. | E37: One-Time if Parabit is the Installer
A38: Project Management | B38: =0.15*B36 -> 0 | C38: 1000-30045 | D38: ea. | E38: One-Time if Parabit is the Installer
A40: Annual Optional Software | B40: Quantity | C40: =+C32 -> Product Number | D40: UOM | E40: Quantity chosen here will appear in Detail Software Sheet (light blue cells)
A41: =_xlfn.XLOOKUP($C41,Tiers_list!$2:$2,Tiers_list!$1:$1,,0) -> Controller/Reader Credential Enrollment Management Module | B41: 0 | C41: 200-50043 | D41: ea.
A42: =_xlfn.XLOOKUP($C42,Tiers_list!$2:$2,Tiers_list!$1:$1,,0) -> ACS system data cloud integration to 3rd party systems ACS Event Messages, Credentials and User Logs Module | B42: 0 | C42: 200-50047 | D42: ea.
A43: =_xlfn.XLOOKUP($C43,Tiers_list!$2:$2,Tiers_list!$1:$1,,0) -> Email/Text EMR Notifier Service Module | B43: 0 | C43: 200-50049 | D43: ea.
A44: =_xlfn.XLOOKUP($C44,Tiers_list!$2:$2,Tiers_list!$1:$1,,0) -> ACS controller Reader Remote Credential Lookup with Local learn Module | B44: 0 | C44: 200-50050 | D44: ea.
A45: =_xlfn.XLOOKUP($C45,Tiers_list!$2:$2,Tiers_list!$1:$1,,0) -> HR & Time Attendance Credential Integration Module | B45: 0 | C45: 200-50053 | D45: ea.
A46: =_xlfn.XLOOKUP($C46,Tiers_list!$2:$2,Tiers_list!$1:$1,,0) -> ACS Hardware and Facility Sensor Data Integration(s) Module | B46: 0 | C46: 200-50054 | D46: ea.
A47: =_xlfn.XLOOKUP($C47,Tiers_list!$2:$2,Tiers_list!$1:$1,,0) -> Suspend distribution of Select or All Event Messages generated by ACS hardware and software Module | B47: 0 | C47: 200-50058 | D47: ea.
A48: =_xlfn.XLOOKUP($C48,Tiers_list!$2:$2,Tiers_list!$1:$1,,0) -> Door / Entrance Supervision Configuration Module | B48: 0 | C48: 200-50062 | D48: ea.
A49: =_xlfn.XLOOKUP($C49,Tiers_list!$2:$2,Tiers_list!$1:$1,,0) -> ACS Controller Software Integrations DB Ecosystem Supervision Module | B49: 0 | C49: 200-50068 | D49: ea.
A51: =_xlfn.XLOOKUP($C51,Tiers_list!$2:$2,Tiers_list!$1:$1,,0) -> Silent Installer with ACS Enterprise software license Cloud Key Validation | B51: 1 | C51: 200-50040 | D51: ea. | E51: Included
A52: =_xlfn.XLOOKUP($C52,Tiers_list!$2:$2,Tiers_list!$1:$1,,0) -> Parabit Cloud App/DB Software Instance Activation/Term Management | B52: 1 | C52: 200-50041 | D52: ea. | E52: Included
A53: =_xlfn.XLOOKUP($C53,Tiers_list!$2:$2,Tiers_list!$1:$1,,0) -> ACS controller Reader Remote Credential Lookup with Local learn Module | B53: 0 | C53: 200-50071 | D53: ea.
A54: =_xlfn.XLOOKUP($C54,Tiers_list!$2:$2,Tiers_list!$1:$1,,0) -> ACS controller Reader Remote Credential Lookup with Local learn Module | B54: 0 | C54: 200-50072 | D54: ea.
A55: =_xlfn.XLOOKUP($C55,Tiers_list!$2:$2,Tiers_list!$1:$1,,0) -> Export & Reporting | B55: 0 | C55: 200-50073 | D55: ea.
A56: =_xlfn.XLOOKUP($C56,Tiers_list!$2:$2,Tiers_list!$1:$1,,0) -> Bulk Synchronisation ans Scheduling | B56: 0 | C56: 200-50074 | D56: ea.
A57: =_xlfn.XLOOKUP($C57,Tiers_list!$2:$2,Tiers_list!$1:$1,,0) -> Clone & Templates | B57: 0 | C57: 200-50075 | D57: ea.
A58: =_xlfn.XLOOKUP($C58,Tiers_list!$2:$2,Tiers_list!$1:$1,,0) -> Merge Operations | B58: 0 | C58: 200-50076 | D58: ea.
A59: =_xlfn.XLOOKUP($C59,Tiers_list!$2:$2,Tiers_list!$1:$1,,0) -> Advanced User Management | B59: 0 | C59: 200-50077 | D59: ea.
A60: =_xlfn.XLOOKUP($C60,Tiers_list!$2:$2,Tiers_list!$1:$1,,0) -> Advanced Log Filtering | B60: 0 | C60: 200-50078 | D60: ea.
A61: =_xlfn.XLOOKUP($C61,Tiers_list!$2:$2,Tiers_list!$1:$1,,0) -> Notification & Alerts | B61: 0 | C61: 200-50079 | D61: ea.

Sheet Detail_Proposal_tier 1
A1: Product # | B1: Product Tree | C1: Category | D1: Prod # Description | E1: Feature Description | F1: Business Description | G1: Feature Type | H1: UoM | I1: =CONCATENATE('Proposal Form Tier 1'!B5," ","Quantity of Primary Production Instance(s)") -> Tier - 1 - 10 Quantity of Primary Production Instance(s) | J1: =CONCATENATE('Proposal Form Tier 1'!B5," ","Total Annual Primary Instance(s) Pricing") -> Tier - 1 - 10 Total Annual Primary Instance(s) Pricing | K1: =CONCATENATE('Proposal Form Tier 1'!B5," ","Total Annual Fail-Over/DR Instance(s) Pricing") -> Tier - 1 - 10 Total Annual Fail-Over/DR Instance(s) Pricing | L1: =CONCATENATE('Proposal Form Tier 1'!B5," ","Total Quantity of Annual Fail-Over/DR Instance(s)") -> Tier - 1 - 10 Total Quantity of Annual Fail-Over/DR Instance(s) | M1: Enter # of Instances per Tier - Quantity of Annual Primary Fail-Over Instance(s) | N1: Enter # of Instances per Tier - Quantity of DR Instance(s) | O1: Enter # of Instances per Tier - Quantity of DR Failover Instance(s) | P1: MSRP / Tier Price Primary Production Instances
A2: 200-50042 | B2: ACS Software | C2: ACS Enterprise Hardware Configuration UI | D2: =_xlfn.XLOOKUP(A2,Tiers_list!$2:$2,Tiers_list!$1:$1,,0) -> Campus, Site, Floor, Controller, Entrance/Reader, User, Credential, Configuration, Diagnostics and Reports Module | E2: By Site by ACS Controller Customer defined ID, Digital Serial #, Customer defined asset tag, Entrance location data (Address, Cross Streets, Contact, Phone, Email, etc., Time Zone/DST, I/O configuration, Overlay/RFID Skim Detection times, IP/Port, DNS, DHCP. By Reader/Entrance: Reader Serial #, PID, Weekly and Holiday schedule(s) assignment, Digital API Data Integration(s) settings, Entrance Door Release duration, Door Ajar detect time, Door opening excessively to Credentials read ratio, Customer Can't Enter/Exit sequential configuration, Reader Egress time, Exit/Entry Switch Egress time, Anti-Tailgating Active/Disabled, Physical Overlay/RFID Skimmer Detect Time, Reader and Lock state Inhibit Active/Disabled integration, Loitering, Single Access, Light Sensor, Last ATM Transaction Date/Time and 3rd party system configurations. | F2: ACS Cloud Enterprise gives operators and administrators a single, unified interface to configure every layer of their access control environment — from site addresses, time zones, and network settings down to individual reader behaviors, credential masks, and third-party integration parameters. Rather than juggling separate tools or on-site visits, teams can define and push the complete hardware profile of every controller and entrance from the cloud, ensuring every site is consistently configured, operationally ready, and aligned with organizational standards from day one. | G2: Required | H2: ea. | I2: =IF('Proposal Form Tier 1'!$B$5=Tiers_list!$A$3,+'Proposal Form Tier 1'!B6,1) -> 1 | J2: =VLOOKUP('Proposal Form Tier 1'!$B$5,Tiers_list!$A:$BC,MATCH($A2,Tiers_list!$2:$2,0),FALSE)*('Proposal Form Tier 1'!$B$3/10)*(1-'Proposal Form Tier 1'!B14-'Proposal Form Tier 1'!B16) -> 2025 | K2: =J2*50% -> 1012.5 | L2: =SUM(M2:O2) -> 1 | M2: =IF($I2>0,+'Proposal Form Tier 1'!$B$8,0) -> 0 | N2: =IF($I2>0,+'Proposal Form Tier 1'!$B$9,0) -> 0 | O2: =IF($I2>0,+'Proposal Form Tier 1'!$B$10,0) -> 1 | P2: =+(J2/(1-'Proposal Form Tier 1'!$B$16-'Proposal Form Tier 1'!$B$14))+(K2/(1-'Proposal Form Tier 1'!$B$16-'Proposal Form Tier 1'!$B$14)) -> 4050
B3: ACS Software | C3: ACS Enterprise Hardware Configuration UI | D3: Campus, Site, Floor, Controller, Entrance/Reader, User, Credential, Configuration, Diagnostics and Reports Module | E3: Create/edit/update/deactivate ACS Users and ACS Users who assign access rights to ACS features | F3: Administrators gain full lifecycle control over every system user — creating, editing, and deactivating accounts while assigning precise role-based access rights that determine exactly which ACS features and data each person can reach. By tying permissions directly to user profiles rather than managing them ad hoc, organizations eliminate over-privileged accounts, enforce the principle of least privilege, and maintain a clean, auditable record of who has access to what across the entire platform.
B4: ACS Software | C4: ACS Enterprise Hardware Configuration UI | D4: Campus, Site, Floor, Controller, Entrance/Reader, User, Credential, Configuration, Diagnostics and Reports Module | E4: Active Directory (AD) support | F4: For organizations already running Microsoft Active Directory, ACS Cloud Enterprise eliminates the need for a separate set of user credentials by enabling staff to log in using their existing AD accounts. Operators can search, assign, and manage AD users and groups directly within ACS — with access permissions updating automatically in real time whenever an AD account is modified or disabled — reducing administrative burden and closing the security gaps that come from manually maintained duplicate user lists.
B5: ACS Software | C5: ACS Enterprise Hardware Configuration UI | D5: Campus, Site, Floor, Controller, Entrance/Reader, User, Credential, Configuration, Diagnostics and Reports Module | E5: Configure reader type, access by Credential holder and by Access Schedule for MMR 2.0 reader Mag Stripe and NFC Card. | F5: Operators can configure every reader in the system — defining the credential types accepted (magnetic stripe, NFC, Bluetooth, biometric, and more), assigning the appropriate access schedules, and linking readers to specific user groups — all from a centralized interface without a site visit. This ensures that every entrance behaves exactly as intended, that the right people have access at the right times, and that configuration changes are applied instantly and consistently across all locations.
B6: ACS Software | C6: ACS Enterprise Hardware Configuration UI | D6: Campus, Site, Floor, Controller, Entrance/Reader, User, Credential, Configuration, Diagnostics and Reports Module | E6: Configure Readers and/or Users on type of credential(s) required to access an entrance or group of entrances. i.e., a reader can require one, two or more types of credentials by Reader or User to gain access to a (or group of) specified Reader. | F6: Organizations can define precise credential matching rules for each reader or entrance — specifying exactly which credential types, card formats, and validation methods are required to gain access at any given point. Whether using standard match, bank credential fallback, external match validation, or protocol-based NFC matching, operators can tailor access logic per reader without firmware changes, giving security teams granular control over who gets through each door and under what conditions.
B7: ACS Software | C7: ACS Enterprise Hardware Configuration UI | D7: Campus, Site, Floor, Controller, Entrance/Reader, User, Credential, Configuration, Diagnostics and Reports Module | E7: Remote ACS controller I/O test and status inquiry | F7: Field technicians and operators can remotely test and query the real-time status of any ACS controller's I/O channels without traveling to the site, enabling rapid diagnosis of hardware issues, connection faults, and configuration mismatches from the cloud. This reduces costly site visits, shortens mean time to resolution, and ensures that technical teams have full visibility into device health before deploying maintenance resources.
B8: ACS Software | C8: ACS Enterprise Hardware Configuration UI | D8: Campus, Site, Floor, Controller, Entrance/Reader, User, Credential, Configuration, Diagnostics and Reports Module | E8: Define and remotely configure Weekly Access Schedule (Credentials required), Open (entrance unlocked) and Locked (entrance closed) | F8: Operators can define weekly access schedules — specifying which credential is required, when an entrance is open to all, or when it is locked — and push those schedules remotely to any controller or group of controllers across the organization. This eliminates manual on-site programming for routine schedule updates, ensures schedules are applied consistently across all sites, and gives security teams the flexibility to respond to operational changes without delay.
B9: ACS Software | C9: ACS Enterprise Hardware Configuration UI | D9: Campus, Site, Floor, Controller, Entrance/Reader, User, Credential, Configuration, Diagnostics and Reports Module | E9: Define Annual Holiday Access (Credential required), Open (entrance unlocked) and Locked (entrance closed) schedule. Notify selected ACS users when a future defined holiday date and schedule has not been defined within the ACS database or programmed into the ACS controller | F9: Define Annual Holiday Access (Credential required), Open (entrance unlocked) and Locked (entrance closed) schedule. Notify selected ACS users when a future defined holiday date and schedule has not been defined within the ACS database or programmed into the ACS controller
B10: ACS Software | C10: ACS Enterprise Hardware Configuration UI | D10: Campus, Site, Floor, Controller, Entrance/Reader, User, Credential, Configuration, Diagnostics and Reports Module | E10: Manage and remotely configure credentials table/configuration accepted for NFC, Magnetic Stripe. Accepted Credentials, Admin Credentials, Financial Credential types and Exception tables and assign to reader(s)/entrance(s). | F10: Operators can create, import, edit, merge, and export credential lists — covering accepted credentials, administrative cards, financial credential types, and exception (suspect/reject) tables — and assign them directly to individual readers or push them across multiple sites simultaneously. By centralizing credential list management in the cloud, organizations avoid the risks of outdated lists on individual controllers and ensure that access decisions are always based on the most current and accurate credential data available.
B11: ACS Software | C11: ACS Enterprise Hardware Configuration UI | D11: Campus, Site, Floor, Controller, Entrance/Reader, User, Credential, Configuration, Diagnostics and Reports Module | E11: Remotely set an ACS controllers Maintenance Mode (Active/Clear) | F11: Operators and technicians can remotely activate and manage Maintenance Mode on any ACS controller, flagging all activity during that window so that alarms generated by maintenance work are clearly identified and not mistakenly escalated to monitoring centers. With configurable durations, automatic expiry, and real-time event tracking of who activated maintenance, when, and for how long, organizations maintain full operational accountability even during planned downtime.
B12: ACS Software | C12: ACS Enterprise Hardware Configuration UI | D12: Campus, Site, Floor, Controller, Entrance/Reader, User, Credential, Configuration, Diagnostics and Reports Module | E12: Remote Door/Entrance Unlock for x - xx seconds | F12: Administrators and operators can instantly unlock any entrance remotely for a defined duration — whether responding to an emergency, assisting a visitor, or supporting a maintenance request — without sending a technician to the site. The action is logged in the audit trail, automatically reversed after the configured time, and fully visible in real-time event monitoring, giving teams both the speed to respond and the traceability to stay compliant.
B13: ACS Software | C13: ACS Enterprise Hardware Configuration UI | D13: Campus, Site, Floor, Controller, Entrance/Reader, User, Credential, Configuration, Diagnostics and Reports Module | E13: Remote Door/Entrance Access Schedule State Override with an until date/time (Access, Lock or Open). | F13: When circumstances require a door to behave differently from its standard schedule — planned maintenance, emergency access, special events, or adverse weather — operators can remotely override the entrance state (open, access, or locked) for a defined date and time window without modifying the underlying schedule. The override clears automatically when the window expires, the original schedule resumes immediately, and the entire action is logged, ensuring operational flexibility never comes at the cost of security accountability.
B14: ACS Software | C14: ACS Enterprise Hardware Configuration UI | D14: Campus, Site, Floor, Controller, Entrance/Reader, User, Credential, Configuration, Diagnostics and Reports Module | E14: Manage User Access Credential(s) data: Import/Export .csv files • Credential Type: Bio Datapoint file1, Bio Datapoint file2, Bio Datapoint file…, Keypad Code, Mobile Device EIN/MAC???, etc. • Prox/NFC Card or Bluetooth: Facility Code / BIN number or ID / PAN number • 5 fields for 1st, middle, last, etc. names • ID used to validate Credential Holder • Driver’s License, Passport, Social Security #, Employee ID #, User Defined Credential 1, User Defined Credential 2… • Address1: #, Street, City, County, Town, Village, Prefecture, State, Zip/Postal Code, Country, • Address2: #, Street, City, County, Town, Village, Prefecture, State, Zip/Postal Code, Country, • Phone1, Phone2, etc. • Email1, Email2, etc. • Manager1, Phone1, Email1 • Manager2, Phone1, Email1 • (Investigate other credential types / fields required per credential and type): | F14: Operators can manage the full credential data profile for each user — importing and exporting credential records via CSV, defining credential types accepted per user, and linking physical or virtual credentials to access rights — giving organizations a clean, importable, and auditable record of who holds which credential and what they can access. This streamlines onboarding, offboarding, and credential audits while reducing the manual effort and error risk of maintaining credential records outside the system.
B15: ACS Software | C15: ACS Enterprise Hardware Configuration UI | D15: Campus, Site, Floor, Controller, Entrance/Reader, User, Credential, Configuration, Diagnostics and Reports Module | E15: View, export and reports sites, hardware, configuration, events, credentials read, user functions executed, user/hardware configuration change logs and ACS controller and reader inventory | F15: Administrators, operators, and auditors can view, filter, search a comprehensive set of reports spanning site activity, hardware status, configuration changes, credential events, and user actions — all from a single interface. Whether preparing for a compliance audit, investigating a security incident, or reviewing operational performance, teams can generate the exact data they need in seconds.
A16: 200-50043 | B16: ACS Software | C16: ACS Enterprise Hardware Configuration UI | D16: =_xlfn.XLOOKUP(A16,Tiers_list!$2:$2,Tiers_list!$1:$1,,0) -> Controller/Reader Credential Enrollment Management Module | E16: Configure an ACS controller reader to learn/enroll a credential. The learn/enroll feature is configured by one or more designated User approval(s). | F16: ACS Cloud Enterprise enables any configured reader to enter a learn or enrollment mode, automatically capturing and storing a new credential when it is presented — eliminating the need to manually enter card numbers during onboarding. This accelerates the setup of new cardholders at large-scale deployments, reduces data entry errors, and gives operators a fast, reliable way to add credentials to the system directly from the physical reader. | G16: Optional | H16: ea. | I16: =_xlfn.XLOOKUP($A16,'Proposal Form Tier 1'!$C:$C,'Proposal Form Tier 1'!$B:$B,0,0) -> 0 | J16: =VLOOKUP('Proposal Form Tier 1'!$B$5,Tiers_list!$A:$BC,MATCH($A16,Tiers_list!$2:$2,0),FALSE)*(I16/10)*(1-'Proposal Form Tier 1'!$B$16-'Proposal Form Tier 1'!$B$14) -> 0 | K16: =J16*50% -> 0 | L16: =SUM(M16:O16) -> 0 | P16: =+(J16/(1-'Proposal Form Tier 1'!$B$16-'Proposal Form Tier 1'!$B$14))+(K16/(1-'Proposal Form Tier 1'!$B$16-'Proposal Form Tier 1'!$B$14)) -> 0
A17: 200-50044 | B17: ACS Software | C17: ACS Enterprise Hardware Configuration UI | D17: =_xlfn.XLOOKUP(A17,Tiers_list!$2:$2,Tiers_list!$1:$1,,0) -> ACS User Login Profile Management Module | E17: Create/Edit/Deactivate ACS Users and assign ACS User function/data access rights by ACS User/ACS User Profile type (Super Admin, Admin, Super Investigator, Investigator, Super Production user, Production user, etc.) A user profile is a type of user(s) that has been defined to perform specified functions within the ACS Enterprise software suite. | F17: Administrators can create, edit, and deactivate ACS user accounts and assign each user precise function and data access rights that determine which modules, sites, and operations they can perform within the platform. With role-based permissions, automated lockout on permission changes, and a full audit trail of every modification, organizations maintain tight control over who can administer the system and ensure that access rights always reflect current responsibilities. | G17: Required | H17: ea. | I17: =+'Proposal Form Tier 1'!$B$6 -> 1 | J17: =VLOOKUP('Proposal Form Tier 1'!$B$5,Tiers_list!$A:$BC,MATCH($A17,Tiers_list!$2:$2,0),FALSE)*('Proposal Form Tier 1'!B3/10)*(1-'Proposal Form Tier 1'!$B$16-'Proposal Form Tier 1'!$B$14) -> 126.5625 | K17: =J17*50% -> 63.28125 | L17: =SUM(M17:O17) -> 1 | M17: =IF($I17>0,+'Proposal Form Tier 1'!$B$8,0) -> 0 | N17: =IF($I17>0,+'Proposal Form Tier 1'!$B$9,0) -> 0 | O17: =IF($I17>0,+'Proposal Form Tier 1'!$B$10,0) -> 1 | P17: =+(J17/(1-'Proposal Form Tier 1'!$B$16-'Proposal Form Tier 1'!$B$14))+(K17/(1-'Proposal Form Tier 1'!$B$16-'Proposal Form Tier 1'!$B$14)) -> 253.125
A18: 200-50045 | B18: ACS Software | C18: ACS Enterprise Hardware Configuration UI | D18: =_xlfn.XLOOKUP(A18,Tiers_list!$2:$2,Tiers_list!$1:$1,,0) -> ACS Controller / User Territory Management Module | E18: Manage Territory's by geographic region, state, time zone, defined controller properties and/or by User. Assign ACS controllers to a Territory(s) and assign Territory(s) to an ACS User(s) supporting assignment of ACS functions to be executed/managed. | G18: Required | H18: ea. | I18: =+'Proposal Form Tier 1'!$B$6 -> 1 | J18: =VLOOKUP('Proposal Form Tier 1'!$B$5,Tiers_list!$A:$BC,MATCH($A18,Tiers_list!$2:$2,0),FALSE)*('Proposal Form Tier 1'!B3/10)*(1-'Proposal Form Tier 1'!$B$16-'Proposal Form Tier 1'!$B$14) -> 126.5625 | K18: =J18*50% -> 63.28125 | L18: =SUM(M18:O18) -> 1 | M18: =IF($I18>0,+'Proposal Form Tier 1'!$B$8,0) -> 0 | N18: =IF($I18>0,+'Proposal Form Tier 1'!$B$9,0) -> 0 | O18: =IF($I18>0,+'Proposal Form Tier 1'!$B$10,0) -> 1 | P18: =+(J18/(1-'Proposal Form Tier 1'!$B$16-'Proposal Form Tier 1'!$B$14))+(K18/(1-'Proposal Form Tier 1'!$B$16-'Proposal Form Tier 1'!$B$14)) -> 253.125
C19: ACS Enterprise Hardware Configuration UI Total | I19: =SUBTOTAL(9,I2:I18) -> 3 | J19: =SUBTOTAL(9,J2:J18) -> 2278.125 | K19: =SUBTOTAL(9,K2:K18) -> 1139.0625 | L19: =SUBTOTAL(9,L2:L18) -> 3 | M19: =SUBTOTAL(9,M2:M18) -> 0 | N19: =SUBTOTAL(9,N2:N18) -> 0 | O19: =SUBTOTAL(9,O2:O18) -> 3 | P19: =SUBTOTAL(9,P2:P18) -> 4556.25
A20: 200-50046 | B20: ACS Software | C20: ACS Enterprise Integrations | D20: =_xlfn.XLOOKUP(A20,Tiers_list!$2:$2,Tiers_list!$1:$1,,0) -> Integration to External ACS Hardware / Software Certificate / Key software / system Module | E20: ACS controller and MMR 2.0 reader and ACS controller and ACS Enterprise software TLS Communication and Data Encryption External System scheduled or on-demand key/cert generation and management (One-Time and Annual Pricing TBD) | F20: ACS Cloud Enterprise secures all communications between controllers, Readers and the cloud using mutual TLS — which is the strongest encryption. This ensures credential data, control commands, and event messages are protected against interception and replay attacks. Certificates are stored in cloud key vaults with policy-controlled access and automated rotation, and all authentication activity is logged, giving organizations the cryptographic foundation needed to meet demanding security and compliance requirements. | G20: Required | H20: ea. | I20: =+'Proposal Form Tier 1'!$B$6 -> 1 | J20: =VLOOKUP('Proposal Form Tier 1'!$B$5,Tiers_list!$A:$BC,MATCH($A20,Tiers_list!$2:$2,0),FALSE)*('Proposal Form Tier 1'!B3/10)*(1-'Proposal Form Tier 1'!$B$16-'Proposal Form Tier 1'!$B$14) -> 168.75 | K20: =J20*50% -> 84.375 | L20: =SUM(M20:O20) -> 1 | M20: =IF($I20>0,+'Proposal Form Tier 1'!$B$8,0) -> 0 | N20: =IF($I20>0,+'Proposal Form Tier 1'!$B$9,0) -> 0 | O20: =IF($I20>0,+'Proposal Form Tier 1'!$B$10,0) -> 1 | P20: =+(J20/(1-'Proposal Form Tier 1'!$B$16-'Proposal Form Tier 1'!$B$14))+(K20/(1-'Proposal Form Tier 1'!$B$16-'Proposal Form Tier 1'!$B$14)) -> 337.5
A21: 200-50047 | B21: ACS Software | C21: ACS Enterprise Integrations | D21: =_xlfn.XLOOKUP(A21,Tiers_list!$2:$2,Tiers_list!$1:$1,,0) -> ACS system data cloud integration to 3rd party systems ACS Event Messages, Credentials and User Logs Module | E21: Define, Parse and forward ACS Event Messages collected/received by ACS controllers via a API / Windows / Micro Service to 3rd party alarm/event message monitoring systems in the following (ContactID, Extended Contact ID, others TBD) formats (MAStermind supported today, but develop interfaces to Genetec, MAStermind, Milestone, Avigilon and others.) | F21: ACS Cloud Enterprise collects, parses, and categorizes every event message generated by ACS controllers — including credential reads, door events, alarms, health checks, and system actions — and routes them to the appropriate destinations in real time. Operators can configure exactly which message types are forwarded to internal databases, external monitoring platforms, or third-party systems, with full control over message priority, credential data masking, and failover queuing to ensure no critical event is lost even when downstream systems are temporarily unavailable. | G21: Optional | H21: ea. | I21: =_xlfn.XLOOKUP($A21,'Proposal Form Tier 1'!$C:$C,'Proposal Form Tier 1'!$B:$B,0,0) -> 0 | J21: =VLOOKUP('Proposal Form Tier 1'!$B$5,Tiers_list!$A:$BC,MATCH($A21,Tiers_list!$2:$2,0),FALSE)*(I21/10)*(1-'Proposal Form Tier 1'!$B$16-'Proposal Form Tier 1'!$B$14) -> 0 | K21: =J21*50% -> 0 | L21: =SUM(M21:O21) -> 0 | P21: =+(J21/(1-'Proposal Form Tier 1'!$B$16-'Proposal Form Tier 1'!$B$14))+(K21/(1-'Proposal Form Tier 1'!$B$16-'Proposal Form Tier 1'!$B$14)) -> 0
A22: 200-50048 | B22: ACS Software | C22: ACS Enterprise Integrations | D22: =_xlfn.XLOOKUP(A22,Tiers_list!$2:$2,Tiers_list!$1:$1,,0) -> ACS system data non cloud integration / parser to 3rd party systems ACS Event Messages, Credentials and User Logs Module | E22: Transmission of ACS Event Messages to non-cloud 3rd party monitoring (MAStermind) applications (Windows Service). (Integration fees may apply) | F22: Organizations using non-cloud monitoring platforms such as MAStermind or similar systems can seamlessly receive ACS event messages through a configurable, authenticated integration that supports multiple server endpoints with automatic failover. Operators define server groups, set message criticality levels, and control credential data exposure in payloads, ensuring that third-party monitoring teams receive exactly the right alerts in real time — without manual intervention and without compromising sensitive cardholder data. | G22: Required. Choose QTY | H22: ea. | I22: =_xlfn.XLOOKUP($A22,'Proposal Form Tier 1'!$C:$C,'Proposal Form Tier 1'!$B:$B,0,0) -> 1 | J22: =IF(I22<>0,VLOOKUP('Proposal Form Tier 1'!$B$5,Tiers_list!$A:$BC,MATCH($A22,Tiers_list!$2:$2,0),FALSE)*('Proposal Form Tier 1'!$B$3/10)*(1-'Proposal Form Tier 1'!$B$16-'Proposal Form Tier 1'!$B$14),0) -> 168.75 | K22: =J22*50% -> 84.375 | L22: =SUM(M22:O22) -> 1 | M22: =IF($I22>0,+'Proposal Form Tier 1'!$B$8,0) -> 0 | N22: =IF($I22>0,+'Proposal Form Tier 1'!$B$9,0) -> 0 | O22: =IF($I22>0,+'Proposal Form Tier 1'!$B$10,0) -> 1 | P22: =+(J22/(1-'Proposal Form Tier 1'!$B$16-'Proposal Form Tier 1'!$B$14))+(K22/(1-'Proposal Form Tier 1'!$B$16-'Proposal Form Tier 1'!$B$14)) -> 337.5
A23: 200-50049 | B23: ACS Software | C23: ACS Enterprise Integrations | D23: =_xlfn.XLOOKUP(A23,Tiers_list!$2:$2,Tiers_list!$1:$1,,0) -> Email/Text EMR Notifier Service Module | E23: EMR sends an email or text to defined Email Address(s)/Mobile #(s) of ACS events selected | F23: Security teams, facility managers, and operations staff can receive instant email or SMS notifications for any ACS event classified as critical — delivered directly to configured user groups without requiring access to the monitoring platform. Operators define notification recipient lists, assign message criticality categories, and configure which alarms trigger immediate outreach, ensuring that the right people are alerted at the right time regardless of whether they are actively monitoring the system dashboard. | G23: Optional | H23: ea. | I23: =_xlfn.XLOOKUP($A23,'Proposal Form Tier 1'!$C:$C,'Proposal Form Tier 1'!$B:$B,0,0) -> 0 | J23: =IF(I23<>0,VLOOKUP('Proposal Form Tier 1'!$B$5,Tiers_list!$A:$BC,MATCH($A23,Tiers_list!$2:$2,0),FALSE)*('Proposal Form Tier 1'!$B$3/10)*(1-'Proposal Form Tier 1'!$B$16-'Proposal Form Tier 1'!$B$14),0) -> 0 | K23: =J23*50% -> 0 | L23: =SUM(M23:O23) -> 0 | P23: =+(J23/(1-'Proposal Form Tier 1'!$B$16-'Proposal Form Tier 1'!$B$14))+(K23/(1-'Proposal Form Tier 1'!$B$16-'Proposal Form Tier 1'!$B$14)) -> 0
A24: 200-50050 | B24: ACS Software | C24: ACS Enterprise Integrations | D24: =_xlfn.XLOOKUP(A24,Tiers_list!$2:$2,Tiers_list!$1:$1,,0) -> ACS controller Reader Remote Credential Lookup with Local learn Module | E24: Remote lookup of Accepted, Rejected and Suspect Credentials in ACS DB. | F24: When a credential is presented at a reader configured for external match validation, ACS Cloud Enterprise forwards the request to the Parabit Cloud Enterprise in real time, retrieves the allow or reject decision, and acts on it immediately . This enables organizations to maintain centralized, organization-wide credential authority in an external system (such as a financial institution's BIN database) while still leveraging the speed and resilience of local controller enforcement. | G24: Optional | H24: ea. | I24: =_xlfn.XLOOKUP($A24,'Proposal Form Tier 1'!$C:$C,'Proposal Form Tier 1'!$B:$B,0,0) -> 0 | J24: =IF(I24<>0,VLOOKUP('Proposal Form Tier 1'!$B$5,Tiers_list!$A:$BC,MATCH($A24,Tiers_list!$2:$2,0),FALSE)*('Proposal Form Tier 1'!$B$3/10)*(1-'Proposal Form Tier 1'!$B$16-'Proposal Form Tier 1'!$B$14),0) -> 0 | K24: =J24*50% -> 0 | L24: =SUM(M24:O24) -> 0 | P24: =+(J24/(1-'Proposal Form Tier 1'!$B$16-'Proposal Form Tier 1'!$B$14))+(K24/(1-'Proposal Form Tier 1'!$B$16-'Proposal Form Tier 1'!$B$14)) -> 0
A25: 200-50051 | B25: ACS Software | C25: ACS Enterprise Integrations | D25: =_xlfn.XLOOKUP(A25,Tiers_list!$2:$2,Tiers_list!$1:$1,,0) -> ACS Enterprise NYCE BIN Table Import / Optimization Module | E25: Monthly download and distribution of the NYCE BIN Table to all ACS Cloud Enterprise Users. Client ACS Cloud Enterprise software detects file update, authenticates and automatically downloads and optimizes the file, then schedules the initialization of the file into all designated ACS controllers. | F25: ACS Cloud Enterprise automates the monthly download and distribution of the NYCE BIN table to all configured controllers across every enterprise site, ensuring that every reader has an up-to-date financial credential reference without requiring manual file transfers or on-site updates. This eliminates the operational risk of controllers running outdated BIN data, reduces the administrative overhead of managing credential table updates at scale, and ensures consistent access decisions across the entire estate. | G25: Required | H25: ea. | I25: =+'Proposal Form Tier 1'!$B$6 -> 1 | J25: =IF(I25<>0,VLOOKUP('Proposal Form Tier 1'!$B$5,Tiers_list!$A:$BC,MATCH($A25,Tiers_list!$2:$2,0),FALSE)*('Proposal Form Tier 1'!$B$3/10)*(1-'Proposal Form Tier 1'!$B$16-'Proposal Form Tier 1'!$B$14),0) -> 126.5625 | K25: =J25*50% -> 63.28125 | L25: =SUM(M25:O25) -> 1 | M25: =IF($I25>0,+'Proposal Form Tier 1'!$B$8,0) -> 0 | N25: =IF($I25>0,+'Proposal Form Tier 1'!$B$9,0) -> 0 | O25: =IF($I25>0,+'Proposal Form Tier 1'!$B$10,0) -> 1 | P25: =+(J25/(1-'Proposal Form Tier 1'!$B$16-'Proposal Form Tier 1'!$B$14))+(K25/(1-'Proposal Form Tier 1'!$B$16-'Proposal Form Tier 1'!$B$14)) -> 253.125
A26: 200-50052 | B26: ACS Software | C26: ACS Enterprise Integrations | D26: =_xlfn.XLOOKUP(A26,Tiers_list!$2:$2,Tiers_list!$1:$1,,0) -> KAL ATM Management Software Integration Module | E26: Remote 6/8 Digit BIN Lookup, Site Lock down and Site Open commands | F26: Operators can execute remote 6- or 8-digit BIN lookup queries against any controller and issue immediate site-wide lockdown or open commands from the cloud — giving security teams the ability to respond to threat events or operational emergencies in seconds without dispatching field personnel. All commands are authenticated, logged, and reversible, ensuring that emergency access control actions are both fast and fully accountable. | G26: Required | H26: ea. | I26: =+'Proposal Form Tier 1'!$B$6 -> 1 | J26: =IF(I26<>0,VLOOKUP('Proposal Form Tier 1'!$B$5,Tiers_list!$A:$BC,MATCH($A26,Tiers_list!$2:$2,0),FALSE)*('Proposal Form Tier 1'!$B$3/10)*(1-'Proposal Form Tier 1'!$B$16-'Proposal Form Tier 1'!$B$14),0) -> 84.375 | K26: =J26*50% -> 42.1875 | L26: =SUM(M26:O26) -> 1 | M26: =IF($I26>0,+'Proposal Form Tier 1'!$B$8,0) -> 0 | N26: =IF($I26>0,+'Proposal Form Tier 1'!$B$9,0) -> 0 | O26: =IF($I26>0,+'Proposal Form Tier 1'!$B$10,0) -> 1 | P26: =+(J26/(1-'Proposal Form Tier 1'!$B$16-'Proposal Form Tier 1'!$B$14))+(K26/(1-'Proposal Form Tier 1'!$B$16-'Proposal Form Tier 1'!$B$14)) -> 168.75
A27: 200-50053 | B27: ACS Software | C27: ACS Enterprise Integrations | D27: =_xlfn.XLOOKUP(A27,Tiers_list!$2:$2,Tiers_list!$1:$1,,0) -> HR & Time Attendance Credential Integration Module | E27: Credential Integration into 3rd Party systems - HR, Time and Attendance, Payroll, Transaction, Credential Management, etc. | F27: ACS Cloud Enterprise can synchronize credential and access event data with external HR, time-and-attendance, payroll, and identity management systems — ensuring that access rights automatically reflect employment status, shift schedules, and organizational changes without requiring duplicate data entry across platforms. This integration eliminates the gaps between physical security and HR processes, reduces the risk of unauthorized access from stale credentials, and provides a unified view of who accessed what and when across interconnected enterprise systems. | G27: Optional | H27: ea. | I27: =_xlfn.XLOOKUP($A27,'Proposal Form Tier 1'!$C:$C,'Proposal Form Tier 1'!$B:$B,0,0) -> 0 | J27: =IF(I27<>0,VLOOKUP('Proposal Form Tier 1'!$B$5,Tiers_list!$A:$BC,MATCH($A27,Tiers_list!$2:$2,0),FALSE)*('Proposal Form Tier 1'!$B$3/10)*(1-'Proposal Form Tier 1'!$B$16-'Proposal Form Tier 1'!$B$14),0) -> 0 | K27: =J27*50% -> 0 | L27: =SUM(M27:O27) -> 0 | M27: =IF($I27>0,+'Proposal Form Tier 1'!$B$8,0) -> 0 | N27: =IF($I27>0,+'Proposal Form Tier 1'!$B$9,0) -> 0 | O27: =IF($I27>0,+'Proposal Form Tier 1'!$B$10,0) -> 0 | P27: =+(J27/(1-'Proposal Form Tier 1'!$B$16-'Proposal Form Tier 1'!$B$14))+(K27/(1-'Proposal Form Tier 1'!$B$16-'Proposal Form Tier 1'!$B$14)) -> 0
A28: 200-50054 | B28: ACS Software | C28: ACS Enterprise Integrations | D28: =_xlfn.XLOOKUP(A28,Tiers_list!$2:$2,Tiers_list!$1:$1,,0) -> ACS Hardware and Facility Sensor Data Integration(s) Module | E28: Facility Sensors integrated to an ACS controller and with Third Party Hardware Data Point (ATM, NVR, Alarm system, etc.) integrations for Loitering, Light, Door, Ingress, Egress, SkimGard, etc. supervision | F28: ACS Cloud Enterprise connects facility sensors and third-party hardware devices to the ACS controller ecosystem, enabling sensor-triggered events — such as light sensor readings, presence detection, or environmental alerts — to be captured, processed, and forwarded alongside standard access control events. This gives operators a unified operational picture that combines physical security with facility intelligence, supporting use cases from loitering detection and single-access enforcement to automated alarm responses tied to environmental conditions. | G28: Optional | H28: ea. | I28: =_xlfn.XLOOKUP($A28,'Proposal Form Tier 1'!$C:$C,'Proposal Form Tier 1'!$B:$B,0,0) -> 0 | J28: =IF(I28<>0,VLOOKUP('Proposal Form Tier 1'!$B$5,Tiers_list!$A:$BC,MATCH($A28,Tiers_list!$2:$2,0),FALSE)*('Proposal Form Tier 1'!$B$3/10)*(1-'Proposal Form Tier 1'!$B$16-'Proposal Form Tier 1'!$B$14),0) -> 0 | K28: =J28*50% -> 0 | L28: =SUM(M28:O28) -> 0 | M28: =IF($I28>0,+'Proposal Form Tier 1'!$B$8,0) -> 0 | N28: =IF($I28>0,+'Proposal Form Tier 1'!$B$9,0) -> 0 | O28: =IF($I28>0,+'Proposal Form Tier 1'!$B$10,0) -> 0 | P28: =+(J28/(1-'Proposal Form Tier 1'!$B$16-'Proposal Form Tier 1'!$B$14))+(K28/(1-'Proposal Form Tier 1'!$B$16-'Proposal Form Tier 1'!$B$14)) -> 0
C29: ACS Enterprise Integrations Total | I29: =SUBTOTAL(9,I20:I28) -> 4 | J29: =SUBTOTAL(9,J20:J28) -> 548.4375 | K29: =SUBTOTAL(9,K20:K28) -> 274.21875 | L29: =SUBTOTAL(9,L20:L28) -> 4 | M29: =SUBTOTAL(9,M20:M28) -> 0 | N29: =SUBTOTAL(9,N20:N28) -> 0 | O29: =SUBTOTAL(9,O20:O28) -> 4 | P29: =SUBTOTAL(9,P20:P28) -> 1096.875
A30: 200-50055 | B30: ACS Software | C30: ACS Enterprise Hardware and Software System Supervision and Activity Logs | D30: =_xlfn.XLOOKUP(A30,Tiers_list!$2:$2,Tiers_list!$1:$1,,0) -> ACS User Data changed / functions executed Activity Tracking Module | E30: ACS User Data changed / functions executed Activity Tracking | F30: Every action taken by an ACS user — from configuration changes and schedule updates to credential assignments and system logins — is automatically captured and stored in a structured activity log that records who did what, when, and from where. Administrators and auditors can search, filter, and export these logs at any time, providing the complete chain of accountability needed for internal audits, compliance reviews, and security investigations without relying on manual record-keeping. | G30: Required | H30: ea. | I30: =+'Proposal Form Tier 1'!$B$6 -> 1 | J30: =IF(I30<>0,VLOOKUP('Proposal Form Tier 1'!$B$5,Tiers_list!$A:$BC,MATCH($A30,Tiers_list!$2:$2,0),FALSE)*('Proposal Form Tier 1'!$B$3/10)*(1-'Proposal Form Tier 1'!$B$16-'Proposal Form Tier 1'!$B$14),0) -> 126.5625 | K30: =J30*50% -> 63.28125 | L30: =SUM(M30:O30) -> 1 | M30: =IF($I30>0,+'Proposal Form Tier 1'!$B$8,0) -> 0 | N30: =IF($I30>0,+'Proposal Form Tier 1'!$B$9,0) -> 0 | O30: =IF($I30>0,+'Proposal Form Tier 1'!$B$10,0) -> 1 | P30: =+(J30/(1-'Proposal Form Tier 1'!$B$16-'Proposal Form Tier 1'!$B$14))+(K30/(1-'Proposal Form Tier 1'!$B$16-'Proposal Form Tier 1'!$B$14)) -> 253.125
A31: 200-50056 | B31: ACS Software | C31: ACS Enterprise Hardware and Software System Supervision and Activity Logs | D31: =_xlfn.XLOOKUP(A31,Tiers_list!$2:$2,Tiers_list!$1:$1,,0) -> ACS Hardware / Software availability monitoring Module | E31: Monitor ACS controller and MMR 2.0 Reader Heartbeats and software / DB availability. Event Messages when ACS hardware, MMR 2.0 readers, ACS software and DB availability are not responding to heartbeat requests | F31: ACS Cloud Enterprise continuously monitors the heartbeat signals from every controller and MMR 2.0 reader in the network, detecting offline devices within a configurable threshold and triggering immediate alerts to the responsible team before the issue impacts operations. Administrators can set monitoring intervals, configure escalation rules, view real-time device status dashboards, and access detailed uptime and connectivity reports — transforming device health monitoring from a reactive, manual process into a proactive, automated capability. | G31: Required | H31: ea. | I31: =+'Proposal Form Tier 1'!$B$6 -> 1 | J31: =IF(I31<>0,VLOOKUP('Proposal Form Tier 1'!$B$5,Tiers_list!$A:$BC,MATCH($A31,Tiers_list!$2:$2,0),FALSE)*('Proposal Form Tier 1'!$B$3/10)*(1-'Proposal Form Tier 1'!$B$16-'Proposal Form Tier 1'!$B$14),0) -> 168.75 | K31: =J31*50% -> 84.375 | L31: =SUM(M31:O31) -> 1 | M31: =IF($I31>0,+'Proposal Form Tier 1'!$B$8,0) -> 0 | N31: =IF($I31>0,+'Proposal Form Tier 1'!$B$9,0) -> 0 | O31: =IF($I31>0,+'Proposal Form Tier 1'!$B$10,0) -> 1 | P31: =+(J31/(1-'Proposal Form Tier 1'!$B$16-'Proposal Form Tier 1'!$B$14))+(K31/(1-'Proposal Form Tier 1'!$B$16-'Proposal Form Tier 1'!$B$14)) -> 337.5
A32: 200-50057 | B32: ACS Software | C32: ACS Enterprise Hardware and Software System Supervision and Activity Logs | D32: =_xlfn.XLOOKUP(A32,Tiers_list!$2:$2,Tiers_list!$1:$1,,0) -> ACS Hardware Configuration Discrepancy Supervision, Notification and Auto Correct Service Module | E32: Collect/Validate/Report/Notify of ACS hardware configuration discrepancies with configuration settings defined for each ACS / MMR 2.0 hardware device within the DB | F32: ACS Cloud Enterprise automatically compares the configuration stored in the cloud database against the actual configuration resident in each controller, flagging any discrepancies in schedules, credential lists, network settings, or device assignments before they cause operational failures or compliance gaps. When a mismatch is detected, the system notifies the responsible team and provides the context needed to resolve the discrepancy quickly — eliminating the silent configuration drift that can undermine security and audit readiness in large, distributed deployments. | G32: Required | H32: ea. | I32: =+'Proposal Form Tier 1'!$B$6 -> 1 | J32: =IF(I32<>0,VLOOKUP('Proposal Form Tier 1'!$B$5,Tiers_list!$A:$BC,MATCH($A32,Tiers_list!$2:$2,0),FALSE)*('Proposal Form Tier 1'!$B$3/10)*(1-'Proposal Form Tier 1'!$B$16-'Proposal Form Tier 1'!$B$14),0) -> 126.5625 | K32: =J32*50% -> 63.28125 | L32: =SUM(M32:O32) -> 1 | M32: =IF($I32>0,+'Proposal Form Tier 1'!$B$8,0) -> 0 | N32: =IF($I32>0,+'Proposal Form Tier 1'!$B$9,0) -> 0 | O32: =IF($I32>0,+'Proposal Form Tier 1'!$B$10,0) -> 1 | P32: =+(J32/(1-'Proposal Form Tier 1'!$B$16-'Proposal Form Tier 1'!$B$14))+(K32/(1-'Proposal Form Tier 1'!$B$16-'Proposal Form Tier 1'!$B$14)) -> 253.125
A33: 200-50058 | B33: ACS Software | C33: ACS Enterprise Hardware and Software System Supervision and Activity Logs | D33: =_xlfn.XLOOKUP(A33,Tiers_list!$2:$2,Tiers_list!$1:$1,,0) -> Suspend distribution of Select or All Event Messages generated by ACS hardware and software Module | E33: Suspend ACS hardware and software message transmission and/or integration configuration activation with an until date/time | F33: Operators can temporarily suspend the transmission of ACS event messages and integration configurations to specified external systems for a defined window — providing a controlled way to pause outbound data flows during maintenance, system updates, or planned downtime without losing the underlying event data. All suppression activity is logged, suppressed server lists are visible for audit review, and normal transmission resumes automatically when the suppression window closes, ensuring that operational maintenance never creates permanent gaps in the monitoring record. | G33: Optional | H33: ea. | I33: =_xlfn.XLOOKUP($A33,'Proposal Form Tier 1'!$C:$C,'Proposal Form Tier 1'!$B:$B,0,0) -> 0 | J33: =IF(I33<>0,VLOOKUP('Proposal Form Tier 1'!$B$5,Tiers_list!$A:$BC,MATCH($A33,Tiers_list!$2:$2,0),FALSE)*('Proposal Form Tier 1'!$B$3/10)*(1-'Proposal Form Tier 1'!$B$16-'Proposal Form Tier 1'!$B$14),0) -> 0 | K33: =J33*50% -> 0 | L33: =SUM(M33:O33) -> 0 | M33: =IF($I33>0,+'Proposal Form Tier 1'!$B$8,0) -> 0 | N33: =IF($I33>0,+'Proposal Form Tier 1'!$B$9,0) -> 0 | O33: =IF($I33>0,+'Proposal Form Tier 1'!$B$10,0) -> 0 | P33: =+(J33/(1-'Proposal Form Tier 1'!$B$16-'Proposal Form Tier 1'!$B$14))+(K33/(1-'Proposal Form Tier 1'!$B$16-'Proposal Form Tier 1'!$B$14)) -> 0
C34: ACS Enterprise Hardware and Software System Supervision and Activity Logs Total | I34: =SUBTOTAL(9,I30:I33) -> 3 | J34: =SUBTOTAL(9,J30:J33) -> 421.875 | K34: =SUBTOTAL(9,K30:K33) -> 210.9375 | L34: =SUBTOTAL(9,L30:L33) -> 3 | M34: =SUBTOTAL(9,M30:M33) -> 0 | N34: =SUBTOTAL(9,N30:N33) -> 0 | O34: =SUBTOTAL(9,O30:O33) -> 3 | P34: =SUBTOTAL(9,P30:P33) -> 843.75
A35: 200-50059 | B35: ACS Software | C35: ACS Enterprise Mass Programming and Data Collection/Receiving Services | D35: =_xlfn.XLOOKUP(A35,Tiers_list!$2:$2,Tiers_list!$1:$1,,0) -> ACS Job Scheduler Service Module | E35: ACS Users schedule effective date/time ACS controller/MMR 2.0 reader configurations to be executed, i.e., reader, I/O, 3rd party integrations, temporary override, configuration settings, weekly and holiday schedules, firmware updates, encryption key/certificate updates, data collection, etc. | F35: Administrators and operators can schedule automated jobs to push configuration updates, initialize access schedules, and manage credential lists across any number of controllers and sites at a defined date and time — eliminating the need for manual, site-by-site initialization during operational hours. Jobs can be configured for one-time, weekly, or monthly recurrence, scoped to individual sites or entire territories, and monitored in real time with automatic retry logic and failure alerts, making large-scale system updates manageable, predictable, and audit-ready. | G35: Required. Choose QTY | H35: ea. | I35: =_xlfn.XLOOKUP($A35,'Proposal Form Tier 1'!$C:$C,'Proposal Form Tier 1'!$B:$B,0,0) -> 1 | J35: =IF(I35<>0,VLOOKUP('Proposal Form Tier 1'!$B$5,Tiers_list!$A:$BC,MATCH($A35,Tiers_list!$2:$2,0),FALSE)*('Proposal Form Tier 1'!$B$3/10)*(1-'Proposal Form Tier 1'!$B$16-'Proposal Form Tier 1'!$B$14),0) -> 126.5625 | K35: =J35*50% -> 63.28125 | L35: =SUM(M35:O35) -> 1 | M35: =IF($I35>0,+'Proposal Form Tier 1'!$B$8,0) -> 0 | N35: =IF($I35>0,+'Proposal Form Tier 1'!$B$9,0) -> 0 | O35: =IF($I35>0,+'Proposal Form Tier 1'!$B$10,0) -> 1 | P35: =+(J35/(1-'Proposal Form Tier 1'!$B$16-'Proposal Form Tier 1'!$B$14))+(K35/(1-'Proposal Form Tier 1'!$B$16-'Proposal Form Tier 1'!$B$14)) -> 253.125
A36: 200-50060 | B36: ACS Software | C36: ACS Enterprise Mass Programming and Data Collection/Receiving Services | D36: =_xlfn.XLOOKUP(A36,Tiers_list!$2:$2,Tiers_list!$1:$1,,0) -> AFH / Data Collection Service Module | E36: Collect/receive ACS hardware / software status Event Messages, Credential Events, User activity and writes stores them within the ACS SQL DB. | F36: ACS Cloud Enterprise continuously collects and stores every event message and credential read event transmitted by ACS controllers in real time — covering access grants, rejections, alarms, device status updates, login events, and more — into a centralized, searchable audit trail. Operators can view, filter, and export this complete event history at any time, ensuring that the full record of what happened at every entrance, on every device, across every site is always available for security review, incident investigation, or compliance reporting. | G36: Required. Choose Qty | H36: ea. | I36: =_xlfn.XLOOKUP($A36,'Proposal Form Tier 1'!$C:$C,'Proposal Form Tier 1'!$B:$B,0,0) -> 1 | J36: =IF(I36<>0,VLOOKUP('Proposal Form Tier 1'!$B$5,Tiers_list!$A:$BC,MATCH($A36,Tiers_list!$2:$2,0),FALSE)*('Proposal Form Tier 1'!$B$3/10)*(1-'Proposal Form Tier 1'!$B$16-'Proposal Form Tier 1'!$B$14),0) -> 126.5625 | K36: =J36*50% -> 63.28125 | L36: =SUM(M36:O36) -> 1 | M36: =IF($I36>0,+'Proposal Form Tier 1'!$B$8,0) -> 0 | N36: =IF($I36>0,+'Proposal Form Tier 1'!$B$9,0) -> 0 | O36: =IF($I36>0,+'Proposal Form Tier 1'!$B$10,0) -> 1 | P36: =+(J36/(1-'Proposal Form Tier 1'!$B$16-'Proposal Form Tier 1'!$B$14))+(K36/(1-'Proposal Form Tier 1'!$B$16-'Proposal Form Tier 1'!$B$14)) -> 253.125
A37: 200-50061 | B37: ACS Software | C37: ACS Enterprise Mass Programming and Data Collection/Receiving Services | D37: =_xlfn.XLOOKUP(A37,Tiers_list!$2:$2,Tiers_list!$1:$1,,0) -> Remote ACS Hardware firmware updates Module | E37: Remote ACS controller and MMR 2.0 reader firmware updates | F37: Administrators can remotely update the firmware of ACS controllers and MMR 2.0 readers across all sites without dispatching technicians — selecting the target firmware version, scoping the update to specific devices or territories, and scheduling execution during off-peak hours through the job scheduler. Firmware files go through an approval process before deployment, update progress is tracked in real time with automatic retry on failure, and all activity is logged — ensuring that every device in the estate stays current, secure, and operating on validated software. | G37: Required. Choose Qty | H37: ea. | I37: =_xlfn.XLOOKUP($A37,'Proposal Form Tier 1'!$C:$C,'Proposal Form Tier 1'!$B:$B,0,0) -> 1 | J37: =IF(I37<>0,VLOOKUP('Proposal Form Tier 1'!$B$5,Tiers_list!$A:$BC,MATCH($A37,Tiers_list!$2:$2,0),FALSE)*('Proposal Form Tier 1'!$B$3/10)*(1-'Proposal Form Tier 1'!$B$16-'Proposal Form Tier 1'!$B$14),0) -> 168.75 | K37: =J37*50% -> 84.375 | L37: =SUM(M37:O37) -> 1 | M37: =IF($I37>0,+'Proposal Form Tier 1'!$B$8,0) -> 0 | N37: =IF($I37>0,+'Proposal Form Tier 1'!$B$9,0) -> 0 | O37: =IF($I37>0,+'Proposal Form Tier 1'!$B$10,0) -> 1 | P37: =+(J37/(1-'Proposal Form Tier 1'!$B$16-'Proposal Form Tier 1'!$B$14))+(K37/(1-'Proposal Form Tier 1'!$B$16-'Proposal Form Tier 1'!$B$14)) -> 337.5
A38: 200-50062 | B38: ACS Software | C38: ACS Enterprise Mass Programming and Data Collection/Receiving Services | D38: =_xlfn.XLOOKUP(A38,Tiers_list!$2:$2,Tiers_list!$1:$1,,0) -> Door / Entrance Supervision Configuration Module | E38: Configuration of Door Ajar, Door Opening Excessively during Access and Locked scheduled states. Event message thresholds are configurable for entry and egress supervision frequency.(Requires a Door Contact and Egress device integrated into the ACS controller) | F38: Operators can configure and enforce door behavior rules that detect when a door is left open beyond an acceptable time (Door Ajar) or opened too frequently relative to credential reads — triggering alerts before a minor door issue becomes a security or compliance concern. Threshold values are configurable per reader and per site, default settings can be applied organization-wide, and all configuration changes are logged with full traceability of who set what and when. | G38: Optional | H38: ea. | I38: =_xlfn.XLOOKUP($A38,'Proposal Form Tier 1'!$C:$C,'Proposal Form Tier 1'!$B:$B,0,0) -> 0 | J38: =IF(I38<>0,VLOOKUP('Proposal Form Tier 1'!$B$5,Tiers_list!$A:$BC,MATCH($A38,Tiers_list!$2:$2,0),FALSE)*('Proposal Form Tier 1'!$B$3/10)*(1-'Proposal Form Tier 1'!$B$16-'Proposal Form Tier 1'!$B$14),0) -> 0 | K38: =J38*50% -> 0 | L38: =SUM(M38:O38) -> 0 | M38: =IF($I38>0,+'Proposal Form Tier 1'!$B$8,0) -> 0 | N38: =IF($I38>0,+'Proposal Form Tier 1'!$B$9,0) -> 0 | O38: =IF($I38>0,+'Proposal Form Tier 1'!$B$10,0) -> 0 | P38: =+(J38/(1-'Proposal Form Tier 1'!$B$16-'Proposal Form Tier 1'!$B$14))+(K38/(1-'Proposal Form Tier 1'!$B$16-'Proposal Form Tier 1'!$B$14)) -> 0
A39: 200-50063 | B39: ACS Software | C39: ACS Enterprise Mass Programming and Data Collection/Receiving Services | D39: =_xlfn.XLOOKUP(A39,Tiers_list!$2:$2,Tiers_list!$1:$1,,0) -> ACS Hardware Firmware Version Supervision Module | E39: MMR 2.0 reader and ACS controller approved firmware version and serial number supervision | F39: ACS Cloud Enterprise maintains a live inventory of the approved firmware versions and serial numbers for every controller and reader in the estate, automatically flagging devices that are running outdated or unapproved firmware versions. This gives administrators a continuous, accurate view of firmware compliance across the entire device fleet, supports proactive update planning, and ensures that no device is overlooked during firmware rollouts — eliminating the audit risk of unknown or uncertified firmware running in a live security environment. | G39: Required | H39: ea. | I39: =+'Proposal Form Tier 1'!$B$6 -> 1 | J39: =IF(I39<>0,VLOOKUP('Proposal Form Tier 1'!$B$5,Tiers_list!$A:$BC,MATCH($A39,Tiers_list!$2:$2,0),FALSE)*('Proposal Form Tier 1'!$B$3/10)*(1-'Proposal Form Tier 1'!$B$16-'Proposal Form Tier 1'!$B$14),0) -> 84.375 | K39: =J39*50% -> 42.1875 | L39: =SUM(M39:O39) -> 1 | M39: =IF($I39>0,+'Proposal Form Tier 1'!$B$8,0) -> 0 | N39: =IF($I39>0,+'Proposal Form Tier 1'!$B$9,0) -> 0 | O39: =IF($I39>0,+'Proposal Form Tier 1'!$B$10,0) -> 1 | P39: =+(J39/(1-'Proposal Form Tier 1'!$B$16-'Proposal Form Tier 1'!$B$14))+(K39/(1-'Proposal Form Tier 1'!$B$16-'Proposal Form Tier 1'!$B$14)) -> 168.75
A40: 200-50064 | B40: ACS Software | C40: ACS Enterprise Mass Programming and Data Collection/Receiving Services | D40: =_xlfn.XLOOKUP(A40,Tiers_list!$2:$2,Tiers_list!$1:$1,,0) -> ACS Data Retention / Archive Module | E40: Definable ACS data (Credentials read, Event Message, ACS User Activity and hardware configuration history) archive management, reports and archive data history viewer. | F40: ACS Cloud Enterprise enables administrators to define retention policies for all system data — including credential events, configuration history, user activity logs, and hardware records — with automatic archiving and purging that keeps storage costs under control while ensuring the organization meets its regulatory and compliance obligations. Archived data remains accessible during the retention window, all archiving activity is captured in a compliance audit log, and access to archived records is restricted to authorized personnel — giving organizations defensible data governance without manual data management overhead. | G40: Required | H40: ea. | I40: =+'Proposal Form Tier 1'!$B$6 -> 1 | J40: =IF(I40<>0,VLOOKUP('Proposal Form Tier 1'!$B$5,Tiers_list!$A:$BC,MATCH($A40,Tiers_list!$2:$2,0),FALSE)*('Proposal Form Tier 1'!$B$3/10)*(1-'Proposal Form Tier 1'!$B$16-'Proposal Form Tier 1'!$B$14),0) -> 84.375 | K40: =J40*50% -> 42.1875 | L40: =SUM(M40:O40) -> 1 | M40: =IF($I40>0,+'Proposal Form Tier 1'!$B$8,0) -> 0 | N40: =IF($I40>0,+'Proposal Form Tier 1'!$B$9,0) -> 0 | O40: =IF($I40>0,+'Proposal Form Tier 1'!$B$10,0) -> 1 | P40: =+(J40/(1-'Proposal Form Tier 1'!$B$16-'Proposal Form Tier 1'!$B$14))+(K40/(1-'Proposal Form Tier 1'!$B$16-'Proposal Form Tier 1'!$B$14)) -> 168.75
A41: 200-50065 | B41: ACS Software | C41: ACS Enterprise Mass Programming and Data Collection/Receiving Services | D41: =_xlfn.XLOOKUP(A41,Tiers_list!$2:$2,Tiers_list!$1:$1,,0) -> Scheduled ACS Export / Report Distribution Module | E41: Scheduled ACS Export / Report Distribution | F41: Administrators can configure recurring scheduled exports of any ACS report — access event summaries, credential analytics, user activity logs, job results, or configuration histories — and have them automatically delivered by email to defined recipient groups on a daily, weekly, or monthly basis. This eliminates the manual effort of pulling and distributing reports, ensures that managers and auditors receive the information they need without logging into the system, and creates a consistent, documented cadence of operational and compliance reporting. | G41: Required | H41: ea. | I41: =+'Proposal Form Tier 1'!$B$6 -> 1 | J41: =IF(I41<>0,VLOOKUP('Proposal Form Tier 1'!$B$5,Tiers_list!$A:$BC,MATCH($A41,Tiers_list!$2:$2,0),FALSE)*('Proposal Form Tier 1'!$B$3/10)*(1-'Proposal Form Tier 1'!$B$16-'Proposal Form Tier 1'!$B$14),0) -> 84.375 | K41: =J41*50% -> 42.1875 | L41: =SUM(M41:O41) -> 1 | M41: =IF($I41>0,+'Proposal Form Tier 1'!$B$8,0) -> 0 | N41: =IF($I41>0,+'Proposal Form Tier 1'!$B$9,0) -> 0 | O41: =IF($I41>0,+'Proposal Form Tier 1'!$B$10,0) -> 1 | P41: =+(J41/(1-'Proposal Form Tier 1'!$B$16-'Proposal Form Tier 1'!$B$14))+(K41/(1-'Proposal Form Tier 1'!$B$16-'Proposal Form Tier 1'!$B$14)) -> 168.75
A42: 200-50066 | B42: ACS Software | C42: ACS Enterprise Mass Programming and Data Collection/Receiving Services | D42: =_xlfn.XLOOKUP(A42,Tiers_list!$2:$2,Tiers_list!$1:$1,,0) -> Duplicate Credential Read within ACS Ecosystem Supervision Module | E42: Duplicate Credential Read within ACS Ecosystem Supervision Module | F42: ACS Cloud Enterprise monitors for instances where the same credential is read at multiple entrances within the same site in a timeframe that makes simultaneous physical presence impossible, automatically flagging potential credential cloning, sharing, or misuse before it escalates into a security incident. When a duplicate pattern is detected, the system generates an alert and logs the event for investigation, giving security teams the real-time intelligence they need to identify and respond to credential abuse across their entire access control estate. | G42: Required | H42: ea. | I42: =+'Proposal Form Tier 1'!$B$6 -> 1 | J42: =IF(I42<>0,VLOOKUP('Proposal Form Tier 1'!$B$5,Tiers_list!$A:$BC,MATCH($A42,Tiers_list!$2:$2,0),FALSE)*('Proposal Form Tier 1'!$B$3/10)*(1-'Proposal Form Tier 1'!$B$16-'Proposal Form Tier 1'!$B$14),0) -> 126.5625 | K42: =J42*50% -> 63.28125 | L42: =SUM(M42:O42) -> 1 | M42: =IF($I42>0,+'Proposal Form Tier 1'!$B$8,0) -> 0 | N42: =IF($I42>0,+'Proposal Form Tier 1'!$B$9,0) -> 0 | O42: =IF($I42>0,+'Proposal Form Tier 1'!$B$10,0) -> 1 | P42: =+(J42/(1-'Proposal Form Tier 1'!$B$16-'Proposal Form Tier 1'!$B$14))+(K42/(1-'Proposal Form Tier 1'!$B$16-'Proposal Form Tier 1'!$B$14)) -> 253.125
C43: ACS Enterprise Mass Programming and Data Collection/Receiving Services Total | I43: =SUBTOTAL(9,I35:I42) -> 7 | J43: =SUBTOTAL(9,J35:J42) -> 801.5625 | K43: =SUBTOTAL(9,K35:K42) -> 400.78125 | L43: =SUBTOTAL(9,L35:L42) -> 7 | M43: =SUBTOTAL(9,M35:M42) -> 0 | N43: =SUBTOTAL(9,N35:N42) -> 0 | O43: =SUBTOTAL(9,O35:O42) -> 7 | P43: =SUBTOTAL(9,P35:P42) -> 1603.125
A44: 200-50067 | B44: ACS Software | C44: Annual ACS Cloud Enterprise Ecosystem, Hardware, Facility Sensors, Reader Monitoring UI features | D44: =_xlfn.XLOOKUP(A44,Tiers_list!$2:$2,Tiers_list!$1:$1,,0) -> ACS Facility Supervision Module | E44: Duplicate Credentials read at each location and the distance between locations where the Credential was read via Google Maps integration calculating and displaying distances between locations where the duplicate credentials were read. | F44: ACS Cloud Enterprise detects when the same credential is used at geographically distant locations within a time window that makes legitimate travel between them physically implausible — a strong indicator of credential cloning or sharing — and immediately alerts the security team for investigation. By continuously analyzing credential events across the full site network and correlating them by distance and timing, organizations gain a powerful, automated early-warning capability that human operators monitoring individual sites could never replicate at scale. | G44: Required | H44: ea. | I44: =+'Proposal Form Tier 1'!$B$6 -> 1 | J44: =IF(I44<>0,VLOOKUP('Proposal Form Tier 1'!$B$5,Tiers_list!$A:$BC,MATCH($A44,Tiers_list!$2:$2,0),FALSE)*('Proposal Form Tier 1'!$B$3/10)*(1-'Proposal Form Tier 1'!$B$16-'Proposal Form Tier 1'!$B$14),0) -> 84.375 | K44: =J44*50% -> 42.1875 | L44: =SUM(M44:O44) -> 1 | M44: =IF($I44>0,+'Proposal Form Tier 1'!$B$8,0) -> 0 | N44: =IF($I44>0,+'Proposal Form Tier 1'!$B$9,0) -> 0 | O44: =IF($I44>0,+'Proposal Form Tier 1'!$B$10,0) -> 1 | P44: =+(J44/(1-'Proposal Form Tier 1'!$B$16-'Proposal Form Tier 1'!$B$14))+(K44/(1-'Proposal Form Tier 1'!$B$16-'Proposal Form Tier 1'!$B$14)) -> 168.75
A45: 200-50068 | B45: ACS Software | C45: Annual ACS Cloud Enterprise Ecosystem, Hardware, Facility Sensors, Reader Monitoring UI features | D45: =_xlfn.XLOOKUP(A45,Tiers_list!$2:$2,Tiers_list!$1:$1,,0) -> ACS Controller Software Integrations DB Ecosystem Supervision Module | E45: Light Sensor monitoring, Presence, Loitering and Single Access Detection, Door Ajar, Door Unsecure and Door opening excessively and Customer Can't Enter or Exit a facility | F45: ACS Cloud Enterprise monitors a rich set of facility sensor inputs — including light sensors, presence detection, loitering patterns, single-access violations, and door ajar conditions — turning raw hardware signals into actionable operational intelligence that security teams can act on in real time. Configurable thresholds, automated alerts, and event correlation with access control activity give operators a comprehensive picture of what is happening at every entrance and in every monitored space, enabling faster response to anomalies and stronger overall facility security posture. | G45: Optional | H45: ea. | I45: =_xlfn.XLOOKUP($A45,'Proposal Form Tier 1'!$C:$C,'Proposal Form Tier 1'!$B:$B,0,0) -> 0 | J45: =IF(I45<>0,VLOOKUP('Proposal Form Tier 1'!$B$5,Tiers_list!$A:$BC,MATCH($A45,Tiers_list!$2:$2,0),FALSE)*('Proposal Form Tier 1'!$B$3/10)*(1-'Proposal Form Tier 1'!$B$16-'Proposal Form Tier 1'!$B$14),0) -> 0 | K45: =J45*50% -> 0 | L45: =SUM(M45:O45) -> 0 | M45: =IF($I45>0,+'Proposal Form Tier 1'!$B$8,0) -> 0 | N45: =IF($I45>0,+'Proposal Form Tier 1'!$B$9,0) -> 0 | O45: =IF($I45>0,+'Proposal Form Tier 1'!$B$10,0) -> 0 | P45: =+(J45/(1-'Proposal Form Tier 1'!$B$16-'Proposal Form Tier 1'!$B$14))+(K45/(1-'Proposal Form Tier 1'!$B$16-'Proposal Form Tier 1'!$B$14)) -> 0
A46: 200-50069 | B46: ACS Software | C46: Annual ACS Cloud Enterprise Ecosystem, Hardware, Facility Sensors, Reader Monitoring UI features | D46: =_xlfn.XLOOKUP(A46,Tiers_list!$2:$2,Tiers_list!$1:$1,,0) -> Reader Credentials Accepted and Rejected Supervision Module | E46: ACS Enterprise software ecosystem Monitoring Service of database connectivity, interservice/API communication, service instance availability and server hardware resources | F46: ACS Cloud Enterprise includes a dedicated ecosystem monitoring service that continuously tracks the health and availability of the platform's own infrastructure — including microservice status, database connectivity, network performance, and integration endpoints — providing administrators with centralized visibility into the operational integrity of the entire system. When a service component degrades or goes offline, the monitoring service triggers alerts, logs the incident, and supports capacity planning and automated remediation, ensuring that the platform responsible for physical security is itself subject to the same standards of reliability and oversight it enforces for the facilities it protects. | G46: Required | H46: ea. | I46: 1 | J46: =IF(I46<>0,VLOOKUP('Proposal Form Tier 1'!$B$5,Tiers_list!$A:$BC,MATCH($A46,Tiers_list!$2:$2,0),FALSE)*('Proposal Form Tier 1'!$B$3/10)*(1-'Proposal Form Tier 1'!$B$16-'Proposal Form Tier 1'!$B$14),0) -> 126.5625 | K46: =J46*50% -> 63.28125 | L46: =SUM(M46:O46) -> 1 | M46: =IF($I46>0,+'Proposal Form Tier 1'!$B$8,0) -> 0 | N46: =IF($I46>0,+'Proposal Form Tier 1'!$B$9,0) -> 0 | O46: =IF($I46>0,+'Proposal Form Tier 1'!$B$10,0) -> 1 | P46: =+(J46/(1-'Proposal Form Tier 1'!$B$16-'Proposal Form Tier 1'!$B$14))+(K46/(1-'Proposal Form Tier 1'!$B$16-'Proposal Form Tier 1'!$B$14)) -> 253.125
A47: 200-50071 | B47: ACS Enterprise Integrations | C47: Annual ACS Cloud Enterprise Ecosystem, Hardware, Facility Sensors, Reader Monitoring UI features | D47: ACS controller Reader Remote Credential Lookup with Local learn Module | E47: Remote lookup of Accepted, Rejected and Suspect Credentials stored on the ACS controller EEPROM with an until date/time for future local Credential lookups. | F47: When a credential is presented at a reader configured for external match validation, ACS Cloud Enterprise forwards the request to a designated external server in real time, retrieves the allow or reject decision, and acts on it immediately — with the response cached at the controller to maintain performance even during brief connectivity interruptions. This enables organizations to maintain centralized, organization-wide credential authority in an external system (such as a financial institution's BIN database) while still leveraging the speed and resilience of local controller enforcement. | G47: Optional | H47: ea. | I47: =_xlfn.XLOOKUP($A47,'Proposal Form Tier 1'!$C:$C,'Proposal Form Tier 1'!$B:$B,0,0) -> 0 | J47: =IF(I47<>0,VLOOKUP('Proposal Form Tier 1'!$B$5,Tiers_list!$A:$BC,MATCH($A47,Tiers_list!$2:$2,0),FALSE)*('Proposal Form Tier 1'!$B$3/10)*(1-'Proposal Form Tier 1'!$B$16-'Proposal Form Tier 1'!$B$14),0) -> 0 | K47: =J47*50% -> 0 | L47: =SUM(M47:O47) -> 0 | M47: =IF($I47>0,+'Proposal Form Tier 1'!$B$8,0) -> 0 | N47: =IF($I47>0,+'Proposal Form Tier 1'!$B$9,0) -> 0 | O47: =IF($I47>0,+'Proposal Form Tier 1'!$B$10,0) -> 0 | P47: =+(J47/(1-'Proposal Form Tier 1'!$B$16-'Proposal Form Tier 1'!$B$14))+(K47/(1-'Proposal Form Tier 1'!$B$16-'Proposal Form Tier 1'!$B$14)) -> 0
A48: 200-50072 | B48: ACS Enterprise Integrations | C48: Annual ACS Cloud Enterprise Ecosystem, Hardware, Facility Sensors, Reader Monitoring UI features | D48: ACS controller Reader Remote Credential Lookup with Local learn Module | E48: Configure reader type, access by Credential holder and by Access Schedule. i.e., HID, Wave Lynx, Elactec, etc. Prox and/or keypad reader, Bio Reader, Wearable Tech NFC, Mobile with NFC card, Bluetooth Local with Bluetooth Cloud, etc. | F48: Operators can configure every reader in the system — defining the credential types accepted (magnetic stripe, NFC, Bluetooth, biometric, and more), assigning the appropriate access schedules, and linking readers to specific user groups — all from a centralized interface without a site visit. This ensures that every entrance behaves exactly as intended, that the right people have access at the right times, and that configuration changes are applied instantly and consistently across all locations. | G48: Optional | H48: ea. | I48: =_xlfn.XLOOKUP($A48,'Proposal Form Tier 1'!$C:$C,'Proposal Form Tier 1'!$B:$B,0,0) -> 0 | J48: =IF(I48<>0,VLOOKUP('Proposal Form Tier 1'!$B$5,Tiers_list!$A:$BC,MATCH($A48,Tiers_list!$2:$2,0),FALSE)*('Proposal Form Tier 1'!$B$3/10)*(1-'Proposal Form Tier 1'!$B$16-'Proposal Form Tier 1'!$B$14),0) -> 0 | K48: =J48*50% -> 0 | L48: =SUM(M48:O48) -> 0 | M48: =IF($I48>0,+'Proposal Form Tier 1'!$B$8,0) -> 0 | N48: =IF($I48>0,+'Proposal Form Tier 1'!$B$9,0) -> 0 | O48: =IF($I48>0,+'Proposal Form Tier 1'!$B$10,0) -> 0 | P48: =+(J48/(1-'Proposal Form Tier 1'!$B$16-'Proposal Form Tier 1'!$B$14))+(K48/(1-'Proposal Form Tier 1'!$B$16-'Proposal Form Tier 1'!$B$14)) -> 0
A49: 200-50073 | B49: ACS Enterprise Integrations | C49: Annual ACS Cloud Enterprise Ecosystem, Hardware, Facility Sensors, Reader Monitoring UI features | D49: Export & Reporting | E49: Adds an Export action to data grids across the Site, Access Point, Login, and Log modules — Sites, Site Tags, Suspect Files, Match Files, User Management, Authorization Resources, Audit Logs, System Logs, Infrastructure Logs, Device Messages, Credential Events, Device Diagnostics Logs, and Service Diagnostics — producing a structured file of the currently displayed dataset. | F49: ACS Cloud Enterprise lets operators download any data grid in the system to a structured file for offline review, compliance reporting, or long-term archiving, without needing direct database access or a separate reporting tool. This turns every grid in the platform into a self-service reporting source, reducing the time security and compliance teams spend assembling audit packages or sharing data with auditors and regulators. | G49: Optional | H49: ea. | I49: =_xlfn.XLOOKUP($A49,'Proposal Form Tier 1'!$C:$C,'Proposal Form Tier 1'!$B:$B,0,0) -> 0 | J49: =IF(I49<>0,VLOOKUP('Proposal Form Tier 1'!$B$5,Tiers_list!$A:$BC,MATCH($A49,Tiers_list!$2:$2,0),FALSE)*('Proposal Form Tier 1'!$B$3/10)*(1-'Proposal Form Tier 1'!$B$16-'Proposal Form Tier 1'!$B$14),0) -> 0 | K49: =J49*50% -> 0 | L49: =SUM(M49:O49) -> 0 | M49: =IF($I49>0,+'Proposal Form Tier 1'!$B$8,0) -> 0 | N49: =IF($I49>0,+'Proposal Form Tier 1'!$B$9,0) -> 0 | O49: =IF($I49>0,+'Proposal Form Tier 1'!$B$10,0) -> 0 | P49: =+(J49/(1-'Proposal Form Tier 1'!$B$16-'Proposal Form Tier 1'!$B$14))+(K49/(1-'Proposal Form Tier 1'!$B$16-'Proposal Form Tier 1'!$B$14)) -> 0
A50: 200-50074 | B50: ACS Enterprise Integrations | C50: Annual ACS Cloud Enterprise Ecosystem, Hardware, Facility Sensors, Reader Monitoring UI features | D50: Bulk Synchronisation ans Scheduling | E50: Adds a Schedule Sync action to Access Point Mgmt configuration grids — Access Point Configuration, Match Configuration, Match File, Suspect File, AP IO Configuration, Controller IO Configuration, Weekly Schedule Management, Holiday Schedule Management, and Controller config-mismatch jobs — allowing a configuration push to be queued and applied automatically at a defined date/time rather than immediately. | F50: ACS Cloud Enterprise lets operators schedule configuration pushes to groups of devices for a future date and time instead of applying every change manually and immediately. This allows large rollouts — new schedules, credential lists, or controller settings — to be staged during a maintenance window and propagate automatically across many sites without an operator present at the time of the sync. | G50: Optional | H50: ea. | I50: =_xlfn.XLOOKUP($A50,'Proposal Form Tier 1'!$C:$C,'Proposal Form Tier 1'!$B:$B,0,0) -> 0 | J50: =IF(I50<>0,VLOOKUP('Proposal Form Tier 1'!$B$5,Tiers_list!$A:$BC,MATCH($A50,Tiers_list!$2:$2,0),FALSE)*('Proposal Form Tier 1'!$B$3/10)*(1-'Proposal Form Tier 1'!$B$16-'Proposal Form Tier 1'!$B$14),0) -> 0 | K50: =J50*50% -> 0 | L50: =SUM(M50:O50) -> 0 | M50: =IF($I50>0,+'Proposal Form Tier 1'!$B$8,0) -> 0 | N50: =IF($I50>0,+'Proposal Form Tier 1'!$B$9,0) -> 0 | O50: =IF($I50>0,+'Proposal Form Tier 1'!$B$10,0) -> 0 | P50: =+(J50/(1-'Proposal Form Tier 1'!$B$16-'Proposal Form Tier 1'!$B$14))+(K50/(1-'Proposal Form Tier 1'!$B$16-'Proposal Form Tier 1'!$B$14)) -> 0
A51: 200-50075 | B51: ACS Enterprise Integrations | C51: Annual ACS Cloud Enterprise Ecosystem, Hardware, Facility Sensors, Reader Monitoring UI features | D51: Clone & Templates | E51: Adds a Clone action to Access Point Mgmt and Login Mgmt configuration entities — Match Configuration, Match File, AP IO Configuration, Controller IO Configuration, Weekly Schedule Management, Holiday Schedule Management, and Authorization Resources — creating a duplicate of an existing configuration record that can be assigned to a new site, controller, or user as a starting point. | F51: ACS Cloud Enterprise lets operators copy an existing, already-tested configuration as a template instead of building every new site, controller, or access profile from scratch. This shortens rollout time for multi-site deployments and reduces configuration drift, since new entities start from a known-good baseline rather than manual re-entry. | G51: Optional | H51: ea. | I51: =_xlfn.XLOOKUP($A51,'Proposal Form Tier 1'!$C:$C,'Proposal Form Tier 1'!$B:$B,0,0) -> 0 | J51: =IF(I51<>0,VLOOKUP('Proposal Form Tier 1'!$B$5,Tiers_list!$A:$BC,MATCH($A51,Tiers_list!$2:$2,0),FALSE)*('Proposal Form Tier 1'!$B$3/10)*(1-'Proposal Form Tier 1'!$B$16-'Proposal Form Tier 1'!$B$14),0) -> 0 | K51: =J51*50% -> 0 | L51: =SUM(M51:O51) -> 0 | M51: =IF($I51>0,+'Proposal Form Tier 1'!$B$8,0) -> 0 | N51: =IF($I51>0,+'Proposal Form Tier 1'!$B$9,0) -> 0 | O51: =IF($I51>0,+'Proposal Form Tier 1'!$B$10,0) -> 0 | P51: =+(J51/(1-'Proposal Form Tier 1'!$B$16-'Proposal Form Tier 1'!$B$14))+(K51/(1-'Proposal Form Tier 1'!$B$16-'Proposal Form Tier 1'!$B$14)) -> 0
A52: 200-50076 | B52: ACS Enterprise Integrations | C52: Annual ACS Cloud Enterprise Ecosystem, Hardware, Facility Sensors, Reader Monitoring UI features | D52: Merge Operations | E52: Adds a Merge action to the Access Point Mgmt Match File grid, combining two or more existing match files into a single consolidated file rather than requiring operators to manage them separately. | F52: ACS Cloud Enterprise lets operators consolidate multiple match file datasets — for example, lists built independently at different sites — into one unified file for centralized credential management. This removes the manual reconciliation work of comparing and merging credential lists by hand, reducing the risk of duplicate or conflicting entries across sites. | G52: Optional | H52: ea. | I52: =_xlfn.XLOOKUP($A52,'Proposal Form Tier 1'!$C:$C,'Proposal Form Tier 1'!$B:$B,0,0) -> 0 | J52: =IF(I52<>0,VLOOKUP('Proposal Form Tier 1'!$B$5,Tiers_list!$A:$BC,MATCH($A52,Tiers_list!$2:$2,0),FALSE)*('Proposal Form Tier 1'!$B$3/10)*(1-'Proposal Form Tier 1'!$B$16-'Proposal Form Tier 1'!$B$14),0) -> 0 | K52: =J52*50% -> 0 | L52: =SUM(M52:O52) -> 0 | M52: =IF($I52>0,+'Proposal Form Tier 1'!$B$8,0) -> 0 | N52: =IF($I52>0,+'Proposal Form Tier 1'!$B$9,0) -> 0 | O52: =IF($I52>0,+'Proposal Form Tier 1'!$B$10,0) -> 0 | P52: =+(J52/(1-'Proposal Form Tier 1'!$B$16-'Proposal Form Tier 1'!$B$14))+(K52/(1-'Proposal Form Tier 1'!$B$16-'Proposal Form Tier 1'!$B$14)) -> 0
A53: 200-50077 | B53: ACS Enterprise Integrations | C53: Annual ACS Cloud Enterprise Ecosystem, Hardware, Facility Sensors, Reader Monitoring UI features | D53: Advanced User Management | E53: Adds a Bulk Assign action to Authorization Resources, allowing an access profile to be applied to multiple users in a single operation, plus a View Profile Permissions screen that lists the full set of resource permissions granted to any role. | F53: ACS Cloud Enterprise lets administrators assign an access profile to many users at once instead of updating permissions one user at a time, and inspect exactly what any given role can see or do across the system. This speeds up onboarding for large teams and gives administrators a clear, auditable view of permission scope when responding to access reviews or compliance questions. | G53: Optional | H53: ea. | I53: =_xlfn.XLOOKUP($A53,'Proposal Form Tier 1'!$C:$C,'Proposal Form Tier 1'!$B:$B,0,0) -> 0 | J53: =IF(I53<>0,VLOOKUP('Proposal Form Tier 1'!$B$5,Tiers_list!$A:$BC,MATCH($A53,Tiers_list!$2:$2,0),FALSE)*('Proposal Form Tier 1'!$B$3/10)*(1-'Proposal Form Tier 1'!$B$16-'Proposal Form Tier 1'!$B$14),0) -> 0 | K53: =J53*50% -> 0 | L53: =SUM(M53:O53) -> 0 | M53: =IF($I53>0,+'Proposal Form Tier 1'!$B$8,0) -> 0 | N53: =IF($I53>0,+'Proposal Form Tier 1'!$B$9,0) -> 0 | O53: =IF($I53>0,+'Proposal Form Tier 1'!$B$10,0) -> 0 | P53: =+(J53/(1-'Proposal Form Tier 1'!$B$16-'Proposal Form Tier 1'!$B$14))+(K53/(1-'Proposal Form Tier 1'!$B$16-'Proposal Form Tier 1'!$B$14)) -> 0
A54: 200-50078 | B54: ACS Enterprise Integrations | C54: Annual ACS Cloud Enterprise Ecosystem, Hardware, Facility Sensors, Reader Monitoring UI features | D54: Advanced Log Filtering | E54: Adds a Filter action to every Log Mgmt grid — Audit Logs, System Logs, Infrastructure Logs, Device Messages, Credential Events, Device Diagnostics Logs, and Service Diagnostics — enabling operators to narrow large result sets by field-level criteria such as date range, device, user, or event type. | F54: ACS Cloud Enterprise lets operators apply granular filters to log and event grids to pinpoint specific records across datasets that can span millions of rows, instead of scrolling through unfiltered results. This significantly reduces the time spent during incident investigations, audits, and troubleshooting, where finding the relevant handful of events quickly is critical. | G54: Optional | H54: ea. | I54: =_xlfn.XLOOKUP($A54,'Proposal Form Tier 1'!$C:$C,'Proposal Form Tier 1'!$B:$B,0,0) -> 0 | J54: =IF(I54<>0,VLOOKUP('Proposal Form Tier 1'!$B$5,Tiers_list!$A:$BC,MATCH($A54,Tiers_list!$2:$2,0),FALSE)*('Proposal Form Tier 1'!$B$3/10)*(1-'Proposal Form Tier 1'!$B$16-'Proposal Form Tier 1'!$B$14),0) -> 0 | K54: =J54*50% -> 0 | L54: =SUM(M54:O54) -> 0 | M54: =IF($I54>0,+'Proposal Form Tier 1'!$B$8,0) -> 0 | N54: =IF($I54>0,+'Proposal Form Tier 1'!$B$9,0) -> 0 | O54: =IF($I54>0,+'Proposal Form Tier 1'!$B$10,0) -> 0 | P54: =+(J54/(1-'Proposal Form Tier 1'!$B$16-'Proposal Form Tier 1'!$B$14))+(K54/(1-'Proposal Form Tier 1'!$B$16-'Proposal Form Tier 1'!$B$14)) -> 0
A55: 200-50079 | B55: ACS Enterprise Integrations | C55: Annual ACS Cloud Enterprise Ecosystem, Hardware, Facility Sensors, Reader Monitoring UI features | D55: Notification & Alerts | E55: Adds Notification Preference, Notification Group, and Scheduler Notification Preference screens to Job Scheduler, allowing operators to define recipient groups and enable or disable email alerts for scheduled job outcomes and system events. | F55: ACS Cloud Enterprise lets operators configure who receives email notifications for scheduled job events and system alerts, and group recipients so the right team is notified automatically when something needs attention. This keeps administrators and stakeholders informed of job successes, failures, and system conditions without requiring them to actively monitor the platform. | G55: Optional | H55: ea. | I55: =_xlfn.XLOOKUP($A55,'Proposal Form Tier 1'!$C:$C,'Proposal Form Tier 1'!$B:$B,0,0) -> 0 | J55: =IF(I55<>0,VLOOKUP('Proposal Form Tier 1'!$B$5,Tiers_list!$A:$BC,MATCH($A55,Tiers_list!$2:$2,0),FALSE)*('Proposal Form Tier 1'!$B$3/10)*(1-'Proposal Form Tier 1'!$B$16-'Proposal Form Tier 1'!$B$14),0) -> 0 | K55: =J55*50% -> 0 | L55: =SUM(M55:O55) -> 0 | M55: =IF($I55>0,+'Proposal Form Tier 1'!$B$8,0) -> 0 | N55: =IF($I55>0,+'Proposal Form Tier 1'!$B$9,0) -> 0 | O55: =IF($I55>0,+'Proposal Form Tier 1'!$B$10,0) -> 0 | P55: =+(J55/(1-'Proposal Form Tier 1'!$B$16-'Proposal Form Tier 1'!$B$14))+(K55/(1-'Proposal Form Tier 1'!$B$16-'Proposal Form Tier 1'!$B$14)) -> 0
C56: Annual ACS Cloud Enterprise Ecosystem, Hardware, Facility Sensors, Reader Monitoring UI features Total | I56: =SUBTOTAL(9,I44:I55) -> 2 | J56: =SUBTOTAL(9,J44:J55) -> 210.9375 | K56: =SUBTOTAL(9,K44:K55) -> 105.46875 | L56: =SUBTOTAL(9,L44:L55) -> 2 | M56: =SUBTOTAL(9,M44:M55) -> 0 | N56: =SUBTOTAL(9,N44:N55) -> 0 | O56: =SUBTOTAL(9,O44:O55) -> 2 | P56: =SUBTOTAL(9,P44:P55) -> 421.875
C57: Grand Total | I57: =SUBTOTAL(9,I2:I55) -> 19 | J57: =SUBTOTAL(9,J2:J55) -> 4260.9375 | K57: =SUBTOTAL(9,K2:K55) -> 2130.4688 | L57: =SUBTOTAL(9,L2:L55) -> 19 | M57: =SUBTOTAL(9,M2:M55) -> 0 | N57: =SUBTOTAL(9,N2:N55) -> 0 | O57: =SUBTOTAL(9,O2:O55) -> 19 | P57: =SUBTOTAL(9,P2:P55) -> 8521.875
A60: Product # | B60: Product Tree | C60: Category | G60: Feature Type | H60: UoM | I60: Qty | J60: Integrator Tier Price | P60: MSRP Total
A61: YEAR-ACS-RTS | B61: ACS Software | C61: Annual 24/7 ACS Enterprise software suite Telephone Support | E61: Annual 24/7 ACS Enterprise software suite Telephone Support | G61: Optional | I61: =_xlfn.XLOOKUP($A61,'Proposal Form Tier 1'!$C:$C,'Proposal Form Tier 1'!$B:$B,0,0) -> 1 | J61: =VLOOKUP('Proposal Form Tier 1'!$B$5,Tiers_list!$A:$AO,MATCH($A61,Tiers_list!$2:$2,0),FALSE)*(I61*(1-'Proposal Form Tier 1'!$B$14-'Proposal Form Tier 1'!$B$13)) -> 5000 | P61: =+(J61/(1-'Proposal Form Tier 1'!$B$16-'Proposal Form Tier 1'!$B$14))+(K61/(1-'Proposal Form Tier 1'!$B$16-'Proposal Form Tier 1'!$B$14)) -> 6666.6667
A62: 1000-30054 | B62: ACS Software | C62: Annual Full Day Remote ACS Training ten (10) hours (Draw down in two (2) hour prescheduled increments | E62: Annual Full Day Remote ACS Training ten (10) hours (Draw down in two (2) hour prescheduled increments | G62: Required. Choose Qty of 10 hours slots | H62: 10 hours | I62: =_xlfn.XLOOKUP($A62,'Proposal Form Tier 1'!$C:$C,'Proposal Form Tier 1'!$B:$B,0,0) -> 1 | J62: =VLOOKUP('Proposal Form Tier 1'!$B$5,Tiers_list!$A:$AT,MATCH($A62,Tiers_list!$2:$2,0),FALSE)*(I62*(1-'Proposal Form Tier 1'!$B$14-'Proposal Form Tier 1'!$B$13)) -> 2500 | P62: =+(J62/(1-'Proposal Form Tier 1'!$B$16-'Proposal Form Tier 1'!$B$14))+(K62/(1-'Proposal Form Tier 1'!$B$16-'Proposal Form Tier 1'!$B$14)) -> 3333.3333
A63: 200-50070 | B63: ACS Software | C63: ACS TLS 1.2/1.3 Encryption Annual Support Fee | E63: ACS TLS 1.2/1.3 PCB Encryption Annual Support Fee | G63: Optional | I63: =_xlfn.XLOOKUP($A63,'Proposal Form Tier 1'!$C:$C,'Proposal Form Tier 1'!$B:$B,0,0) -> 9 | J63: =VLOOKUP('Proposal Form Tier 1'!$B$5,Tiers_list!$A:$AO,MATCH($A63,Tiers_list!$2:$2,0),FALSE)*'Proposal Form Tier 1'!B26 -> 135 | P63: =+(J63/(1-'Proposal Form Tier 1'!$B$16-'Proposal Form Tier 1'!$B$14))+(K63/(1-'Proposal Form Tier 1'!$B$16-'Proposal Form Tier 1'!$B$14)) -> 180
A64: 200-50007-NTS | B64: ACS Software | C64: Annual Tech Software | E64: ACS Enterprise software - Tech Software License - Annual Software Assurance | G64: Optional | I64: =_xlfn.XLOOKUP($A64,'Proposal Form Tier 1'!$C:$C,'Proposal Form Tier 1'!$B:$B,0,0) -> 0 | J64: =VLOOKUP('Proposal Form Tier 1'!$B$5,Tiers_list!$A:$AO,MATCH($A64,Tiers_list!$2:$2,0),FALSE)*I64 -> 0 | P64: =+(J64/(1-'Proposal Form Tier 1'!$B$16-'Proposal Form Tier 1'!$B$14))+(K64/(1-'Proposal Form Tier 1'!$B$16-'Proposal Form Tier 1'!$B$14)) -> 0
A65: 200-50040 | B65: ACS Software | C65: ACS Enterprise software suite Silent Installer Cloud Automatic Instance Key Activation and Term Management | E65: Single click of an installation Icon/.exe for all ACS Enterprise Micro Services and UI(s) for Private Cloud / Parabit Public Cloud and On Prem versions and SQL database with automatic Parabit Cloud software license key issuance, cloud key exchange validation and license expiration notice management | G65: Included | H65: ea. | I65: =_xlfn.XLOOKUP($A65,'Proposal Form Tier 1'!$C:$C,'Proposal Form Tier 1'!$B:$B,0,0) -> 1 | J65: =IF(I65<>0,VLOOKUP('Proposal Form Tier 1'!$B$5,Tiers_list!$A:$BC,MATCH($A65,Tiers_list!$2:$2,0),FALSE)*('Proposal Form Tier 1'!$B$3/10)*(1-'Proposal Form Tier 1'!$B$16-'Proposal Form Tier 1'!$B$14),0) -> 0 | P65: =+(J65/(1-'Proposal Form Tier 1'!$B$16-'Proposal Form Tier 1'!$B$14))+(K65/(1-'Proposal Form Tier 1'!$B$16-'Proposal Form Tier 1'!$B$14)) -> 0
A66: 200-50041 | B66: ACS Software | C66: ACS Enterprise software suite Silent Installer Cloud Automatic Instance Key Activation and Term Management | E66: Cloud Key DA / Microservice(s) and Parabit internal UI Manages Cloud DB of PO's received, ACS software instance keys ordered per Tier and Tech software license and new release and license term approaching notifier. | G66: Included | H66: ea. | I66: =_xlfn.XLOOKUP($A66,'Proposal Form Tier 1'!$C:$C,'Proposal Form Tier 1'!$B:$B,0,0) -> 1 | J66: =IF(I66<>0,VLOOKUP('Proposal Form Tier 1'!$B$5,Tiers_list!$A:$BC,MATCH($A66,Tiers_list!$2:$2,0),FALSE)*('Proposal Form Tier 1'!$B$3/10)*(1-'Proposal Form Tier 1'!$B$16-'Proposal Form Tier 1'!$B$14),0) -> 0 | P66: =+(J66/(1-'Proposal Form Tier 1'!$B$16-'Proposal Form Tier 1'!$B$14))+(K66/(1-'Proposal Form Tier 1'!$B$16-'Proposal Form Tier 1'!$B$14)) -> 0
I67: Subtotal Annual Support, Encryption and Technician Software Fee | J67: =SUM(J61:J66) -> 7635 | P67: =SUM(P61:P66) -> 10180
I69: Total Annual ACS Cloud Enterprise Software and Annual Support, Encryption, and Technician Software Fees | J69: =+J67+J57 -> 11895.938 | K69: =+K57 -> 2130.4688 | L69: =SUM(J69:K69) -> 14026.406 | P69: =+P67+P57 -> 18701.875
A73: Product # | B73: Product Tree | C73: Category | D73: Prod # Description | E73: One-Time New ACS Enterprise Private Cloud/Parabit ACSaaS/On-Prem Software Features and Professional Services | G73: Feature Type | H73: UoM | I73: MSRP ea. / Tier Price | J73: Integrator Discount % | K73: Integrator Tier Price | L73: Quantity | M73: MSRP Total | N73: Integrator Total
A74: 1000-30053 | B74: ACS Software | C74: ACS OSDP TLS Enterprise software Installation Support | D74: =_xlfn.XLOOKUP(A74,Tiers_list!$2:$2,Tiers_list!$1:$1,,0) -> Remote ACS Software Install Support | E74: ACS/MMR Cloud/On-Prem Software Installation Per Instance support | G74: Required. Choose Qty | H74: ea. | I74: =IF('Proposal Form Tier 1'!$B$5<>"Tier - 1 - 10",VLOOKUP('Proposal Form Tier 1'!$B$5,Tiers_list!$A:$AT,MATCH($A74,Tiers_list!$2:$2,0),FALSE),VLOOKUP('Proposal Form Tier 1'!$B$5,Tiers_list!$A:$AT,MATCH($A74,Tiers_list!$2:$2,0),FALSE)) -> 250 | J74: =+'Proposal Form Tier 1'!$B$16+'Proposal Form Tier 1'!$B$14 -> 0.25 | K74: =+I74*(1-J74) -> 187.5 | L74: =SUBTOTAL(9,I2:I55)+SUBTOTAL(9,L2:L55) -> 38 | M74: =+L74*I74 -> 9500 | N74: =+L74*K74 -> 7125
A75: 200-50007-KT | B75: ACS Hardware | C75: ACS Tech Enterprise License Diagnostic/Programming Hardware | D75: =_xlfn.XLOOKUP(A75,Tiers_list!$2:$2,Tiers_list!$1:$1,,0) -> ACS Enterprise - Hardware - Controller Firmware Programmer KIT - No license Provided. | E75: ACS Enterprise - Hardware - Controller Firmware Programmer KIT - No license Provided. | G75: Required. Choose Qty | H75: ea. | I75: =IF('Proposal Form Tier 1'!$B$5<>"Tier - 1 - 10",VLOOKUP('Proposal Form Tier 1'!$B$5,Tiers_list!$A:$AT,MATCH($A75,Tiers_list!$2:$2,0),FALSE),VLOOKUP('Proposal Form Tier 1'!$B$5,Tiers_list!$A:$AT,MATCH($A75,Tiers_list!$2:$2,0),FALSE)) -> 926 | J75: =+'Proposal Form Tier 1'!$B$16+'Proposal Form Tier 1'!$B$14 -> 0.25 | K75: =+I75*(1-J75) -> 694.5 | L75: =_xlfn.XLOOKUP($A75,'Proposal Form Tier 1'!$C:$C,'Proposal Form Tier 1'!$B:$B,0,0) -> 0 | M75: =+L75*I75 -> 0 | N75: =+L75*K75 -> 0
A76: 200-10115-PCBA | B76: ACS Hardware | C76: ACS TLS 1.2/1.3 Crypto PCB | D76: =_xlfn.XLOOKUP(A76,Tiers_list!$2:$2,Tiers_list!$1:$1,,0) -> TLS 1.2/1.3 PCB | E76: ACS TLS 1.2/1.3 PCB Crypto Board | G76: Required. Choose Qty | H76: ea. | I76: =IF('Proposal Form Tier 1'!$B$5<>"Tier - 1 - 10",VLOOKUP('Proposal Form Tier 1'!$B$5,Tiers_list!$A:$AT,MATCH($A76,Tiers_list!$2:$2,0),FALSE),VLOOKUP('Proposal Form Tier 1'!$B$5,Tiers_list!$A:$AT,MATCH($A76,Tiers_list!$2:$2,0),FALSE)) -> 389 | J76: =+'Proposal Form Tier 1'!$B$16+'Proposal Form Tier 1'!$B$14 -> 0.25 | K76: =+I76*(1-J76) -> 291.75 | L76: =_xlfn.XLOOKUP($A76,'Proposal Form Tier 1'!$C:$C,'Proposal Form Tier 1'!$B:$B,0,0) -> 9 | M76: =+L76*I76 -> 3501 | N76: =+L76*K76 -> 2625.75
E77: Subtotal : One-Time New ACS Enterprise Private Cloud/Parabit ACSaaS/On-Prem Software Features and Professional Services | M77: =SUM(M74:M76) -> 13001 | N77: =SUM(N74:N76) -> 9750.75
E79: One-Time Onsite Services
A80: 1000-30052 | B80: ACS Hardware | C80: Installation and Project Management Labor support for ACS TLS 1.2/1.3 Crypto PCB | D80: =_xlfn.XLOOKUP(A80,Tiers_list!$2:$2,Tiers_list!$1:$1,,0) -> Labor - Trip Charge - Non-Union - On-Site Tech Labor Standard Weekday Business Hours Travel / Service Rate (M-F 09:00-17:00) | E80: Trip Charge, Installation and PM Labor | G80: Required. Choose Qty | H80: ea. | I80: =IF('Proposal Form Tier 1'!$B$5<>"Tier - 1 - 10",VLOOKUP('Proposal Form Tier 1'!$B$5,Tiers_list!$A:$AT,MATCH($A80,Tiers_list!$2:$2,0),FALSE),VLOOKUP('Proposal Form Tier 1'!$B$5,Tiers_list!$A:$AT,MATCH($A80,Tiers_list!$2:$2,0),FALSE)) -> 225 | J80: =+'Proposal Form Tier 1'!$B$16+'Proposal Form Tier 1'!$B$14 -> 0.25 | K80: =+I80*(1-J80) -> 168.75 | L80: =_xlfn.XLOOKUP($A80,'Proposal Form Tier 1'!$C:$C,'Proposal Form Tier 1'!$B:$B,0,0) -> 0 | M80: =+L80*I80 -> 0 | N80: =+L80*K80 -> 0
A81: 1000-20000 | B81: ACS Hardware | C81: Installation and Project Management Labor support for ACS TLS 1.2/1.3 Crypto PCB | D81: =_xlfn.XLOOKUP(A81,Tiers_list!$2:$2,Tiers_list!$1:$1,,0) -> Labor - Non-Union - On-Site Tech Labor Standard Weekday Business Hours Travel / Service Rate (M-F 09:00-17:00) 1st Hour On-Site Minimum Invoice. Additional time invoiced in fifteen (15) minute increments | E81: On-Site/Remote Low Voltage/Mechanical Tech Weekday Business Hours | G81: Required. Choose Qty | H81: ea. | I81: =IF('Proposal Form Tier 1'!$B$5<>"Tier - 1 - 10",VLOOKUP('Proposal Form Tier 1'!$B$5,Tiers_list!$A:$AT,MATCH($A81,Tiers_list!$2:$2,0),FALSE),VLOOKUP('Proposal Form Tier 1'!$B$5,Tiers_list!$A:$AT,MATCH($A81,Tiers_list!$2:$2,0),FALSE)) -> 190 | J81: =+'Proposal Form Tier 1'!$B$16+'Proposal Form Tier 1'!$B$14 -> 0.25 | K81: =+I81*(1-J81) -> 142.5 | L81: =_xlfn.XLOOKUP($A81,'Proposal Form Tier 1'!$C:$C,'Proposal Form Tier 1'!$B:$B,0,0) -> 0 | M81: =+L81*I81 -> 0 | N81: =+L81*K81 -> 0
A82: 1000-30045 | B82: ACS Hardware | C82: Installation and Project Management Labor support for ACS TLS 1.2/1.3 Crypto PCB | D82: =_xlfn.XLOOKUP(A82,Tiers_list!$2:$2,Tiers_list!$1:$1,,0) -> Labor - Project Management - Weekday Business Hours (M-F 09:00-17:00) | E82: Project Management | G82: Required. Choose Qty | H82: ea. | I82: =IF('Proposal Form Tier 1'!$B$5<>"Tier - 1 - 10",VLOOKUP('Proposal Form Tier 1'!$B$5,Tiers_list!$A:$AT,MATCH($A82,Tiers_list!$2:$2,0),FALSE),VLOOKUP('Proposal Form Tier 1'!$B$5,Tiers_list!$A:$AT,MATCH($A82,Tiers_list!$2:$2,0),FALSE)) -> 250 | J82: =+'Proposal Form Tier 1'!$B$16+'Proposal Form Tier 1'!$B$14 -> 0.25 | K82: =+I82*(1-J82) -> 187.5 | L82: =_xlfn.XLOOKUP($A82,'Proposal Form Tier 1'!$C:$C,'Proposal Form Tier 1'!$B:$B,0,0) -> 0 | M82: =+L82*I82 -> 0 | N82: =+L82*K82 -> 0
E83: Subtotal One-Time Onsite Services | M83: =SUM(M80:M82) -> 0 | N83: =SUM(N80:N82) -> 0
L84: Total One-Time ACS Cloud TLS Software Installation, Training Services, Tech Hardware, ACS TLS PCB and Installation and Project Management Services | M84: =+M83+M77 -> 13001 | N84: =+N83+N77 -> 9750.75
M85: MSRP Total | N85: Integrator Total
L86: Grand Total Annual and One Time Service | M86: =+M84+P69 -> 31702.875 | N86: =+N77+J69+K57 -> 23777.156
A87: {=CONCATENATE("R:\SalesInfo\Pricing Lists and Modules\ACS SaaS\",_xlfn.TEXTAFTER(_xlfn.TEXTBEFORE(CELL("filename"),"]"),"["))} -> R:\SalesInfo\Pricing Lists and Modules\ACS SaaS\New_Confidential Parabit Private-Public Cloud On-Prem ACS Enterprise Tiered Software Quote Form_Rev_06-22-26.xlsx

Sheet Proposal Summary - Tier 1
A1: =CONCATENATE("Confidential Parabit Private-Public Cloud On-Premise ACS Enterprise Tiered Software Quote for ",'Proposal Form Tier 2-12'!B2) -> Confidential Parabit Private-Public Cloud On-Premise ACS Enterprise Tiered Software Quote for Bank of America
A2: New ACS Private/Public Cloud and On-Prem Enterprise software suite Annual License Fees
A3: See detail price list for a breakdown of each line items pricing
F4: Integrator | G4: End User
F5: =+'Proposal Form Tier 1'!B15 -> Securitas Technology Co. | G5: =+'Proposal Form Tier 1'!B2 -> Bank of America
A6: Annual and One-Time New ACS Enterprise Private Cloud/Parabit ACSaaS/On-Prem Software Features and Professional Services | B6: =+'Detail_Proposal_tier 1'!I1 -> Tier - 1 - 10 Quantity of Primary Production Instance(s) | C6: =+'Detail_Proposal_tier 1'!J1 -> Tier - 1 - 10 Total Annual Primary Instance(s) Pricing | D6: =+'Detail_Proposal_tier 1'!K1 -> Tier - 1 - 10 Total Annual Fail-Over/DR Instance(s) Pricing | E6: =+'Detail_Proposal_tier 1'!L1 -> Tier - 1 - 10 Total Quantity of Annual Fail-Over/DR Instance(s) | F6: =+'Proposal Summary - Tier 2-12'!F6 -> Total Price | G6: =+'Proposal Summary - Tier 2-12'!G6 -> MSRP / Tier Price Total
A7: =+'Proposal Summary - Tier 2-12'!A7 -> ACS Enterprise Hardware Configuration UI | B7: =SUMIF('Detail_Proposal_tier 1'!$C:$L,$A7,'Detail_Proposal_tier 1'!I:I) -> 3 | C7: =SUMIF('Detail_Proposal_tier 1'!$C:$L,$A7,'Detail_Proposal_tier 1'!J:J) -> 2278.125 | D7: =SUMIF('Detail_Proposal_tier 1'!$C:$L,$A7,'Detail_Proposal_tier 1'!L:L) -> 3 | E7: =SUMIF('Detail_Proposal_tier 1'!$C:$L,$A7,'Detail_Proposal_tier 1'!K:K) -> 1139.0625 | F7: =+E7+C7 -> 3417.1875 | G7: =SUMIF('Detail_Proposal_tier 1'!$C:$L,$A7,'Detail_Proposal_tier 1'!P:P) -> 4556.25
A8: =+'Proposal Summary - Tier 2-12'!A8 -> ACS Enterprise Integrations | B8: =SUMIF('Detail_Proposal_tier 1'!$C:$L,$A8,'Detail_Proposal_tier 1'!I:I) -> 4 | C8: =SUMIF('Detail_Proposal_tier 1'!$C:$L,$A8,'Detail_Proposal_tier 1'!J:J) -> 548.4375 | D8: =SUMIF('Detail_Proposal_tier 1'!$C:$L,$A8,'Detail_Proposal_tier 1'!L:L) -> 4 | E8: =SUMIF('Detail_Proposal_tier 1'!$C:$L,$A8,'Detail_Proposal_tier 1'!K:K) -> 274.21875 | F8: =+E8+C8 -> 822.65625 | G8: =SUMIF('Detail_Proposal_tier 1'!$C:$L,$A8,'Detail_Proposal_tier 1'!P:P) -> 1096.875
A9: =+'Proposal Summary - Tier 2-12'!A9 -> ACS Enterprise Hardware and Software System Supervision and Activity Logs | B9: =SUMIF('Detail_Proposal_tier 1'!$C:$L,$A9,'Detail_Proposal_tier 1'!I:I) -> 3 | C9: =SUMIF('Detail_Proposal_tier 1'!$C:$L,$A9,'Detail_Proposal_tier 1'!J:J) -> 421.875 | D9: =SUMIF('Detail_Proposal_tier 1'!$C:$L,$A9,'Detail_Proposal_tier 1'!L:L) -> 3 | E9: =SUMIF('Detail_Proposal_tier 1'!$C:$L,$A9,'Detail_Proposal_tier 1'!K:K) -> 210.9375 | F9: =+E9+C9 -> 632.8125 | G9: =SUMIF('Detail_Proposal_tier 1'!$C:$L,$A9,'Detail_Proposal_tier 1'!P:P) -> 843.75
A10: =+'Proposal Summary - Tier 2-12'!A10 -> ACS Enterprise Mass Programming and Data Collection/Receiving Services | B10: =SUMIF('Detail_Proposal_tier 1'!$C:$L,$A10,'Detail_Proposal_tier 1'!I:I) -> 7 | C10: =SUMIF('Detail_Proposal_tier 1'!$C:$L,$A10,'Detail_Proposal_tier 1'!J:J) -> 801.5625 | D10: =SUMIF('Detail_Proposal_tier 1'!$C:$L,$A10,'Detail_Proposal_tier 1'!L:L) -> 7 | E10: =SUMIF('Detail_Proposal_tier 1'!$C:$L,$A10,'Detail_Proposal_tier 1'!K:K) -> 400.78125 | F10: =+E10+C10 -> 1202.3438 | G10: =SUMIF('Detail_Proposal_tier 1'!$C:$L,$A10,'Detail_Proposal_tier 1'!P:P) -> 1603.125
A11: =+'Proposal Summary - Tier 2-12'!A11 -> Annual ACS Cloud Enterprise Ecosystem, Hardware, Facility Sensors, Reader Monitoring UI features | B11: =SUMIF('Detail_Proposal_tier 1'!$C:$L,$A11,'Detail_Proposal_tier 1'!I:I) -> 2 | C11: =SUMIF('Detail_Proposal_tier 1'!$C:$L,$A11,'Detail_Proposal_tier 1'!J:J) -> 210.9375 | D11: =SUMIF('Detail_Proposal_tier 1'!$C:$L,$A11,'Detail_Proposal_tier 1'!L:L) -> 2 | E11: =SUMIF('Detail_Proposal_tier 1'!$C:$L,$A11,'Detail_Proposal_tier 1'!K:K) -> 105.46875 | F11: =+E11+C11 -> 316.40625 | G11: =SUMIF('Detail_Proposal_tier 1'!$C:$L,$A11,'Detail_Proposal_tier 1'!P:P) -> 421.875
A12: =+'Proposal Summary - Tier 2-12'!A12 -> Subtotal ACS OSDP TLS Enterprise/Tech software suite Annual License and Support Fees | B12: =SUM(B7:B11) -> 19 | C12: =SUM(C7:C11) -> 4260.9375 | D12: =SUM(D7:D11) -> 19 | E12: =SUM(E7:E11) -> 2130.4688 | F12: =SUM(F7:F11) -> 6391.4062 | G12: =SUM(G7:G11) -> 8521.875
A13: =+'Proposal Summary - Tier 2-12'!A13 -> 0
A14: =+'Proposal Summary - Tier 2-12'!A14 -> Annual Support, Encryption and Technician Software Fees | B14: Qty | C14: Total | F14: =+F6 -> Total Price | G14: =+G6 -> MSRP / Tier Price Total
A15: =+'Proposal Summary - Tier 2-12'!A15 -> Annual 24/7 ACS Enterprise software suite Telephone Support | B15: =SUMIF('Detail_Proposal_tier 1'!$C:$L,$A15,'Detail_Proposal_tier 1'!I:I) -> 1 | C15: =SUMIF('Detail_Proposal_tier 1'!$C:$L,$A15,'Detail_Proposal_tier 1'!J:J) -> 5000 | F15: =+E15+C15 -> 5000 | G15: =SUMIF('Detail_Proposal_tier 1'!$C:$L,$A15,'Detail_Proposal_tier 1'!P:P) -> 6666.6667
A16: =+'Proposal Summary - Tier 2-12'!A16 -> Annual Full Day Remote ACS Training ten (10) hours (Draw down in two (2) hour prescheduled increments | B16: =SUMIF('Detail_Proposal_tier 1'!$C:$L,$A16,'Detail_Proposal_tier 1'!I:I) -> 1 | C16: =SUMIF('Detail_Proposal_tier 1'!$C:$L,$A16,'Detail_Proposal_tier 1'!J:J) -> 2500 | F16: =+E16+C16 -> 2500 | G16: =SUMIF('Detail_Proposal_tier 1'!$C:$L,$A16,'Detail_Proposal_tier 1'!P:P) -> 3333.3333
A17: =+'Proposal Summary - Tier 2-12'!A17 -> ACS TLS 1.2/1.3 Encryption Annual Support Fee | B17: =SUMIF('Detail_Proposal_tier 1'!$C:$L,$A17,'Detail_Proposal_tier 1'!I:I) -> 9 | C17: =SUMIF('Detail_Proposal_tier 1'!$C:$L,$A17,'Detail_Proposal_tier 1'!J:J) -> 135 | F17: =+E17+C17 -> 135 | G17: =SUMIF('Detail_Proposal_tier 1'!$C:$L,$A17,'Detail_Proposal_tier 1'!P:P) -> 180
A18: =+'Proposal Summary - Tier 2-12'!A18 -> Annual Tech Software | B18: =SUMIF('Detail_Proposal_tier 1'!$C:$L,$A18,'Detail_Proposal_tier 1'!I:I) -> 0 | C18: =SUMIF('Detail_Proposal_tier 1'!$C:$L,$A18,'Detail_Proposal_tier 1'!J:J) -> 0 | F18: =+E18+C18 -> 0 | G18: =SUMIF('Detail_Proposal_tier 1'!$C:$L,$A18,'Detail_Proposal_tier 1'!P:P) -> 0
A19: =+'Proposal Summary - Tier 2-12'!A19 -> Subtotal Annual Support, Encryption and Technician Software Fees | C19: =SUM(C15:C18) -> 7635 | F19: =SUM(F15:F18) -> 7635 | G19: =SUM(G15:G18) -> 10180
A20: =+'Proposal Summary - Tier 2-12'!A20 -> 0
A21: =+'Proposal Summary - Tier 2-12'!A21 -> Total Annual ACS OSDP TLS Enterprise software suite and Annual Support, Encryption, and Technician Software Fees | C21: =+C19+C12 -> 11895.938 | E21: =+E19+E12 -> 2130.4688 | F21: =+F19+F12 -> 14026.406 | G21: =+G19+G12 -> 18701.875
A22: =+'Proposal Summary - Tier 2-12'!A22 -> Discount off above pricing | B22: =+'Proposal Form Tier 1'!$B$16+'Proposal Form Tier 1'!$B$14 -> 0.25
A23: =+'Proposal Summary - Tier 2-12'!A23 -> 0
A24: =+'Proposal Summary - Tier 2-12'!A24 -> One-Time ACS OSDP TLS Enterprise software Professional Services | B24: Qty | C24: Total | F24: =+F14 -> Total Price | G24: =+G14 -> MSRP / Tier Price Total
A25: =+'Proposal Summary - Tier 2-12'!A25 -> ACS OSDP TLS Enterprise software Installation Support | B25: =SUMIF('Detail_Proposal_tier 1'!C$73:C$138,$A25,'Detail_Proposal_tier 1'!L$73:L$138) -> 38 | C25: =SUMIF('Detail_Proposal_tier 1'!$C$73:$N$138,$A25,'Detail_Proposal_tier 1'!N$73:N$138) -> 7125 | F25: =+E25+C25 -> 7125 | G25: =SUMIF('Detail_Proposal_tier 1'!$C$73:$N$138,$A25,'Detail_Proposal_tier 1'!M$73:M$138) -> 9500
A26: =+'Proposal Summary - Tier 2-12'!A26 -> ACS Tech Enterprise License Diagnostic/Programming Hardware | B26: =SUMIF('Detail_Proposal_tier 1'!C$73:C$138,$A26,'Detail_Proposal_tier 1'!L$73:L$138) -> 0 | C26: =SUMIF('Detail_Proposal_tier 1'!C$73:N$138,$A26,'Detail_Proposal_tier 1'!N$73:N$138) -> 0 | F26: =+E26+C26 -> 0 | G26: =SUMIF('Detail_Proposal_tier 1'!$C$73:$N$138,$A26,'Detail_Proposal_tier 1'!M$73:M$138) -> 0
A27: =+'Proposal Summary - Tier 2-12'!A27 -> ACS TLS 1.2/1.3 Crypto PCB | B27: =SUMIF('Detail_Proposal_tier 1'!C$73:C$138,$A27,'Detail_Proposal_tier 1'!L$73:L$138) -> 9 | C27: =SUMIF('Detail_Proposal_tier 1'!C$73:N$138,$A27,'Detail_Proposal_tier 1'!N$73:N$138) -> 2625.75 | F27: =+E27+C27 -> 2625.75 | G27: =SUMIF('Detail_Proposal_tier 1'!$C$73:$N$138,$A27,'Detail_Proposal_tier 1'!M$73:M$138) -> 3501
A28: =+'Proposal Summary - Tier 2-12'!A28 -> Installation and Project Management Labor support for ACS TLS 1.2/1.3 Crypto PCB | B28: =SUMIF('Detail_Proposal_tier 1'!C$73:C$138,$A28,'Detail_Proposal_tier 1'!L$73:L$138) -> 0 | C28: =SUMIF('Detail_Proposal_tier 1'!C$73:N$138,$A28,'Detail_Proposal_tier 1'!N$73:N$138) -> 0 | F28: =+E28+C28 -> 0 | G28: =SUMIF('Detail_Proposal_tier 1'!$C$73:$N$138,$A28,'Detail_Proposal_tier 1'!M$73:M$138) -> 0
A29: =+'Proposal Summary - Tier 2-12'!A29 -> Total One-Time ACS OSDP TLS Enterprise software Professional Services | C29: =SUM(C25:C28) -> 9750.75 | F29: =+E29+C29 -> 9750.75 | G29: =SUM(G25:G28) -> 13001
A30: =+'Proposal Summary - Tier 2-12'!A30 -> Discount off this section pricing | B30: =+'Proposal Form Tier 1'!$B$16+'Proposal Form Tier 1'!$B$14 -> 0.25
A31: =+'Proposal Summary - Tier 2-12'!A31 -> 0
A32: =+'Proposal Summary - Tier 2-12'!A32 -> Grand Total Annual and One Time Service | C32: =+C21+C29 -> 21646.688 | E32: =+E21+E29 -> 2130.4688 | F32: =+F21+F29 -> 23777.156 | G32: =+G21+G29 -> 31702.875
A34: Notes:
A35: All Annual Fees are due prior to each terms start
A36: This proposal includes one Production and one Failover or Disaster Recovery Annual License
A37: {=CONCATENATE("R:\SalesInfo\Pricing Lists and Modules\ACS SaaS\",_xlfn.TEXTAFTER(_xlfn.TEXTBEFORE(CELL("filename"),"]"),"["))} -> R:\SalesInfo\Pricing Lists and Modules\ACS SaaS\New_Confidential Parabit Private-Public Cloud On-Prem ACS Enterprise Tiered Software Quote Form_Rev_06-22-26.xlsx

Sheet Proposal Form Tier 2-12
A1: Specific Criteria For the quote | B1: Quantity | E1: Instructions
A2: End-User Name | B2: Bank of America
A3: Number Of Controllers | B3: 2200
C4: Chosen Tier Min QTY of Controllers | D4: Chosen Tier Max QTY of Controllers
A5: Annual Service Tier Level | B5: =_xlfn.XLOOKUP($B$3,Tiers_list!$D:$D,Tiers_list!$A:$A,,1) -> Tier 11 - 2001 - 3000 | C5: =_xlfn.XLOOKUP('Proposal Form Tier 2-12'!$B$5,Tiers_list!$A:$A,Tiers_list!C:C,,0) -> 2001 | D5: =_xlfn.XLOOKUP('Proposal Form Tier 2-12'!$B$5,Tiers_list!$A:$A,Tiers_list!D:D,,0) -> 3000 | E5: =IF(B5="Tier - 1 - 10","This Sheet is notintended for Tier 1. If controller less than 11 use 'Basic Form Tier 1'","")
A6: Quantity of Annual Primary Production Instance(s) | B6: 1
A8: Quantity of Annual Primary Fail-Over Instance(s) | B8: 1
A9: Quantity of Annual DR Instance(s) | B9: 0
A10: Quantity of Annual DR Failover Instance(s) | B10: 0
A11: Total Quantity of Annual Fail-Over / DR Instance(s) | B11: =SUM(B8:B10) -> 1
A12: Percentage of Production cost to use for Failover and DR Instance(s) | B12: 0.5
A14: End-User Discount Rate | B14: =_xlfn.XLOOKUP(B2,End_user!A:A,End_user!B:B,0,0) -> 0
A15: Integrator Name | B15: Securitas Technology Co.
A16: Integrator Discount Rate | B16: =_xlfn.XLOOKUP(B15,'Integrator List'!A:A,'Integrator List'!B:B,0,0) -> 0.25
A19: Annual - Advanced Optional Micro Services | B19: Quantity | C19: Product Number | D19: UOM
A20: =_xlfn.XLOOKUP($C20,Tiers_list!$2:$2,Tiers_list!$1:$1,,0) -> ACS system data non cloud integration / parser to 3rd party systems ACS Event Messages, Credentials and User Logs Module | B20: 1 | C20: 200-50048 | D20: ea. | E20: Annual
A21: =_xlfn.XLOOKUP($C21,Tiers_list!$2:$2,Tiers_list!$1:$1,,0) -> ACS Job Scheduler Service Module | B21: 1 | C21: 200-50059 | D21: ea. | E21: Annual
A22: =_xlfn.XLOOKUP($C22,Tiers_list!$2:$2,Tiers_list!$1:$1,,0) -> AFH / Data Collection Service Module | B22: 1 | C22: 200-50060 | D22: ea. | E22: Annual
A23: =_xlfn.XLOOKUP($C23,Tiers_list!$2:$2,Tiers_list!$1:$1,,0) -> Remote ACS Hardware firmware updates Module | B23: 1 | C23: 200-50061 | D23: ea. | E23: Annual
A24: =_xlfn.XLOOKUP($C24,Tiers_list!$2:$2,Tiers_list!$1:$1,,0) -> Reader Credentials Accepted and Rejected Supervision Module | B24: 1 | C24: 200-50069 | D24: ea. | E24: Annual
A26: =_xlfn.XLOOKUP($C26,Tiers_list!$2:$2,Tiers_list!$1:$1,,0) -> ACS TLS 1.2/1.3 PCB | B26: =+B3 -> 2200 | C26: 200-50070 | D26: ea. | E26: Annual
A27: =_xlfn.XLOOKUP($C27,Tiers_list!$2:$2,Tiers_list!$1:$1,,0) -> 24/7 ACS Enterprise Telephone Support | B27: 1 | C27: YEAR-ACS-RTS | D27: ea. | E27: Annual / Optional
A28: =_xlfn.XLOOKUP($C28,Tiers_list!$2:$2,Tiers_list!$1:$1,,0) -> Annual Remote Training ACS | B28: 1 | C28: 1000-30054 | D28: Required. Choose Qty of 10 hours slots | E28: Annual
A30: =_xlfn.XLOOKUP($C30,Tiers_list!$2:$2,Tiers_list!$1:$1,,0) -> ACS Enterprise - Tech Software License - Annual Software Assurance | B30: 1 | C30: 200-50007-NTS | D30: ea. | E30: Annual
A32: One-Time Required Hardware and Installation Service and support | B32: Quantity | C32: =+C19 -> Product Number | D32: UOM
A33: =_xlfn.XLOOKUP($C33,Tiers_list!$2:$2,Tiers_list!$1:$1,,0) -> TLS 1.2/1.3 PCB | B33: =+B26 -> 2200 | C33: 200-10115-PCBA | D33: ea. | E33: One-Time
A34: =_xlfn.XLOOKUP($C34,Tiers_list!$2:$2,Tiers_list!$1:$1,,0) -> ACS Enterprise - Hardware - Controller Firmware Programmer KIT - No license Provided. | B34: 1 | C34: 200-50007-KT | D34: ea. | E34: One-Time
A36: Trip Charge | B36: =+IF(B15="Parabit Systems, Inc.",B3,0) -> 0 | C36: 1000-30052 | D36: ea. | E36: One-Time if Parabit is the Installer
A37: On-Site/Remote Low Voltage/Mechanical Tech Weekday Business Hours | B37: =+B36*2 -> 0 | C37: 1000-20000 | D37: ea. | E37: One-Time if Parabit is the Installer
A38: Project Management | B38: =0.15*B36 -> 0 | C38: 1000-30045 | D38: ea. | E38: One-Time if Parabit is the Installer
A40: Annual Optional Software | B40: Quantity | C40: =+C32 -> Product Number | D40: UOM | E40: Quantity chosen here will appear in Detail Software Sheet (light blue cells)
A41: =_xlfn.XLOOKUP($C41,Tiers_list!$2:$2,Tiers_list!$1:$1,,0) -> Controller/Reader Credential Enrollment Management Module | B41: 0 | C41: 200-50043 | D41: ea.
A42: =_xlfn.XLOOKUP($C42,Tiers_list!$2:$2,Tiers_list!$1:$1,,0) -> ACS system data cloud integration to 3rd party systems ACS Event Messages, Credentials and User Logs Module | B42: 0 | C42: 200-50047 | D42: ea.
A43: =_xlfn.XLOOKUP($C43,Tiers_list!$2:$2,Tiers_list!$1:$1,,0) -> Email/Text EMR Notifier Service Module | B43: 0 | C43: 200-50049 | D43: ea.
A44: =_xlfn.XLOOKUP($C44,Tiers_list!$2:$2,Tiers_list!$1:$1,,0) -> ACS controller Reader Remote Credential Lookup with Local learn Module | B44: 0 | C44: 200-50050 | D44: ea.
A45: =_xlfn.XLOOKUP($C45,Tiers_list!$2:$2,Tiers_list!$1:$1,,0) -> HR & Time Attendance Credential Integration Module | B45: 0 | C45: 200-50053 | D45: ea.
A46: =_xlfn.XLOOKUP($C46,Tiers_list!$2:$2,Tiers_list!$1:$1,,0) -> ACS Hardware and Facility Sensor Data Integration(s) Module | B46: 0 | C46: 200-50054 | D46: ea.
A47: =_xlfn.XLOOKUP($C47,Tiers_list!$2:$2,Tiers_list!$1:$1,,0) -> Suspend distribution of Select or All Event Messages generated by ACS hardware and software Module | B47: 0 | C47: 200-50058 | D47: ea.
A48: =_xlfn.XLOOKUP($C48,Tiers_list!$2:$2,Tiers_list!$1:$1,,0) -> Door / Entrance Supervision Configuration Module | B48: 0 | C48: 200-50062 | D48: ea.
A49: =_xlfn.XLOOKUP($C49,Tiers_list!$2:$2,Tiers_list!$1:$1,,0) -> ACS Controller Software Integrations DB Ecosystem Supervision Module | B49: 0 | C49: 200-50068 | D49: ea.
A51: =_xlfn.XLOOKUP($C51,Tiers_list!$2:$2,Tiers_list!$1:$1,,0) -> Silent Installer with ACS Enterprise software license Cloud Key Validation | B51: 1 | C51: 200-50040 | D51: ea. | E51: Included
A52: =_xlfn.XLOOKUP($C52,Tiers_list!$2:$2,Tiers_list!$1:$1,,0) -> Parabit Cloud App/DB Software Instance Activation/Term Management | B52: 1 | C52: 200-50041 | D52: ea. | E52: Included
A53: =_xlfn.XLOOKUP($C53,Tiers_list!$2:$2,Tiers_list!$1:$1,,0) -> ACS controller Reader Remote Credential Lookup with Local learn Module | B53: 0 | C53: 200-50071 | D53: ea.
A54: =_xlfn.XLOOKUP($C54,Tiers_list!$2:$2,Tiers_list!$1:$1,,0) -> ACS controller Reader Remote Credential Lookup with Local learn Module | B54: 0 | C54: 200-50072 | D54: ea.
A55: =_xlfn.XLOOKUP($C55,Tiers_list!$2:$2,Tiers_list!$1:$1,,0) -> Export & Reporting | B55: 0 | C55: 200-50073 | D55: ea.
A56: =_xlfn.XLOOKUP($C56,Tiers_list!$2:$2,Tiers_list!$1:$1,,0) -> Bulk Synchronisation ans Scheduling | B56: 0 | C56: 200-50074 | D56: ea.
A57: =_xlfn.XLOOKUP($C57,Tiers_list!$2:$2,Tiers_list!$1:$1,,0) -> Clone & Templates | B57: 0 | C57: 200-50075 | D57: ea.
A58: =_xlfn.XLOOKUP($C58,Tiers_list!$2:$2,Tiers_list!$1:$1,,0) -> Merge Operations | B58: 0 | C58: 200-50076 | D58: ea.
A59: =_xlfn.XLOOKUP($C59,Tiers_list!$2:$2,Tiers_list!$1:$1,,0) -> Advanced User Management | B59: 0 | C59: 200-50077 | D59: ea.
A60: =_xlfn.XLOOKUP($C60,Tiers_list!$2:$2,Tiers_list!$1:$1,,0) -> Advanced Log Filtering | B60: 0 | C60: 200-50078 | D60: ea.
A61: =_xlfn.XLOOKUP($C61,Tiers_list!$2:$2,Tiers_list!$1:$1,,0) -> Notification & Alerts | B61: 0 | C61: 200-50079 | D61: ea.

Sheet Detail_Proposal_tier 2-12
A1: Product # | B1: Product Tree | C1: Category | D1: Prod # Description | E1: =+'Detail_Proposal_tier 1'!E1 -> Feature Description | F1: =+'Detail_Proposal_tier 1'!F1 -> Business Description | G1: Feature Type | H1: UoM | I1: =CONCATENATE('Proposal Form Tier 2-12'!B5," ","Quantity of Primary Production Instance(s)") -> Tier 11 - 2001 - 3000 Quantity of Primary Production Instance(s) | J1: =CONCATENATE('Proposal Form Tier 2-12'!B5," ","Total Annual Primary Instance(s) Pricing") -> Tier 11 - 2001 - 3000 Total Annual Primary Instance(s) Pricing | K1: =CONCATENATE('Proposal Form Tier 2-12'!B5," ","Total Annual Fail-Over/DR Instance(s) Pricing") -> Tier 11 - 2001 - 3000 Total Annual Fail-Over/DR Instance(s) Pricing | L1: =CONCATENATE('Proposal Form Tier 2-12'!B5," ","Total Quantity of Annual Fail-Over/DR Instance(s)") -> Tier 11 - 2001 - 3000 Total Quantity of Annual Fail-Over/DR Instance(s) | M1: Enter # of Instances per Tier - Quantity of Annual Primary Fail-Over Instance(s) | N1: Enter # of Instances per Tier - Quantity of DR Instance(s) | O1: Enter # of Instances per Tier - Quantity of DR Failover Instance(s) | P1: MSRP Total
A2: 200-50042 | B2: ACS Software | C2: ACS Enterprise Hardware Configuration UI | D2: Campus, Site, Floor, Controller, Entrance/Reader, User, Credential, Configuration, Diagnostics and Reports Module | E2: =+'Detail_Proposal_tier 1'!E2 -> By Site by ACS Controller Customer defined ID, Digital Serial #, Customer defined asset tag, Entrance location data (Address, Cross Streets, Contact, Phone, Email, etc., Time Zone/DST, I/O configuration, Overlay/RFID Skim Detection times, IP/Port, DNS, DHCP. By Reader/Entrance: Reader Serial #, PID, Weekly and Holiday schedule(s) assignment, Digital API Data Integration(s) settings, Entrance Door Release duration, Door Ajar detect time, Door opening excessively to Credentials read ratio, Customer Can't Enter/Exit sequential configuration, Reader Egress time, Exit/Entry Switch Egress time, Anti-Tailgating Active/Disabled, Physical Overlay/RFID Skimmer Detect Time, Reader and Lock state Inhibit Active/Disabled integration, Loitering, Single Access, Light Sensor, Last ATM Transaction Date/Time and 3rd party system configurations. | F2: =+'Detail_Proposal_tier 1'!F2 -> ACS Cloud Enterprise gives operators and administrators a single, unified interface to configure every layer of their access control environment — from site addresses, time zones, and network settings down to individual reader behaviors, credential masks, and third-party integration parameters. Rather than juggling separate tools or on-site visits, teams can define and push the complete hardware profile of every controller and entrance from the cloud, ensuring every site is consistently configured, operationally ready, and aligned with organizational standards from day one. | G2: Required | H2: ea. | I2: =IF('Proposal Form Tier 2-12'!$B$5=Tiers_list!$A$3,+'Proposal Form Tier 2-12'!B6,1) -> 1 | J2: =IF('Proposal Form Tier 2-12'!$B$5<>"Tier - 1 - 10",VLOOKUP('Proposal Form Tier 2-12'!$B$5,Tiers_list!$A:$BC,MATCH($A2,Tiers_list!$2:$2,0),FALSE)*$I2,VLOOKUP('Proposal Form Tier 2-12'!$B$5,Tiers_list!$A:$BC,MATCH($A2,Tiers_list!$2:$2,0),FALSE)*$I2/10)*(1-'Proposal Form Tier 2-12'!$B$16-'Proposal Form Tier 2-12'!$B$14) -> 8550 | K2: =IF('Proposal Form Tier 2-12'!$B$5<>"Tier - 1 - 10",VLOOKUP('Proposal Form Tier 2-12'!$B$5,Tiers_list!$A:$BC,MATCH($A2,Tiers_list!$2:$2,0),FALSE)*L2*'Proposal Form Tier 2-12'!B$12,VLOOKUP('Proposal Form Tier 2-12'!$B$5,Tiers_list!$A:$BC,MATCH($A2,Tiers_list!$2:$2,0),FALSE)*'Proposal Form Tier 2-12'!B$12*L2/10)*(1-'Proposal Form Tier 2-12'!B14-'Proposal Form Tier 2-12'!B16) -> 4275 | L2: =SUM(M2:O2) -> 1 | M2: =IF($I2>0,'Proposal Form Tier 2-12'!$B$8,0) -> 1 | N2: =IF($I2>0,'Proposal Form Tier 2-12'!$B$9,0) -> 0 | O2: =IF($I2>0,'Proposal Form Tier 2-12'!$B$10,0) -> 0 | P2: =+(J2/(1-'Proposal Form Tier 2-12'!$B$16-'Proposal Form Tier 2-12'!$B$14))+(K2/(1-'Proposal Form Tier 2-12'!$B$16-'Proposal Form Tier 2-12'!$B$14)) -> 17100
B3: ACS Software | C3: ACS Enterprise Hardware Configuration UI | D3: Campus, Site, Floor, Controller, Entrance/Reader, User, Credential, Configuration, Diagnostics and Reports Module | E3: =+'Detail_Proposal_tier 1'!E3 -> Create/edit/update/deactivate ACS Users and ACS Users who assign access rights to ACS features | F3: =+'Detail_Proposal_tier 1'!F3 -> Administrators gain full lifecycle control over every system user — creating, editing, and deactivating accounts while assigning precise role-based access rights that determine exactly which ACS features and data each person can reach. By tying permissions directly to user profiles rather than managing them ad hoc, organizations eliminate over-privileged accounts, enforce the principle of least privilege, and maintain a clean, auditable record of who has access to what across the entire platform.
B4: ACS Software | C4: ACS Enterprise Hardware Configuration UI | D4: Campus, Site, Floor, Controller, Entrance/Reader, User, Credential, Configuration, Diagnostics and Reports Module | E4: =+'Detail_Proposal_tier 1'!E4 -> Active Directory (AD) support | F4: =+'Detail_Proposal_tier 1'!F4 -> For organizations already running Microsoft Active Directory, ACS Cloud Enterprise eliminates the need for a separate set of user credentials by enabling staff to log in using their existing AD accounts. Operators can search, assign, and manage AD users and groups directly within ACS — with access permissions updating automatically in real time whenever an AD account is modified or disabled — reducing administrative burden and closing the security gaps that come from manually maintained duplicate user lists.
B5: ACS Software | C5: ACS Enterprise Hardware Configuration UI | D5: Campus, Site, Floor, Controller, Entrance/Reader, User, Credential, Configuration, Diagnostics and Reports Module | E5: =+'Detail_Proposal_tier 1'!E5 -> Configure reader type, access by Credential holder and by Access Schedule for MMR 2.0 reader Mag Stripe and NFC Card. | F5: =+'Detail_Proposal_tier 1'!F5 -> Operators can configure every reader in the system — defining the credential types accepted (magnetic stripe, NFC, Bluetooth, biometric, and more), assigning the appropriate access schedules, and linking readers to specific user groups — all from a centralized interface without a site visit. This ensures that every entrance behaves exactly as intended, that the right people have access at the right times, and that configuration changes are applied instantly and consistently across all locations.
B6: ACS Software | C6: ACS Enterprise Hardware Configuration UI | D6: Campus, Site, Floor, Controller, Entrance/Reader, User, Credential, Configuration, Diagnostics and Reports Module | E6: =+'Detail_Proposal_tier 1'!E6 -> Configure Readers and/or Users on type of credential(s) required to access an entrance or group of entrances. i.e., a reader can require one, two or more types of credentials by Reader or User to gain access to a (or group of) specified Reader. | F6: =+'Detail_Proposal_tier 1'!F6 -> Organizations can define precise credential matching rules for each reader or entrance — specifying exactly which credential types, card formats, and validation methods are required to gain access at any given point. Whether using standard match, bank credential fallback, external match validation, or protocol-based NFC matching, operators can tailor access logic per reader without firmware changes, giving security teams granular control over who gets through each door and under what conditions.
B7: ACS Software | C7: ACS Enterprise Hardware Configuration UI | D7: Campus, Site, Floor, Controller, Entrance/Reader, User, Credential, Configuration, Diagnostics and Reports Module | E7: =+'Detail_Proposal_tier 1'!E7 -> Remote ACS controller I/O test and status inquiry | F7: =+'Detail_Proposal_tier 1'!F7 -> Field technicians and operators can remotely test and query the real-time status of any ACS controller's I/O channels without traveling to the site, enabling rapid diagnosis of hardware issues, connection faults, and configuration mismatches from the cloud. This reduces costly site visits, shortens mean time to resolution, and ensures that technical teams have full visibility into device health before deploying maintenance resources.
B8: ACS Software | C8: ACS Enterprise Hardware Configuration UI | D8: Campus, Site, Floor, Controller, Entrance/Reader, User, Credential, Configuration, Diagnostics and Reports Module | E8: =+'Detail_Proposal_tier 1'!E8 -> Define and remotely configure Weekly Access Schedule (Credentials required), Open (entrance unlocked) and Locked (entrance closed) | F8: =+'Detail_Proposal_tier 1'!F8 -> Operators can define weekly access schedules — specifying which credential is required, when an entrance is open to all, or when it is locked — and push those schedules remotely to any controller or group of controllers across the organization. This eliminates manual on-site programming for routine schedule updates, ensures schedules are applied consistently across all sites, and gives security teams the flexibility to respond to operational changes without delay.
B9: ACS Software | C9: ACS Enterprise Hardware Configuration UI | D9: Campus, Site, Floor, Controller, Entrance/Reader, User, Credential, Configuration, Diagnostics and Reports Module | E9: =+'Detail_Proposal_tier 1'!E9 -> Define Annual Holiday Access (Credential required), Open (entrance unlocked) and Locked (entrance closed) schedule. Notify selected ACS users when a future defined holiday date and schedule has not been defined within the ACS database or programmed into the ACS controller | F9: =+'Detail_Proposal_tier 1'!F9 -> Define Annual Holiday Access (Credential required), Open (entrance unlocked) and Locked (entrance closed) schedule. Notify selected ACS users when a future defined holiday date and schedule has not been defined within the ACS database or programmed into the ACS controller
B10: ACS Software | C10: ACS Enterprise Hardware Configuration UI | D10: Campus, Site, Floor, Controller, Entrance/Reader, User, Credential, Configuration, Diagnostics and Reports Module | E10: =+'Detail_Proposal_tier 1'!E10 -> Manage and remotely configure credentials table/configuration accepted for NFC, Magnetic Stripe. Accepted Credentials, Admin Credentials, Financial Credential types and Exception tables and assign to reader(s)/entrance(s). | F10: =+'Detail_Proposal_tier 1'!F10 -> Operators can create, import, edit, merge, and export credential lists — covering accepted credentials, administrative cards, financial credential types, and exception (suspect/reject) tables — and assign them directly to individual readers or push them across multiple sites simultaneously. By centralizing credential list management in the cloud, organizations avoid the risks of outdated lists on individual controllers and ensure that access decisions are always based on the most current and accurate credential data available.
B11: ACS Software | C11: ACS Enterprise Hardware Configuration UI | D11: Campus, Site, Floor, Controller, Entrance/Reader, User, Credential, Configuration, Diagnostics and Reports Module | E11: =+'Detail_Proposal_tier 1'!E11 -> Remotely set an ACS controllers Maintenance Mode (Active/Clear) | F11: =+'Detail_Proposal_tier 1'!F11 -> Operators and technicians can remotely activate and manage Maintenance Mode on any ACS controller, flagging all activity during that window so that alarms generated by maintenance work are clearly identified and not mistakenly escalated to monitoring centers. With configurable durations, automatic expiry, and real-time event tracking of who activated maintenance, when, and for how long, organizations maintain full operational accountability even during planned downtime.
B12: ACS Software | C12: ACS Enterprise Hardware Configuration UI | D12: Campus, Site, Floor, Controller, Entrance/Reader, User, Credential, Configuration, Diagnostics and Reports Module | E12: =+'Detail_Proposal_tier 1'!E12 -> Remote Door/Entrance Unlock for x - xx seconds | F12: =+'Detail_Proposal_tier 1'!F12 -> Administrators and operators can instantly unlock any entrance remotely for a defined duration — whether responding to an emergency, assisting a visitor, or supporting a maintenance request — without sending a technician to the site. The action is logged in the audit trail, automatically reversed after the configured time, and fully visible in real-time event monitoring, giving teams both the speed to respond and the traceability to stay compliant.
B13: ACS Software | C13: ACS Enterprise Hardware Configuration UI | D13: Campus, Site, Floor, Controller, Entrance/Reader, User, Credential, Configuration, Diagnostics and Reports Module | E13: =+'Detail_Proposal_tier 1'!E13 -> Remote Door/Entrance Access Schedule State Override with an until date/time (Access, Lock or Open). | F13: =+'Detail_Proposal_tier 1'!F13 -> When circumstances require a door to behave differently from its standard schedule — planned maintenance, emergency access, special events, or adverse weather — operators can remotely override the entrance state (open, access, or locked) for a defined date and time window without modifying the underlying schedule. The override clears automatically when the window expires, the original schedule resumes immediately, and the entire action is logged, ensuring operational flexibility never comes at the cost of security accountability.
B14: ACS Software | C14: ACS Enterprise Hardware Configuration UI | D14: Campus, Site, Floor, Controller, Entrance/Reader, User, Credential, Configuration, Diagnostics and Reports Module | E14: =+'Detail_Proposal_tier 1'!E14 -> Manage User Access Credential(s) data: Import/Export .csv files • Credential Type: Bio Datapoint file1, Bio Datapoint file2, Bio Datapoint file…, Keypad Code, Mobile Device EIN/MAC???, etc. • Prox/NFC Card or Bluetooth: Facility Code / BIN number or ID / PAN number • 5 fields for 1st, middle, last, etc. names • ID used to validate Credential Holder • Driver’s License, Passport, Social Security #, Employee ID #, User Defined Credential 1, User Defined Credential 2… • Address1: #, Street, City, County, Town, Village, Prefecture, State, Zip/Postal Code, Country, • Address2: #, Street, City, County, Town, Village, Prefecture, State, Zip/Postal Code, Country, • Phone1, Phone2, etc. • Email1, Email2, etc. • Manager1, Phone1, Email1 • Manager2, Phone1, Email1 • (Investigate other credential types / fields required per credential and type): | F14: =+'Detail_Proposal_tier 1'!F14 -> Operators can manage the full credential data profile for each user — importing and exporting credential records via CSV, defining credential types accepted per user, and linking physical or virtual credentials to access rights — giving organizations a clean, importable, and auditable record of who holds which credential and what they can access. This streamlines onboarding, offboarding, and credential audits while reducing the manual effort and error risk of maintaining credential records outside the system.
B15: ACS Software | C15: ACS Enterprise Hardware Configuration UI | D15: Campus, Site, Floor, Controller, Entrance/Reader, User, Credential, Configuration, Diagnostics and Reports Module | E15: =+'Detail_Proposal_tier 1'!E15 -> View, export and reports sites, hardware, configuration, events, credentials read, user functions executed, user/hardware configuration change logs and ACS controller and reader inventory | F15: =+'Detail_Proposal_tier 1'!F15 -> Administrators, operators, and auditors can view, filter, search a comprehensive set of reports spanning site activity, hardware status, configuration changes, credential events, and user actions — all from a single interface. Whether preparing for a compliance audit, investigating a security incident, or reviewing operational performance, teams can generate the exact data they need in seconds.
A16: 200-50043 | B16: ACS Software | C16: ACS Enterprise Hardware Configuration UI | D16: Controller/Reader Credential Enrollment Management Module | E16: =+'Detail_Proposal_tier 1'!E16 -> Configure an ACS controller reader to learn/enroll a credential. The learn/enroll feature is configured by one or more designated User approval(s). | F16: =+'Detail_Proposal_tier 1'!F16 -> ACS Cloud Enterprise enables any configured reader to enter a learn or enrollment mode, automatically capturing and storing a new credential when it is presented — eliminating the need to manually enter card numbers during onboarding. This accelerates the setup of new cardholders at large-scale deployments, reduces data entry errors, and gives operators a fast, reliable way to add credentials to the system directly from the physical reader. | G16: Optional | H16: ea. | I16: =_xlfn.XLOOKUP($A16,'Proposal Form Tier 2-12'!$C:$C,'Proposal Form Tier 2-12'!$B:$B,0,0) -> 0 | J16: =IF('Proposal Form Tier 2-12'!$B$5<>"Tier - 1 - 10",VLOOKUP('Proposal Form Tier 2-12'!$B$5,Tiers_list!$A:$BC,MATCH($A16,Tiers_list!$2:$2,0),FALSE)*I16,VLOOKUP('Proposal Form Tier 2-12'!$B$5,Tiers_list!$A:$BC,MATCH($A16,Tiers_list!$2:$2,0),FALSE)*I16/10)*(1-'Proposal Form Tier 2-12'!$B$16-'Proposal Form Tier 2-12'!$B$14) -> 0 | K16: =IF('Proposal Form Tier 2-12'!$B$5<>"Tier - 1 - 10",VLOOKUP('Proposal Form Tier 2-12'!$B$5,Tiers_list!$A:$BC,MATCH($A16,Tiers_list!$2:$2,0),FALSE)*L16*'Proposal Form Tier 2-12'!B$12,VLOOKUP('Proposal Form Tier 2-12'!$B$5,Tiers_list!$A:$BC,MATCH($A16,Tiers_list!$2:$2,0),FALSE)*'Proposal Form Tier 2-12'!B$12*L16/10)*(1-'Proposal Form Tier 2-12'!$B$16-'Proposal Form Tier 2-12'!$B$14) -> 0 | L16: =SUM(M16:O16) -> 0 | M16: =IF($I16>0,'Proposal Form Tier 2-12'!$B$8,0) -> 0 | N16: =IF($I16>0,'Proposal Form Tier 2-12'!$B$9,0) -> 0 | O16: =IF($I16>0,'Proposal Form Tier 2-12'!$B$10,0) -> 0 | P16: =+(J16/(1-'Proposal Form Tier 2-12'!$B$16-'Proposal Form Tier 2-12'!$B$14))+(K16/(1-'Proposal Form Tier 2-12'!$B$16-'Proposal Form Tier 2-12'!$B$14)) -> 0
A17: 200-50044 | B17: ACS Software | C17: ACS Enterprise Hardware Configuration UI | D17: ACS User Login Profile Management Module | E17: =+'Detail_Proposal_tier 1'!E17 -> Create/Edit/Deactivate ACS Users and assign ACS User function/data access rights by ACS User/ACS User Profile type (Super Admin, Admin, Super Investigator, Investigator, Super Production user, Production user, etc.) A user profile is a type of user(s) that has been defined to perform specified functions within the ACS Enterprise software suite. | F17: =+'Detail_Proposal_tier 1'!F17 -> Administrators can create, edit, and deactivate ACS user accounts and assign each user precise function and data access rights that determine which modules, sites, and operations they can perform within the platform. With role-based permissions, automated lockout on permission changes, and a full audit trail of every modification, organizations maintain tight control over who can administer the system and ensure that access rights always reflect current responsibilities. | G17: Required | H17: ea. | I17: =+'Proposal Form Tier 2-12'!$B$6 -> 1 | J17: =IF('Proposal Form Tier 2-12'!$B$5<>"Tier - 1 - 10",VLOOKUP('Proposal Form Tier 2-12'!$B$5,Tiers_list!$A:$BC,MATCH($A17,Tiers_list!$2:$2,0),FALSE)*I17,VLOOKUP('Proposal Form Tier 2-12'!$B$5,Tiers_list!$A:$BC,MATCH($A17,Tiers_list!$2:$2,0),FALSE)*I17/10)*(1-'Proposal Form Tier 2-12'!$B$16-'Proposal Form Tier 2-12'!$B$14) -> 534.375 | K17: =IF('Proposal Form Tier 2-12'!$B$5<>"Tier - 1 - 10",VLOOKUP('Proposal Form Tier 2-12'!$B$5,Tiers_list!$A:$BC,MATCH($A17,Tiers_list!$2:$2,0),FALSE)*L17*'Proposal Form Tier 2-12'!B$12,VLOOKUP('Proposal Form Tier 2-12'!$B$5,Tiers_list!$A:$BC,MATCH($A17,Tiers_list!$2:$2,0),FALSE)*'Proposal Form Tier 2-12'!B$12*L17/10)*(1-'Proposal Form Tier 2-12'!$B$16-'Proposal Form Tier 2-12'!$B$14) -> 267.1875 | L17: =SUM(M17:O17) -> 1 | M17: =IF($I17>0,'Proposal Form Tier 2-12'!$B$8,0) -> 1 | N17: =IF($I17>0,'Proposal Form Tier 2-12'!$B$9,0) -> 0 | O17: =IF($I17>0,'Proposal Form Tier 2-12'!$B$10,0) -> 0 | P17: =+(J17/(1-'Proposal Form Tier 2-12'!$B$16-'Proposal Form Tier 2-12'!$B$14))+(K17/(1-'Proposal Form Tier 2-12'!$B$16-'Proposal Form Tier 2-12'!$B$14)) -> 1068.75
A18: 200-50045 | B18: ACS Software | C18: ACS Enterprise Hardware Configuration UI | D18: ACS Controller / User Territory Management Module | E18: =+'Detail_Proposal_tier 1'!E18 -> Manage Territory's by geographic region, state, time zone, defined controller properties and/or by User. Assign ACS controllers to a Territory(s) and assign Territory(s) to an ACS User(s) supporting assignment of ACS functions to be executed/managed. | F18: =+'Detail_Proposal_tier 1'!F18 -> 0 | G18: Required | H18: ea. | I18: =+'Proposal Form Tier 2-12'!$B$6 -> 1 | J18: =IF('Proposal Form Tier 2-12'!$B$5<>"Tier - 1 - 10",VLOOKUP('Proposal Form Tier 2-12'!$B$5,Tiers_list!$A:$BC,MATCH($A18,Tiers_list!$2:$2,0),FALSE)*I18,VLOOKUP('Proposal Form Tier 2-12'!$B$5,Tiers_list!$A:$BC,MATCH($A18,Tiers_list!$2:$2,0),FALSE)*I18/10)*(1-'Proposal Form Tier 2-12'!$B$16-'Proposal Form Tier 2-12'!$B$14) -> 534.375 | K18: =IF('Proposal Form Tier 2-12'!$B$5<>"Tier - 1 - 10",VLOOKUP('Proposal Form Tier 2-12'!$B$5,Tiers_list!$A:$BC,MATCH($A18,Tiers_list!$2:$2,0),FALSE)*L18*'Proposal Form Tier 2-12'!B$12,VLOOKUP('Proposal Form Tier 2-12'!$B$5,Tiers_list!$A:$BC,MATCH($A18,Tiers_list!$2:$2,0),FALSE)*'Proposal Form Tier 2-12'!B$12*L18/10)*(1-'Proposal Form Tier 2-12'!$B$16-'Proposal Form Tier 2-12'!$B$14) -> 267.1875 | L18: =SUM(M18:O18) -> 1 | M18: =IF($I18>0,'Proposal Form Tier 2-12'!$B$8,0) -> 1 | N18: =IF($I18>0,'Proposal Form Tier 2-12'!$B$9,0) -> 0 | O18: =IF($I18>0,'Proposal Form Tier 2-12'!$B$10,0) -> 0 | P18: =+(J18/(1-'Proposal Form Tier 2-12'!$B$16-'Proposal Form Tier 2-12'!$B$14))+(K18/(1-'Proposal Form Tier 2-12'!$B$16-'Proposal Form Tier 2-12'!$B$14)) -> 1068.75
C19: ACS Enterprise Hardware Configuration UI Total | I19: =SUBTOTAL(9,I2:I18) -> 3 | J19: =SUBTOTAL(9,J2:J18) -> 9618.75 | K19: =SUBTOTAL(9,K2:K18) -> 4809.375 | L19: =SUBTOTAL(9,L2:L18) -> 3 | M19: =SUBTOTAL(9,M2:M18) -> 3 | N19: =SUBTOTAL(9,N2:N18) -> 0 | O19: =SUBTOTAL(9,O2:O18) -> 0 | P19: =SUBTOTAL(9,P2:P18) -> 19237.5
A20: 200-50046 | B20: ACS Software | C20: ACS Enterprise Integrations | D20: Integration to External ACS Hardware / Software Certificate / Key software / system Module | E20: =+'Detail_Proposal_tier 1'!E20 -> ACS controller and MMR 2.0 reader and ACS controller and ACS Enterprise software TLS Communication and Data Encryption External System scheduled or on-demand key/cert generation and management (One-Time and Annual Pricing TBD) | F20: =+'Detail_Proposal_tier 1'!F20 -> ACS Cloud Enterprise secures all communications between controllers, Readers and the cloud using mutual TLS — which is the strongest encryption. This ensures credential data, control commands, and event messages are protected against interception and replay attacks. Certificates are stored in cloud key vaults with policy-controlled access and automated rotation, and all authentication activity is logged, giving organizations the cryptographic foundation needed to meet demanding security and compliance requirements. | G20: Required | H20: ea. | I20: =+'Proposal Form Tier 2-12'!$B$6 -> 1 | J20: =IF('Proposal Form Tier 2-12'!$B$5<>"Tier - 1 - 10",VLOOKUP('Proposal Form Tier 2-12'!$B$5,Tiers_list!$A:$BC,MATCH($A20,Tiers_list!$2:$2,0),FALSE)*I20,VLOOKUP('Proposal Form Tier 2-12'!$B$5,Tiers_list!$A:$BC,MATCH($A20,Tiers_list!$2:$2,0),FALSE)*I20/10)*(1-'Proposal Form Tier 2-12'!$B$16-'Proposal Form Tier 2-12'!$B$14) -> 712.5 | K20: =IF('Proposal Form Tier 2-12'!$B$5<>"Tier - 1 - 10",VLOOKUP('Proposal Form Tier 2-12'!$B$5,Tiers_list!$A:$BC,MATCH($A20,Tiers_list!$2:$2,0),FALSE)*L20*'Proposal Form Tier 2-12'!B$12,VLOOKUP('Proposal Form Tier 2-12'!$B$5,Tiers_list!$A:$BC,MATCH($A20,Tiers_list!$2:$2,0),FALSE)*'Proposal Form Tier 2-12'!B$12*L20/10)*(1-'Proposal Form Tier 2-12'!$B$16-'Proposal Form Tier 2-12'!$B$14) -> 356.25 | L20: =SUM(M20:O20) -> 1 | M20: =IF($I20>0,'Proposal Form Tier 2-12'!$B$8,0) -> 1 | N20: =IF($I20>0,'Proposal Form Tier 2-12'!$B$9,0) -> 0 | O20: =IF($I20>0,'Proposal Form Tier 2-12'!$B$10,0) -> 0 | P20: =+(J20/(1-'Proposal Form Tier 2-12'!$B$16-'Proposal Form Tier 2-12'!$B$14))+(K20/(1-'Proposal Form Tier 2-12'!$B$16-'Proposal Form Tier 2-12'!$B$14)) -> 1425
A21: 200-50047 | B21: ACS Software | C21: ACS Enterprise Integrations | D21: ACS system data cloud integration to 3rd party systems ACS Event Messages, Credentials and User Logs Module | E21: =+'Detail_Proposal_tier 1'!E21 -> Define, Parse and forward ACS Event Messages collected/received by ACS controllers via a API / Windows / Micro Service to 3rd party alarm/event message monitoring systems in the following (ContactID, Extended Contact ID, others TBD) formats (MAStermind supported today, but develop interfaces to Genetec, MAStermind, Milestone, Avigilon and others.) | F21: =+'Detail_Proposal_tier 1'!F21 -> ACS Cloud Enterprise collects, parses, and categorizes every event message generated by ACS controllers — including credential reads, door events, alarms, health checks, and system actions — and routes them to the appropriate destinations in real time. Operators can configure exactly which message types are forwarded to internal databases, external monitoring platforms, or third-party systems, with full control over message priority, credential data masking, and failover queuing to ensure no critical event is lost even when downstream systems are temporarily unavailable. | G21: Optional | H21: ea. | I21: =_xlfn.XLOOKUP($A21,'Proposal Form Tier 2-12'!$C:$C,'Proposal Form Tier 2-12'!$B:$B,0,0) -> 0 | J21: =IF('Proposal Form Tier 2-12'!$B$5<>"Tier - 1 - 10",VLOOKUP('Proposal Form Tier 2-12'!$B$5,Tiers_list!$A:$BC,MATCH($A21,Tiers_list!$2:$2,0),FALSE)*I21,VLOOKUP('Proposal Form Tier 2-12'!$B$5,Tiers_list!$A:$BC,MATCH($A21,Tiers_list!$2:$2,0),FALSE)*I21/10)*(1-'Proposal Form Tier 2-12'!$B$16-'Proposal Form Tier 2-12'!$B$14) -> 0 | K21: =IF('Proposal Form Tier 2-12'!$B$5<>"Tier - 1 - 10",VLOOKUP('Proposal Form Tier 2-12'!$B$5,Tiers_list!$A:$BC,MATCH($A21,Tiers_list!$2:$2,0),FALSE)*L21*'Proposal Form Tier 2-12'!B$12,VLOOKUP('Proposal Form Tier 2-12'!$B$5,Tiers_list!$A:$BC,MATCH($A21,Tiers_list!$2:$2,0),FALSE)*'Proposal Form Tier 2-12'!B$12*L21/10)*(1-'Proposal Form Tier 2-12'!$B$16-'Proposal Form Tier 2-12'!$B$14) -> 0 | L21: =SUM(M21:O21) -> 0 | M21: =IF($I21>0,'Proposal Form Tier 2-12'!$B$8,0) -> 0 | N21: =IF($I21>0,'Proposal Form Tier 2-12'!$B$9,0) -> 0 | O21: =IF($I21>0,'Proposal Form Tier 2-12'!$B$10,0) -> 0 | P21: =+(J21/(1-'Proposal Form Tier 2-12'!$B$16-'Proposal Form Tier 2-12'!$B$14))+(K21/(1-'Proposal Form Tier 2-12'!$B$16-'Proposal Form Tier 2-12'!$B$14)) -> 0
A22: 200-50048 | B22: ACS Software | C22: ACS Enterprise Integrations | D22: ACS system data non cloud integration / parser to 3rd party systems ACS Event Messages, Credentials and User Logs Module | E22: =+'Detail_Proposal_tier 1'!E22 -> Transmission of ACS Event Messages to non-cloud 3rd party monitoring (MAStermind) applications (Windows Service). (Integration fees may apply) | F22: =+'Detail_Proposal_tier 1'!F22 -> Organizations using non-cloud monitoring platforms such as MAStermind or similar systems can seamlessly receive ACS event messages through a configurable, authenticated integration that supports multiple server endpoints with automatic failover. Operators define server groups, set message criticality levels, and control credential data exposure in payloads, ensuring that third-party monitoring teams receive exactly the right alerts in real time — without manual intervention and without compromising sensitive cardholder data. | G22: Required. Choose QTY | H22: ea. | I22: =_xlfn.XLOOKUP($A22,'Proposal Form Tier 2-12'!$C:$C,'Proposal Form Tier 2-12'!$B:$B,0,0) -> 1 | J22: =IF('Proposal Form Tier 2-12'!$B$5<>"Tier - 1 - 10",VLOOKUP('Proposal Form Tier 2-12'!$B$5,Tiers_list!$A:$BC,MATCH($A22,Tiers_list!$2:$2,0),FALSE)*I22,VLOOKUP('Proposal Form Tier 2-12'!$B$5,Tiers_list!$A:$BC,MATCH($A22,Tiers_list!$2:$2,0),FALSE)*I22/10)*(1-'Proposal Form Tier 2-12'!$B$16-'Proposal Form Tier 2-12'!$B$14) -> 712.5 | K22: =IF('Proposal Form Tier 2-12'!$B$5<>"Tier - 1 - 10",VLOOKUP('Proposal Form Tier 2-12'!$B$5,Tiers_list!$A:$BC,MATCH($A22,Tiers_list!$2:$2,0),FALSE)*L22*'Proposal Form Tier 2-12'!B$12,VLOOKUP('Proposal Form Tier 2-12'!$B$5,Tiers_list!$A:$BC,MATCH($A22,Tiers_list!$2:$2,0),FALSE)*'Proposal Form Tier 2-12'!B$12*L22/10)*(1-'Proposal Form Tier 2-12'!$B$16-'Proposal Form Tier 2-12'!$B$14) -> 356.25 | L22: =SUM(M22:O22) -> 1 | M22: =IF($I22>0,'Proposal Form Tier 2-12'!$B$8,0) -> 1 | N22: =IF($I22>0,'Proposal Form Tier 2-12'!$B$9,0) -> 0 | O22: =IF($I22>0,'Proposal Form Tier 2-12'!$B$10,0) -> 0 | P22: =+(J22/(1-'Proposal Form Tier 2-12'!$B$16-'Proposal Form Tier 2-12'!$B$14))+(K22/(1-'Proposal Form Tier 2-12'!$B$16-'Proposal Form Tier 2-12'!$B$14)) -> 1425
A23: 200-50049 | B23: ACS Software | C23: ACS Enterprise Integrations | D23: Email/Text EMR Notifier Service Module | E23: =+'Detail_Proposal_tier 1'!E23 -> EMR sends an email or text to defined Email Address(s)/Mobile #(s) of ACS events selected | F23: =+'Detail_Proposal_tier 1'!F23 -> Security teams, facility managers, and operations staff can receive instant email or SMS notifications for any ACS event classified as critical — delivered directly to configured user groups without requiring access to the monitoring platform. Operators define notification recipient lists, assign message criticality categories, and configure which alarms trigger immediate outreach, ensuring that the right people are alerted at the right time regardless of whether they are actively monitoring the system dashboard. | G23: Optional | H23: ea. | I23: =_xlfn.XLOOKUP($A23,'Proposal Form Tier 2-12'!$C:$C,'Proposal Form Tier 2-12'!$B:$B,0,0) -> 0 | J23: =IF('Proposal Form Tier 2-12'!$B$5<>"Tier - 1 - 10",VLOOKUP('Proposal Form Tier 2-12'!$B$5,Tiers_list!$A:$BC,MATCH($A23,Tiers_list!$2:$2,0),FALSE)*I23,VLOOKUP('Proposal Form Tier 2-12'!$B$5,Tiers_list!$A:$BC,MATCH($A23,Tiers_list!$2:$2,0),FALSE)*I23/10)*(1-'Proposal Form Tier 2-12'!$B$16-'Proposal Form Tier 2-12'!$B$14) -> 0 | K23: =IF('Proposal Form Tier 2-12'!$B$5<>"Tier - 1 - 10",VLOOKUP('Proposal Form Tier 2-12'!$B$5,Tiers_list!$A:$BC,MATCH($A23,Tiers_list!$2:$2,0),FALSE)*L23*'Proposal Form Tier 2-12'!B$12,VLOOKUP('Proposal Form Tier 2-12'!$B$5,Tiers_list!$A:$BC,MATCH($A23,Tiers_list!$2:$2,0),FALSE)*'Proposal Form Tier 2-12'!B$12*L23/10)*(1-'Proposal Form Tier 2-12'!$B$16-'Proposal Form Tier 2-12'!$B$14) -> 0 | L23: =SUM(M23:O23) -> 0 | M23: =IF($I23>0,'Proposal Form Tier 2-12'!$B$8,0) -> 0 | N23: =IF($I23>0,'Proposal Form Tier 2-12'!$B$9,0) -> 0 | O23: =IF($I23>0,'Proposal Form Tier 2-12'!$B$10,0) -> 0 | P23: =+(J23/(1-'Proposal Form Tier 2-12'!$B$16-'Proposal Form Tier 2-12'!$B$14))+(K23/(1-'Proposal Form Tier 2-12'!$B$16-'Proposal Form Tier 2-12'!$B$14)) -> 0
A24: 200-50050 | B24: ACS Software | C24: ACS Enterprise Integrations | D24: ACS controller Reader Remote Credential Lookup with Local learn Module | E24: =+'Detail_Proposal_tier 1'!E24 -> Remote lookup of Accepted, Rejected and Suspect Credentials in ACS DB. | F24: =+'Detail_Proposal_tier 1'!F24 -> When a credential is presented at a reader configured for external match validation, ACS Cloud Enterprise forwards the request to the Parabit Cloud Enterprise in real time, retrieves the allow or reject decision, and acts on it immediately . This enables organizations to maintain centralized, organization-wide credential authority in an external system (such as a financial institution's BIN database) while still leveraging the speed and resilience of local controller enforcement. | G24: Optional | H24: ea. | I24: =_xlfn.XLOOKUP($A24,'Proposal Form Tier 2-12'!$C:$C,'Proposal Form Tier 2-12'!$B:$B,0,0) -> 0 | J24: =IF('Proposal Form Tier 2-12'!$B$5<>"Tier - 1 - 10",VLOOKUP('Proposal Form Tier 2-12'!$B$5,Tiers_list!$A:$BC,MATCH($A24,Tiers_list!$2:$2,0),FALSE)*I24,VLOOKUP('Proposal Form Tier 2-12'!$B$5,Tiers_list!$A:$BC,MATCH($A24,Tiers_list!$2:$2,0),FALSE)*I24/10)*(1-'Proposal Form Tier 2-12'!$B$16-'Proposal Form Tier 2-12'!$B$14) -> 0 | K24: =IF('Proposal Form Tier 2-12'!$B$5<>"Tier - 1 - 10",VLOOKUP('Proposal Form Tier 2-12'!$B$5,Tiers_list!$A:$BC,MATCH($A24,Tiers_list!$2:$2,0),FALSE)*L24*'Proposal Form Tier 2-12'!B$12,VLOOKUP('Proposal Form Tier 2-12'!$B$5,Tiers_list!$A:$BC,MATCH($A24,Tiers_list!$2:$2,0),FALSE)*'Proposal Form Tier 2-12'!B$12*L24/10)*(1-'Proposal Form Tier 2-12'!$B$16-'Proposal Form Tier 2-12'!$B$14) -> 0 | L24: =SUM(M24:O24) -> 0 | M24: =IF($I24>0,'Proposal Form Tier 2-12'!$B$8,0) -> 0 | N24: =IF($I24>0,'Proposal Form Tier 2-12'!$B$9,0) -> 0 | O24: =IF($I24>0,'Proposal Form Tier 2-12'!$B$10,0) -> 0 | P24: =+(J24/(1-'Proposal Form Tier 2-12'!$B$16-'Proposal Form Tier 2-12'!$B$14))+(K24/(1-'Proposal Form Tier 2-12'!$B$16-'Proposal Form Tier 2-12'!$B$14)) -> 0
A25: 200-50051 | B25: ACS Software | C25: ACS Enterprise Integrations | D25: ACS Enterprise NYCE BIN Table Import / Optimization Module | E25: =+'Detail_Proposal_tier 1'!E25 -> Monthly download and distribution of the NYCE BIN Table to all ACS Cloud Enterprise Users. Client ACS Cloud Enterprise software detects file update, authenticates and automatically downloads and optimizes the file, then schedules the initialization of the file into all designated ACS controllers. | F25: =+'Detail_Proposal_tier 1'!F25 -> ACS Cloud Enterprise automates the monthly download and distribution of the NYCE BIN table to all configured controllers across every enterprise site, ensuring that every reader has an up-to-date financial credential reference without requiring manual file transfers or on-site updates. This eliminates the operational risk of controllers running outdated BIN data, reduces the administrative overhead of managing credential table updates at scale, and ensures consistent access decisions across the entire estate. | G25: Required | H25: ea. | I25: =+'Proposal Form Tier 2-12'!$B$6 -> 1 | J25: =IF('Proposal Form Tier 2-12'!$B$5<>"Tier - 1 - 10",VLOOKUP('Proposal Form Tier 2-12'!$B$5,Tiers_list!$A:$BC,MATCH($A25,Tiers_list!$2:$2,0),FALSE)*I25,VLOOKUP('Proposal Form Tier 2-12'!$B$5,Tiers_list!$A:$BC,MATCH($A25,Tiers_list!$2:$2,0),FALSE)*I25/10)*(1-'Proposal Form Tier 2-12'!$B$16-'Proposal Form Tier 2-12'!$B$14) -> 534.375 | K25: =IF('Proposal Form Tier 2-12'!$B$5<>"Tier - 1 - 10",VLOOKUP('Proposal Form Tier 2-12'!$B$5,Tiers_list!$A:$BC,MATCH($A25,Tiers_list!$2:$2,0),FALSE)*L25*'Proposal Form Tier 2-12'!B$12,VLOOKUP('Proposal Form Tier 2-12'!$B$5,Tiers_list!$A:$BC,MATCH($A25,Tiers_list!$2:$2,0),FALSE)*'Proposal Form Tier 2-12'!B$12*L25/10)*(1-'Proposal Form Tier 2-12'!$B$16-'Proposal Form Tier 2-12'!$B$14) -> 267.1875 | L25: =SUM(M25:O25) -> 1 | M25: =IF($I25>0,'Proposal Form Tier 2-12'!$B$8,0) -> 1 | N25: =IF($I25>0,'Proposal Form Tier 2-12'!$B$9,0) -> 0 | O25: =IF($I25>0,'Proposal Form Tier 2-12'!$B$10,0) -> 0 | P25: =+(J25/(1-'Proposal Form Tier 2-12'!$B$16-'Proposal Form Tier 2-12'!$B$14))+(K25/(1-'Proposal Form Tier 2-12'!$B$16-'Proposal Form Tier 2-12'!$B$14)) -> 1068.75
A26: 200-50052 | B26: ACS Software | C26: ACS Enterprise Integrations | D26: KAL ATM Management Software Integration Module | E26: =+'Detail_Proposal_tier 1'!E26 -> Remote 6/8 Digit BIN Lookup, Site Lock down and Site Open commands | F26: =+'Detail_Proposal_tier 1'!F26 -> Operators can execute remote 6- or 8-digit BIN lookup queries against any controller and issue immediate site-wide lockdown or open commands from the cloud — giving security teams the ability to respond to threat events or operational emergencies in seconds without dispatching field personnel. All commands are authenticated, logged, and reversible, ensuring that emergency access control actions are both fast and fully accountable. | G26: Required | H26: ea. | I26: =+'Proposal Form Tier 2-12'!$B$6 -> 1 | J26: =IF('Proposal Form Tier 2-12'!$B$5<>"Tier - 1 - 10",VLOOKUP('Proposal Form Tier 2-12'!$B$5,Tiers_list!$A:$BC,MATCH($A26,Tiers_list!$2:$2,0),FALSE)*I26,VLOOKUP('Proposal Form Tier 2-12'!$B$5,Tiers_list!$A:$BC,MATCH($A26,Tiers_list!$2:$2,0),FALSE)*I26/10)*(1-'Proposal Form Tier 2-12'!$B$16-'Proposal Form Tier 2-12'!$B$14) -> 356.25 | K26: =IF('Proposal Form Tier 2-12'!$B$5<>"Tier - 1 - 10",VLOOKUP('Proposal Form Tier 2-12'!$B$5,Tiers_list!$A:$BC,MATCH($A26,Tiers_list!$2:$2,0),FALSE)*L26*'Proposal Form Tier 2-12'!B$12,VLOOKUP('Proposal Form Tier 2-12'!$B$5,Tiers_list!$A:$BC,MATCH($A26,Tiers_list!$2:$2,0),FALSE)*'Proposal Form Tier 2-12'!B$12*L26/10)*(1-'Proposal Form Tier 2-12'!$B$16-'Proposal Form Tier 2-12'!$B$14) -> 178.125 | L26: =SUM(M26:O26) -> 1 | M26: =IF($I26>0,'Proposal Form Tier 2-12'!$B$8,0) -> 1 | N26: =IF($I26>0,'Proposal Form Tier 2-12'!$B$9,0) -> 0 | O26: =IF($I26>0,'Proposal Form Tier 2-12'!$B$10,0) -> 0 | P26: =+(J26/(1-'Proposal Form Tier 2-12'!$B$16-'Proposal Form Tier 2-12'!$B$14))+(K26/(1-'Proposal Form Tier 2-12'!$B$16-'Proposal Form Tier 2-12'!$B$14)) -> 712.5
A27: 200-50053 | B27: ACS Software | C27: ACS Enterprise Integrations | D27: HR & Time Attendance Credential Integration Module | E27: =+'Detail_Proposal_tier 1'!E27 -> Credential Integration into 3rd Party systems - HR, Time and Attendance, Payroll, Transaction, Credential Management, etc. | F27: =+'Detail_Proposal_tier 1'!F27 -> ACS Cloud Enterprise can synchronize credential and access event data with external HR, time-and-attendance, payroll, and identity management systems — ensuring that access rights automatically reflect employment status, shift schedules, and organizational changes without requiring duplicate data entry across platforms. This integration eliminates the gaps between physical security and HR processes, reduces the risk of unauthorized access from stale credentials, and provides a unified view of who accessed what and when across interconnected enterprise systems. | G27: Optional | H27: ea. | I27: =_xlfn.XLOOKUP($A27,'Proposal Form Tier 2-12'!$C:$C,'Proposal Form Tier 2-12'!$B:$B,0,0) -> 0 | J27: =IF('Proposal Form Tier 2-12'!$B$5<>"Tier - 1 - 10",VLOOKUP('Proposal Form Tier 2-12'!$B$5,Tiers_list!$A:$BC,MATCH($A27,Tiers_list!$2:$2,0),FALSE)*I27,VLOOKUP('Proposal Form Tier 2-12'!$B$5,Tiers_list!$A:$BC,MATCH($A27,Tiers_list!$2:$2,0),FALSE)*I27/10)*(1-'Proposal Form Tier 2-12'!$B$16-'Proposal Form Tier 2-12'!$B$14) -> 0 | K27: =IF('Proposal Form Tier 2-12'!$B$5<>"Tier - 1 - 10",VLOOKUP('Proposal Form Tier 2-12'!$B$5,Tiers_list!$A:$BC,MATCH($A27,Tiers_list!$2:$2,0),FALSE)*L27*'Proposal Form Tier 2-12'!B$12,VLOOKUP('Proposal Form Tier 2-12'!$B$5,Tiers_list!$A:$BC,MATCH($A27,Tiers_list!$2:$2,0),FALSE)*'Proposal Form Tier 2-12'!B$12*L27/10)*(1-'Proposal Form Tier 2-12'!$B$16-'Proposal Form Tier 2-12'!$B$14) -> 0 | L27: =SUM(M27:O27) -> 0 | M27: =IF($I27>0,'Proposal Form Tier 2-12'!$B$8,0) -> 0 | N27: =IF($I27>0,'Proposal Form Tier 2-12'!$B$9,0) -> 0 | O27: =IF($I27>0,'Proposal Form Tier 2-12'!$B$10,0) -> 0 | P27: =+(J27/(1-'Proposal Form Tier 2-12'!$B$16-'Proposal Form Tier 2-12'!$B$14))+(K27/(1-'Proposal Form Tier 2-12'!$B$16-'Proposal Form Tier 2-12'!$B$14)) -> 0
A28: 200-50054 | B28: ACS Software | C28: ACS Enterprise Integrations | D28: ACS Hardware and Facility Sensor Data Integration(s) Module | E28: =+'Detail_Proposal_tier 1'!E28 -> Facility Sensors integrated to an ACS controller and with Third Party Hardware Data Point (ATM, NVR, Alarm system, etc.) integrations for Loitering, Light, Door, Ingress, Egress, SkimGard, etc. supervision | F28: =+'Detail_Proposal_tier 1'!F28 -> ACS Cloud Enterprise connects facility sensors and third-party hardware devices to the ACS controller ecosystem, enabling sensor-triggered events — such as light sensor readings, presence detection, or environmental alerts — to be captured, processed, and forwarded alongside standard access control events. This gives operators a unified operational picture that combines physical security with facility intelligence, supporting use cases from loitering detection and single-access enforcement to automated alarm responses tied to environmental conditions. | G28: Optional | H28: ea. | I28: =_xlfn.XLOOKUP($A28,'Proposal Form Tier 2-12'!$C:$C,'Proposal Form Tier 2-12'!$B:$B,0,0) -> 0 | J28: =IF('Proposal Form Tier 2-12'!$B$5<>"Tier - 1 - 10",VLOOKUP('Proposal Form Tier 2-12'!$B$5,Tiers_list!$A:$BC,MATCH($A28,Tiers_list!$2:$2,0),FALSE)*I28,VLOOKUP('Proposal Form Tier 2-12'!$B$5,Tiers_list!$A:$BC,MATCH($A28,Tiers_list!$2:$2,0),FALSE)*I28/10)*(1-'Proposal Form Tier 2-12'!$B$16-'Proposal Form Tier 2-12'!$B$14) -> 0 | K28: =IF('Proposal Form Tier 2-12'!$B$5<>"Tier - 1 - 10",VLOOKUP('Proposal Form Tier 2-12'!$B$5,Tiers_list!$A:$BC,MATCH($A28,Tiers_list!$2:$2,0),FALSE)*L28*'Proposal Form Tier 2-12'!B$12,VLOOKUP('Proposal Form Tier 2-12'!$B$5,Tiers_list!$A:$BC,MATCH($A28,Tiers_list!$2:$2,0),FALSE)*'Proposal Form Tier 2-12'!B$12*L28/10)*(1-'Proposal Form Tier 2-12'!$B$16-'Proposal Form Tier 2-12'!$B$14) -> 0 | L28: =SUM(M28:O28) -> 0 | M28: =IF($I28>0,'Proposal Form Tier 2-12'!$B$8,0) -> 0 | N28: =IF($I28>0,'Proposal Form Tier 2-12'!$B$9,0) -> 0 | O28: =IF($I28>0,'Proposal Form Tier 2-12'!$B$10,0) -> 0 | P28: =+(J28/(1-'Proposal Form Tier 2-12'!$B$16-'Proposal Form Tier 2-12'!$B$14))+(K28/(1-'Proposal Form Tier 2-12'!$B$16-'Proposal Form Tier 2-12'!$B$14)) -> 0
C29: ACS Enterprise Integrations Total | I29: =SUBTOTAL(9,I20:I28) -> 4 | J29: =SUBTOTAL(9,J20:J28) -> 2315.625 | K29: =SUBTOTAL(9,K20:K28) -> 1157.8125 | L29: =SUBTOTAL(9,L20:L28) -> 4 | M29: =SUBTOTAL(9,M20:M28) -> 4 | N29: =SUBTOTAL(9,N20:N28) -> 0 | O29: =SUBTOTAL(9,O20:O28) -> 0 | P29: =SUBTOTAL(9,P20:P28) -> 4631.25
A30: 200-50055 | B30: ACS Software | C30: ACS Enterprise Hardware and Software System Supervision and Activity Logs | D30: ACS User Data changed / functions executed Activity Tracking Module | E30: =+'Detail_Proposal_tier 1'!E30 -> ACS User Data changed / functions executed Activity Tracking | F30: =+'Detail_Proposal_tier 1'!F30 -> Every action taken by an ACS user — from configuration changes and schedule updates to credential assignments and system logins — is automatically captured and stored in a structured activity log that records who did what, when, and from where. Administrators and auditors can search, filter, and export these logs at any time, providing the complete chain of accountability needed for internal audits, compliance reviews, and security investigations without relying on manual record-keeping. | G30: Required | H30: ea. | I30: =+'Proposal Form Tier 2-12'!$B$6 -> 1 | J30: =IF('Proposal Form Tier 2-12'!$B$5<>"Tier - 1 - 10",VLOOKUP('Proposal Form Tier 2-12'!$B$5,Tiers_list!$A:$BC,MATCH($A30,Tiers_list!$2:$2,0),FALSE)*I30,VLOOKUP('Proposal Form Tier 2-12'!$B$5,Tiers_list!$A:$BC,MATCH($A30,Tiers_list!$2:$2,0),FALSE)*I30/10)*(1-'Proposal Form Tier 2-12'!$B$16-'Proposal Form Tier 2-12'!$B$14) -> 534.375 | K30: =IF('Proposal Form Tier 2-12'!$B$5<>"Tier - 1 - 10",VLOOKUP('Proposal Form Tier 2-12'!$B$5,Tiers_list!$A:$BC,MATCH($A30,Tiers_list!$2:$2,0),FALSE)*L30*'Proposal Form Tier 2-12'!B$12,VLOOKUP('Proposal Form Tier 2-12'!$B$5,Tiers_list!$A:$BC,MATCH($A30,Tiers_list!$2:$2,0),FALSE)*'Proposal Form Tier 2-12'!B$12*L30/10)*(1-'Proposal Form Tier 2-12'!$B$16-'Proposal Form Tier 2-12'!$B$14) -> 267.1875 | L30: =SUM(M30:O30) -> 1 | M30: =IF($I30>0,'Proposal Form Tier 2-12'!$B$8,0) -> 1 | N30: =IF($I30>0,'Proposal Form Tier 2-12'!$B$9,0) -> 0 | O30: =IF($I30>0,'Proposal Form Tier 2-12'!$B$10,0) -> 0 | P30: =+(J30/(1-'Proposal Form Tier 2-12'!$B$16-'Proposal Form Tier 2-12'!$B$14))+(K30/(1-'Proposal Form Tier 2-12'!$B$16-'Proposal Form Tier 2-12'!$B$14)) -> 1068.75
A31: 200-50056 | B31: ACS Software | C31: ACS Enterprise Hardware and Software System Supervision and Activity Logs | D31: ACS Hardware / Software availability monitoring Module | E31: =+'Detail_Proposal_tier 1'!E31 -> Monitor ACS controller and MMR 2.0 Reader Heartbeats and software / DB availability. Event Messages when ACS hardware, MMR 2.0 readers, ACS software and DB availability are not responding to heartbeat requests | F31: =+'Detail_Proposal_tier 1'!F31 -> ACS Cloud Enterprise continuously monitors the heartbeat signals from every controller and MMR 2.0 reader in the network, detecting offline devices within a configurable threshold and triggering immediate alerts to the responsible team before the issue impacts operations. Administrators can set monitoring intervals, configure escalation rules, view real-time device status dashboards, and access detailed uptime and connectivity reports — transforming device health monitoring from a reactive, manual process into a proactive, automated capability. | G31: Required | H31: ea. | I31: =+'Proposal Form Tier 2-12'!$B$6 -> 1 | J31: =IF('Proposal Form Tier 2-12'!$B$5<>"Tier - 1 - 10",VLOOKUP('Proposal Form Tier 2-12'!$B$5,Tiers_list!$A:$BC,MATCH($A31,Tiers_list!$2:$2,0),FALSE)*I31,VLOOKUP('Proposal Form Tier 2-12'!$B$5,Tiers_list!$A:$BC,MATCH($A31,Tiers_list!$2:$2,0),FALSE)*I31/10)*(1-'Proposal Form Tier 2-12'!$B$16-'Proposal Form Tier 2-12'!$B$14) -> 712.5 | K31: =IF('Proposal Form Tier 2-12'!$B$5<>"Tier - 1 - 10",VLOOKUP('Proposal Form Tier 2-12'!$B$5,Tiers_list!$A:$BC,MATCH($A31,Tiers_list!$2:$2,0),FALSE)*L31*'Proposal Form Tier 2-12'!B$12,VLOOKUP('Proposal Form Tier 2-12'!$B$5,Tiers_list!$A:$BC,MATCH($A31,Tiers_list!$2:$2,0),FALSE)*'Proposal Form Tier 2-12'!B$12*L31/10)*(1-'Proposal Form Tier 2-12'!$B$16-'Proposal Form Tier 2-12'!$B$14) -> 356.25 | L31: =SUM(M31:O31) -> 1 | M31: =IF($I31>0,'Proposal Form Tier 2-12'!$B$8,0) -> 1 | N31: =IF($I31>0,'Proposal Form Tier 2-12'!$B$9,0) -> 0 | O31: =IF($I31>0,'Proposal Form Tier 2-12'!$B$10,0) -> 0 | P31: =+(J31/(1-'Proposal Form Tier 2-12'!$B$16-'Proposal Form Tier 2-12'!$B$14))+(K31/(1-'Proposal Form Tier 2-12'!$B$16-'Proposal Form Tier 2-12'!$B$14)) -> 1425
A32: 200-50057 | B32: ACS Software | C32: ACS Enterprise Hardware and Software System Supervision and Activity Logs | D32: ACS Hardware Configuration Discrepancy Supervision, Notification and Auto Correct Service Module | E32: =+'Detail_Proposal_tier 1'!E32 -> Collect/Validate/Report/Notify of ACS hardware configuration discrepancies with configuration settings defined for each ACS / MMR 2.0 hardware device within the DB | F32: =+'Detail_Proposal_tier 1'!F32 -> ACS Cloud Enterprise automatically compares the configuration stored in the cloud database against the actual configuration resident in each controller, flagging any discrepancies in schedules, credential lists, network settings, or device assignments before they cause operational failures or compliance gaps. When a mismatch is detected, the system notifies the responsible team and provides the context needed to resolve the discrepancy quickly — eliminating the silent configuration drift that can undermine security and audit readiness in large, distributed deployments. | G32: Required | H32: ea. | I32: =+'Proposal Form Tier 2-12'!$B$6 -> 1 | J32: =IF('Proposal Form Tier 2-12'!$B$5<>"Tier - 1 - 10",VLOOKUP('Proposal Form Tier 2-12'!$B$5,Tiers_list!$A:$BC,MATCH($A32,Tiers_list!$2:$2,0),FALSE)*I32,VLOOKUP('Proposal Form Tier 2-12'!$B$5,Tiers_list!$A:$BC,MATCH($A32,Tiers_list!$2:$2,0),FALSE)*I32/10)*(1-'Proposal Form Tier 2-12'!$B$16-'Proposal Form Tier 2-12'!$B$14) -> 534.375 | K32: =IF('Proposal Form Tier 2-12'!$B$5<>"Tier - 1 - 10",VLOOKUP('Proposal Form Tier 2-12'!$B$5,Tiers_list!$A:$BC,MATCH($A32,Tiers_list!$2:$2,0),FALSE)*L32*'Proposal Form Tier 2-12'!B$12,VLOOKUP('Proposal Form Tier 2-12'!$B$5,Tiers_list!$A:$BC,MATCH($A32,Tiers_list!$2:$2,0),FALSE)*'Proposal Form Tier 2-12'!B$12*L32/10)*(1-'Proposal Form Tier 2-12'!$B$16-'Proposal Form Tier 2-12'!$B$14) -> 267.1875 | L32: =SUM(M32:O32) -> 1 | M32: =IF($I32>0,'Proposal Form Tier 2-12'!$B$8,0) -> 1 | N32: =IF($I32>0,'Proposal Form Tier 2-12'!$B$9,0) -> 0 | O32: =IF($I32>0,'Proposal Form Tier 2-12'!$B$10,0) -> 0 | P32: =+(J32/(1-'Proposal Form Tier 2-12'!$B$16-'Proposal Form Tier 2-12'!$B$14))+(K32/(1-'Proposal Form Tier 2-12'!$B$16-'Proposal Form Tier 2-12'!$B$14)) -> 1068.75
A33: 200-50058 | B33: ACS Software | C33: ACS Enterprise Hardware and Software System Supervision and Activity Logs | D33: Suspend distribution of Select or All Event Messages generated by ACS hardware and software Module | E33: =+'Detail_Proposal_tier 1'!E33 -> Suspend ACS hardware and software message transmission and/or integration configuration activation with an until date/time | F33: =+'Detail_Proposal_tier 1'!F33 -> Operators can temporarily suspend the transmission of ACS event messages and integration configurations to specified external systems for a defined window — providing a controlled way to pause outbound data flows during maintenance, system updates, or planned downtime without losing the underlying event data. All suppression activity is logged, suppressed server lists are visible for audit review, and normal transmission resumes automatically when the suppression window closes, ensuring that operational maintenance never creates permanent gaps in the monitoring record. | G33: Optional | H33: ea. | I33: =_xlfn.XLOOKUP($A33,'Proposal Form Tier 2-12'!$C:$C,'Proposal Form Tier 2-12'!$B:$B,0,0) -> 0 | J33: =IF('Proposal Form Tier 2-12'!$B$5<>"Tier - 1 - 10",VLOOKUP('Proposal Form Tier 2-12'!$B$5,Tiers_list!$A:$BC,MATCH($A33,Tiers_list!$2:$2,0),FALSE)*I33,VLOOKUP('Proposal Form Tier 2-12'!$B$5,Tiers_list!$A:$BC,MATCH($A33,Tiers_list!$2:$2,0),FALSE)*I33/10)*(1-'Proposal Form Tier 2-12'!$B$16-'Proposal Form Tier 2-12'!$B$14) -> 0 | K33: =IF('Proposal Form Tier 2-12'!$B$5<>"Tier - 1 - 10",VLOOKUP('Proposal Form Tier 2-12'!$B$5,Tiers_list!$A:$BC,MATCH($A33,Tiers_list!$2:$2,0),FALSE)*L33*'Proposal Form Tier 2-12'!B$12,VLOOKUP('Proposal Form Tier 2-12'!$B$5,Tiers_list!$A:$BC,MATCH($A33,Tiers_list!$2:$2,0),FALSE)*'Proposal Form Tier 2-12'!B$12*L33/10)*(1-'Proposal Form Tier 2-12'!$B$16-'Proposal Form Tier 2-12'!$B$14) -> 0 | L33: =SUM(M33:O33) -> 0 | M33: =IF($I33>0,'Proposal Form Tier 2-12'!$B$8,0) -> 0 | N33: =IF($I33>0,'Proposal Form Tier 2-12'!$B$9,0) -> 0 | O33: =IF($I33>0,'Proposal Form Tier 2-12'!$B$10,0) -> 0 | P33: =+(J33/(1-'Proposal Form Tier 2-12'!$B$16-'Proposal Form Tier 2-12'!$B$14))+(K33/(1-'Proposal Form Tier 2-12'!$B$16-'Proposal Form Tier 2-12'!$B$14)) -> 0
C34: ACS Enterprise Hardware and Software System Supervision and Activity Logs Total | I34: =SUBTOTAL(9,I30:I33) -> 3 | J34: =SUBTOTAL(9,J30:J33) -> 1781.25 | K34: =SUBTOTAL(9,K30:K33) -> 890.625 | L34: =SUBTOTAL(9,L30:L33) -> 3 | M34: =SUBTOTAL(9,M30:M33) -> 3 | N34: =SUBTOTAL(9,N30:N33) -> 0 | O34: =SUBTOTAL(9,O30:O33) -> 0 | P34: =SUBTOTAL(9,P30:P33) -> 3562.5
A35: 200-50059 | B35: ACS Software | C35: ACS Enterprise Mass Programming and Data Collection/Receiving Services | D35: =_xlfn.XLOOKUP(A35,Tiers_list!$2:$2,Tiers_list!$1:$1,,0) -> ACS Job Scheduler Service Module | E35: =+'Detail_Proposal_tier 1'!E35 -> ACS Users schedule effective date/time ACS controller/MMR 2.0 reader configurations to be executed, i.e., reader, I/O, 3rd party integrations, temporary override, configuration settings, weekly and holiday schedules, firmware updates, encryption key/certificate updates, data collection, etc. | F35: =+'Detail_Proposal_tier 1'!F35 -> Administrators and operators can schedule automated jobs to push configuration updates, initialize access schedules, and manage credential lists across any number of controllers and sites at a defined date and time — eliminating the need for manual, site-by-site initialization during operational hours. Jobs can be configured for one-time, weekly, or monthly recurrence, scoped to individual sites or entire territories, and monitored in real time with automatic retry logic and failure alerts, making large-scale system updates manageable, predictable, and audit-ready. | G35: Required. Choose QTY | H35: ea. | I35: =_xlfn.XLOOKUP($A35,'Proposal Form Tier 2-12'!$C:$C,'Proposal Form Tier 2-12'!$B:$B,0,0) -> 1 | J35: =IF('Proposal Form Tier 2-12'!$B$5<>"Tier - 1 - 10",VLOOKUP('Proposal Form Tier 2-12'!$B$5,Tiers_list!$A:$BC,MATCH($A35,Tiers_list!$2:$2,0),FALSE)*I35,VLOOKUP('Proposal Form Tier 2-12'!$B$5,Tiers_list!$A:$BC,MATCH($A35,Tiers_list!$2:$2,0),FALSE)*I35/10)*(1-'Proposal Form Tier 2-12'!$B$16-'Proposal Form Tier 2-12'!$B$14) -> 534.375 | K35: =IF('Proposal Form Tier 2-12'!$B$5<>"Tier - 1 - 10",VLOOKUP('Proposal Form Tier 2-12'!$B$5,Tiers_list!$A:$BC,MATCH($A35,Tiers_list!$2:$2,0),FALSE)*L35*'Proposal Form Tier 2-12'!B$12,VLOOKUP('Proposal Form Tier 2-12'!$B$5,Tiers_list!$A:$BC,MATCH($A35,Tiers_list!$2:$2,0),FALSE)*'Proposal Form Tier 2-12'!B$12*L35/10)*(1-'Proposal Form Tier 2-12'!$B$16-'Proposal Form Tier 2-12'!$B$14) -> 267.1875 | L35: =SUM(M35:O35) -> 1 | M35: =IF($I35>0,'Proposal Form Tier 2-12'!$B$8,0) -> 1 | N35: =IF($I35>0,'Proposal Form Tier 2-12'!$B$9,0) -> 0 | O35: =IF($I35>0,'Proposal Form Tier 2-12'!$B$10,0) -> 0 | P35: =+(J35/(1-'Proposal Form Tier 2-12'!$B$16-'Proposal Form Tier 2-12'!$B$14))+(K35/(1-'Proposal Form Tier 2-12'!$B$16-'Proposal Form Tier 2-12'!$B$14)) -> 1068.75
A36: 200-50060 | B36: ACS Software | C36: ACS Enterprise Mass Programming and Data Collection/Receiving Services | D36: =_xlfn.XLOOKUP(A36,Tiers_list!$2:$2,Tiers_list!$1:$1,,0) -> AFH / Data Collection Service Module | E36: =+'Detail_Proposal_tier 1'!E36 -> Collect/receive ACS hardware / software status Event Messages, Credential Events, User activity and writes stores them within the ACS SQL DB. | F36: =+'Detail_Proposal_tier 1'!F36 -> ACS Cloud Enterprise continuously collects and stores every event message and credential read event transmitted by ACS controllers in real time — covering access grants, rejections, alarms, device status updates, login events, and more — into a centralized, searchable audit trail. Operators can view, filter, and export this complete event history at any time, ensuring that the full record of what happened at every entrance, on every device, across every site is always available for security review, incident investigation, or compliance reporting. | G36: Required. Choose Qty | H36: ea. | I36: =_xlfn.XLOOKUP($A36,'Proposal Form Tier 2-12'!$C:$C,'Proposal Form Tier 2-12'!$B:$B,0,0) -> 1 | J36: =IF('Proposal Form Tier 2-12'!$B$5<>"Tier - 1 - 10",VLOOKUP('Proposal Form Tier 2-12'!$B$5,Tiers_list!$A:$BC,MATCH($A36,Tiers_list!$2:$2,0),FALSE)*I36,VLOOKUP('Proposal Form Tier 2-12'!$B$5,Tiers_list!$A:$BC,MATCH($A36,Tiers_list!$2:$2,0),FALSE)*I36/10)*(1-'Proposal Form Tier 2-12'!$B$16-'Proposal Form Tier 2-12'!$B$14) -> 534.375 | K36: =IF('Proposal Form Tier 2-12'!$B$5<>"Tier - 1 - 10",VLOOKUP('Proposal Form Tier 2-12'!$B$5,Tiers_list!$A:$BC,MATCH($A36,Tiers_list!$2:$2,0),FALSE)*L36*'Proposal Form Tier 2-12'!B$12,VLOOKUP('Proposal Form Tier 2-12'!$B$5,Tiers_list!$A:$BC,MATCH($A36,Tiers_list!$2:$2,0),FALSE)*'Proposal Form Tier 2-12'!B$12*L36/10)*(1-'Proposal Form Tier 2-12'!$B$16-'Proposal Form Tier 2-12'!$B$14) -> 267.1875 | L36: =SUM(M36:O36) -> 1 | M36: =IF($I36>0,'Proposal Form Tier 2-12'!$B$8,0) -> 1 | N36: =IF($I36>0,'Proposal Form Tier 2-12'!$B$9,0) -> 0 | O36: =IF($I36>0,'Proposal Form Tier 2-12'!$B$10,0) -> 0 | P36: =+(J36/(1-'Proposal Form Tier 2-12'!$B$16-'Proposal Form Tier 2-12'!$B$14))+(K36/(1-'Proposal Form Tier 2-12'!$B$16-'Proposal Form Tier 2-12'!$B$14)) -> 1068.75
A37: 200-50061 | B37: ACS Software | C37: ACS Enterprise Mass Programming and Data Collection/Receiving Services | D37: =_xlfn.XLOOKUP(A37,Tiers_list!$2:$2,Tiers_list!$1:$1,,0) -> Remote ACS Hardware firmware updates Module | E37: =+'Detail_Proposal_tier 1'!E37 -> Remote ACS controller and MMR 2.0 reader firmware updates | F37: =+'Detail_Proposal_tier 1'!F37 -> Administrators can remotely update the firmware of ACS controllers and MMR 2.0 readers across all sites without dispatching technicians — selecting the target firmware version, scoping the update to specific devices or territories, and scheduling execution during off-peak hours through the job scheduler. Firmware files go through an approval process before deployment, update progress is tracked in real time with automatic retry on failure, and all activity is logged — ensuring that every device in the estate stays current, secure, and operating on validated software. | G37: Required. Choose Qty | H37: ea. | I37: =_xlfn.XLOOKUP($A37,'Proposal Form Tier 2-12'!$C:$C,'Proposal Form Tier 2-12'!$B:$B,0,0) -> 1 | J37: =IF('Proposal Form Tier 2-12'!$B$5<>"Tier - 1 - 10",VLOOKUP('Proposal Form Tier 2-12'!$B$5,Tiers_list!$A:$BC,MATCH($A37,Tiers_list!$2:$2,0),FALSE)*I37,VLOOKUP('Proposal Form Tier 2-12'!$B$5,Tiers_list!$A:$BC,MATCH($A37,Tiers_list!$2:$2,0),FALSE)*I37/10)*(1-'Proposal Form Tier 2-12'!$B$16-'Proposal Form Tier 2-12'!$B$14) -> 712.5 | K37: =IF('Proposal Form Tier 2-12'!$B$5<>"Tier - 1 - 10",VLOOKUP('Proposal Form Tier 2-12'!$B$5,Tiers_list!$A:$BC,MATCH($A37,Tiers_list!$2:$2,0),FALSE)*L37*'Proposal Form Tier 2-12'!B$12,VLOOKUP('Proposal Form Tier 2-12'!$B$5,Tiers_list!$A:$BC,MATCH($A37,Tiers_list!$2:$2,0),FALSE)*'Proposal Form Tier 2-12'!B$12*L37/10)*(1-'Proposal Form Tier 2-12'!$B$16-'Proposal Form Tier 2-12'!$B$14) -> 356.25 | L37: =SUM(M37:O37) -> 1 | M37: =IF($I37>0,'Proposal Form Tier 2-12'!$B$8,0) -> 1 | N37: =IF($I37>0,'Proposal Form Tier 2-12'!$B$9,0) -> 0 | O37: =IF($I37>0,'Proposal Form Tier 2-12'!$B$10,0) -> 0 | P37: =+(J37/(1-'Proposal Form Tier 2-12'!$B$16-'Proposal Form Tier 2-12'!$B$14))+(K37/(1-'Proposal Form Tier 2-12'!$B$16-'Proposal Form Tier 2-12'!$B$14)) -> 1425
A38: 200-50062 | B38: ACS Software | C38: ACS Enterprise Mass Programming and Data Collection/Receiving Services | D38: =_xlfn.XLOOKUP(A38,Tiers_list!$2:$2,Tiers_list!$1:$1,,0) -> Door / Entrance Supervision Configuration Module | E38: =+'Detail_Proposal_tier 1'!E38 -> Configuration of Door Ajar, Door Opening Excessively during Access and Locked scheduled states. Event message thresholds are configurable for entry and egress supervision frequency.(Requires a Door Contact and Egress device integrated into the ACS controller) | F38: =+'Detail_Proposal_tier 1'!F38 -> Operators can configure and enforce door behavior rules that detect when a door is left open beyond an acceptable time (Door Ajar) or opened too frequently relative to credential reads — triggering alerts before a minor door issue becomes a security or compliance concern. Threshold values are configurable per reader and per site, default settings can be applied organization-wide, and all configuration changes are logged with full traceability of who set what and when. | G38: Optional | H38: ea. | I38: =_xlfn.XLOOKUP($A38,'Proposal Form Tier 2-12'!$C:$C,'Proposal Form Tier 2-12'!$B:$B,0,0) -> 0 | J38: =IF('Proposal Form Tier 2-12'!$B$5<>"Tier - 1 - 10",VLOOKUP('Proposal Form Tier 2-12'!$B$5,Tiers_list!$A:$BC,MATCH($A38,Tiers_list!$2:$2,0),FALSE)*I38,VLOOKUP('Proposal Form Tier 2-12'!$B$5,Tiers_list!$A:$BC,MATCH($A38,Tiers_list!$2:$2,0),FALSE)*I38/10)*(1-'Proposal Form Tier 2-12'!$B$16-'Proposal Form Tier 2-12'!$B$14) -> 0 | K38: =IF('Proposal Form Tier 2-12'!$B$5<>"Tier - 1 - 10",VLOOKUP('Proposal Form Tier 2-12'!$B$5,Tiers_list!$A:$BC,MATCH($A38,Tiers_list!$2:$2,0),FALSE)*L38*'Proposal Form Tier 2-12'!B$12,VLOOKUP('Proposal Form Tier 2-12'!$B$5,Tiers_list!$A:$BC,MATCH($A38,Tiers_list!$2:$2,0),FALSE)*'Proposal Form Tier 2-12'!B$12*L38/10)*(1-'Proposal Form Tier 2-12'!$B$16-'Proposal Form Tier 2-12'!$B$14) -> 0 | L38: =SUM(M38:O38) -> 0 | M38: =IF($I38>0,'Proposal Form Tier 2-12'!$B$8,0) -> 0 | N38: =IF($I38>0,'Proposal Form Tier 2-12'!$B$9,0) -> 0 | O38: =IF($I38>0,'Proposal Form Tier 2-12'!$B$10,0) -> 0 | P38: =+(J38/(1-'Proposal Form Tier 2-12'!$B$16-'Proposal Form Tier 2-12'!$B$14))+(K38/(1-'Proposal Form Tier 2-12'!$B$16-'Proposal Form Tier 2-12'!$B$14)) -> 0
A39: 200-50063 | B39: ACS Software | C39: ACS Enterprise Mass Programming and Data Collection/Receiving Services | D39: =_xlfn.XLOOKUP(A39,Tiers_list!$2:$2,Tiers_list!$1:$1,,0) -> ACS Hardware Firmware Version Supervision Module | E39: =+'Detail_Proposal_tier 1'!E39 -> MMR 2.0 reader and ACS controller approved firmware version and serial number supervision | F39: =+'Detail_Proposal_tier 1'!F39 -> ACS Cloud Enterprise maintains a live inventory of the approved firmware versions and serial numbers for every controller and reader in the estate, automatically flagging devices that are running outdated or unapproved firmware versions. This gives administrators a continuous, accurate view of firmware compliance across the entire device fleet, supports proactive update planning, and ensures that no device is overlooked during firmware rollouts — eliminating the audit risk of unknown or uncertified firmware running in a live security environment. | G39: Required | H39: ea. | I39: =+'Proposal Form Tier 2-12'!$B$6 -> 1 | J39: =IF('Proposal Form Tier 2-12'!$B$5<>"Tier - 1 - 10",VLOOKUP('Proposal Form Tier 2-12'!$B$5,Tiers_list!$A:$BC,MATCH($A39,Tiers_list!$2:$2,0),FALSE)*I39,VLOOKUP('Proposal Form Tier 2-12'!$B$5,Tiers_list!$A:$BC,MATCH($A39,Tiers_list!$2:$2,0),FALSE)*I39/10)*(1-'Proposal Form Tier 2-12'!$B$16-'Proposal Form Tier 2-12'!$B$14) -> 356.25 | K39: =IF('Proposal Form Tier 2-12'!$B$5<>"Tier - 1 - 10",VLOOKUP('Proposal Form Tier 2-12'!$B$5,Tiers_list!$A:$BC,MATCH($A39,Tiers_list!$2:$2,0),FALSE)*L39*'Proposal Form Tier 2-12'!B$12,VLOOKUP('Proposal Form Tier 2-12'!$B$5,Tiers_list!$A:$BC,MATCH($A39,Tiers_list!$2:$2,0),FALSE)*'Proposal Form Tier 2-12'!B$12*L39/10)*(1-'Proposal Form Tier 2-12'!$B$16-'Proposal Form Tier 2-12'!$B$14) -> 178.125 | L39: =SUM(M39:O39) -> 1 | M39: =IF($I39>0,'Proposal Form Tier 2-12'!$B$8,0) -> 1 | N39: =IF($I39>0,'Proposal Form Tier 2-12'!$B$9,0) -> 0 | O39: =IF($I39>0,'Proposal Form Tier 2-12'!$B$10,0) -> 0 | P39: =+(J39/(1-'Proposal Form Tier 2-12'!$B$16-'Proposal Form Tier 2-12'!$B$14))+(K39/(1-'Proposal Form Tier 2-12'!$B$16-'Proposal Form Tier 2-12'!$B$14)) -> 712.5
A40: 200-50064 | B40: ACS Software | C40: ACS Enterprise Mass Programming and Data Collection/Receiving Services | D40: =_xlfn.XLOOKUP(A40,Tiers_list!$2:$2,Tiers_list!$1:$1,,0) -> ACS Data Retention / Archive Module | E40: =+'Detail_Proposal_tier 1'!E40 -> Definable ACS data (Credentials read, Event Message, ACS User Activity and hardware configuration history) archive management, reports and archive data history viewer. | F40: =+'Detail_Proposal_tier 1'!F40 -> ACS Cloud Enterprise enables administrators to define retention policies for all system data — including credential events, configuration history, user activity logs, and hardware records — with automatic archiving and purging that keeps storage costs under control while ensuring the organization meets its regulatory and compliance obligations. Archived data remains accessible during the retention window, all archiving activity is captured in a compliance audit log, and access to archived records is restricted to authorized personnel — giving organizations defensible data governance without manual data management overhead. | G40: Required | H40: ea. | I40: =+'Proposal Form Tier 2-12'!$B$6 -> 1 | J40: =IF('Proposal Form Tier 2-12'!$B$5<>"Tier - 1 - 10",VLOOKUP('Proposal Form Tier 2-12'!$B$5,Tiers_list!$A:$BC,MATCH($A40,Tiers_list!$2:$2,0),FALSE)*I40,VLOOKUP('Proposal Form Tier 2-12'!$B$5,Tiers_list!$A:$BC,MATCH($A40,Tiers_list!$2:$2,0),FALSE)*I40/10)*(1-'Proposal Form Tier 2-12'!$B$16-'Proposal Form Tier 2-12'!$B$14) -> 356.25 | K40: =IF('Proposal Form Tier 2-12'!$B$5<>"Tier - 1 - 10",VLOOKUP('Proposal Form Tier 2-12'!$B$5,Tiers_list!$A:$BC,MATCH($A40,Tiers_list!$2:$2,0),FALSE)*L40*'Proposal Form Tier 2-12'!B$12,VLOOKUP('Proposal Form Tier 2-12'!$B$5,Tiers_list!$A:$BC,MATCH($A40,Tiers_list!$2:$2,0),FALSE)*'Proposal Form Tier 2-12'!B$12*L40/10)*(1-'Proposal Form Tier 2-12'!$B$16-'Proposal Form Tier 2-12'!$B$14) -> 178.125 | L40: =SUM(M40:O40) -> 1 | M40: =IF($I40>0,'Proposal Form Tier 2-12'!$B$8,0) -> 1 | N40: =IF($I40>0,'Proposal Form Tier 2-12'!$B$9,0) -> 0 | O40: =IF($I40>0,'Proposal Form Tier 2-12'!$B$10,0) -> 0 | P40: =+(J40/(1-'Proposal Form Tier 2-12'!$B$16-'Proposal Form Tier 2-12'!$B$14))+(K40/(1-'Proposal Form Tier 2-12'!$B$16-'Proposal Form Tier 2-12'!$B$14)) -> 712.5
A41: 200-50065 | B41: ACS Software | C41: ACS Enterprise Mass Programming and Data Collection/Receiving Services | D41: =_xlfn.XLOOKUP(A41,Tiers_list!$2:$2,Tiers_list!$1:$1,,0) -> Scheduled ACS Export / Report Distribution Module | E41: =+'Detail_Proposal_tier 1'!E41 -> Scheduled ACS Export / Report Distribution | F41: =+'Detail_Proposal_tier 1'!F41 -> Administrators can configure recurring scheduled exports of any ACS report — access event summaries, credential analytics, user activity logs, job results, or configuration histories — and have them automatically delivered by email to defined recipient groups on a daily, weekly, or monthly basis. This eliminates the manual effort of pulling and distributing reports, ensures that managers and auditors receive the information they need without logging into the system, and creates a consistent, documented cadence of operational and compliance reporting. | G41: Required | H41: ea. | I41: =+'Proposal Form Tier 2-12'!$B$6 -> 1 | J41: =IF('Proposal Form Tier 2-12'!$B$5<>"Tier - 1 - 10",VLOOKUP('Proposal Form Tier 2-12'!$B$5,Tiers_list!$A:$BC,MATCH($A41,Tiers_list!$2:$2,0),FALSE)*I41,VLOOKUP('Proposal Form Tier 2-12'!$B$5,Tiers_list!$A:$BC,MATCH($A41,Tiers_list!$2:$2,0),FALSE)*I41/10)*(1-'Proposal Form Tier 2-12'!$B$16-'Proposal Form Tier 2-12'!$B$14) -> 356.25 | K41: =IF('Proposal Form Tier 2-12'!$B$5<>"Tier - 1 - 10",VLOOKUP('Proposal Form Tier 2-12'!$B$5,Tiers_list!$A:$BC,MATCH($A41,Tiers_list!$2:$2,0),FALSE)*L41*'Proposal Form Tier 2-12'!B$12,VLOOKUP('Proposal Form Tier 2-12'!$B$5,Tiers_list!$A:$BC,MATCH($A41,Tiers_list!$2:$2,0),FALSE)*'Proposal Form Tier 2-12'!B$12*L41/10)*(1-'Proposal Form Tier 2-12'!$B$16-'Proposal Form Tier 2-12'!$B$14) -> 178.125 | L41: =SUM(M41:O41) -> 1 | M41: =IF($I41>0,'Proposal Form Tier 2-12'!$B$8,0) -> 1 | N41: =IF($I41>0,'Proposal Form Tier 2-12'!$B$9,0) -> 0 | O41: =IF($I41>0,'Proposal Form Tier 2-12'!$B$10,0) -> 0 | P41: =+(J41/(1-'Proposal Form Tier 2-12'!$B$16-'Proposal Form Tier 2-12'!$B$14))+(K41/(1-'Proposal Form Tier 2-12'!$B$16-'Proposal Form Tier 2-12'!$B$14)) -> 712.5
A42: 200-50066 | B42: ACS Software | C42: ACS Enterprise Mass Programming and Data Collection/Receiving Services | D42: =_xlfn.XLOOKUP(A42,Tiers_list!$2:$2,Tiers_list!$1:$1,,0) -> Duplicate Credential Read within ACS Ecosystem Supervision Module | E42: =+'Detail_Proposal_tier 1'!E42 -> Duplicate Credential Read within ACS Ecosystem Supervision Module | F42: =+'Detail_Proposal_tier 1'!F42 -> ACS Cloud Enterprise monitors for instances where the same credential is read at multiple entrances within the same site in a timeframe that makes simultaneous physical presence impossible, automatically flagging potential credential cloning, sharing, or misuse before it escalates into a security incident. When a duplicate pattern is detected, the system generates an alert and logs the event for investigation, giving security teams the real-time intelligence they need to identify and respond to credential abuse across their entire access control estate. | G42: Required | H42: ea. | I42: =+'Proposal Form Tier 2-12'!$B$6 -> 1 | J42: =IF('Proposal Form Tier 2-12'!$B$5<>"Tier - 1 - 10",VLOOKUP('Proposal Form Tier 2-12'!$B$5,Tiers_list!$A:$BC,MATCH($A42,Tiers_list!$2:$2,0),FALSE)*I42,VLOOKUP('Proposal Form Tier 2-12'!$B$5,Tiers_list!$A:$BC,MATCH($A42,Tiers_list!$2:$2,0),FALSE)*I42/10)*(1-'Proposal Form Tier 2-12'!$B$16-'Proposal Form Tier 2-12'!$B$14) -> 534.375 | K42: =IF('Proposal Form Tier 2-12'!$B$5<>"Tier - 1 - 10",VLOOKUP('Proposal Form Tier 2-12'!$B$5,Tiers_list!$A:$BC,MATCH($A42,Tiers_list!$2:$2,0),FALSE)*L42*'Proposal Form Tier 2-12'!B$12,VLOOKUP('Proposal Form Tier 2-12'!$B$5,Tiers_list!$A:$BC,MATCH($A42,Tiers_list!$2:$2,0),FALSE)*'Proposal Form Tier 2-12'!B$12*L42/10)*(1-'Proposal Form Tier 2-12'!$B$16-'Proposal Form Tier 2-12'!$B$14) -> 267.1875 | L42: =SUM(M42:O42) -> 1 | M42: =IF($I42>0,'Proposal Form Tier 2-12'!$B$8,0) -> 1 | N42: =IF($I42>0,'Proposal Form Tier 2-12'!$B$9,0) -> 0 | O42: =IF($I42>0,'Proposal Form Tier 2-12'!$B$10,0) -> 0 | P42: =+(J42/(1-'Proposal Form Tier 2-12'!$B$16-'Proposal Form Tier 2-12'!$B$14))+(K42/(1-'Proposal Form Tier 2-12'!$B$16-'Proposal Form Tier 2-12'!$B$14)) -> 1068.75
C43: ACS Enterprise Mass Programming and Data Collection/Receiving Services Total | I43: =SUBTOTAL(9,I35:I42) -> 7 | J43: =SUBTOTAL(9,J35:J42) -> 3384.375 | K43: =SUBTOTAL(9,K35:K42) -> 1692.1875 | L43: =SUBTOTAL(9,L35:L42) -> 7 | M43: =SUBTOTAL(9,M35:M42) -> 7 | N43: =SUBTOTAL(9,N35:N42) -> 0 | O43: =SUBTOTAL(9,O35:O42) -> 0 | P43: =SUBTOTAL(9,P35:P42) -> 6768.75
A44: 200-50067 | B44: ACS Software | C44: Annual ACS Cloud Enterprise Ecosystem, Hardware, Facility Sensors, Reader Monitoring UI features | D44: =_xlfn.XLOOKUP(A44,Tiers_list!$2:$2,Tiers_list!$1:$1,,0) -> ACS Facility Supervision Module | E44: =+'Detail_Proposal_tier 1'!E44 -> Duplicate Credentials read at each location and the distance between locations where the Credential was read via Google Maps integration calculating and displaying distances between locations where the duplicate credentials were read. | F44: =+'Detail_Proposal_tier 1'!F44 -> ACS Cloud Enterprise detects when the same credential is used at geographically distant locations within a time window that makes legitimate travel between them physically implausible — a strong indicator of credential cloning or sharing — and immediately alerts the security team for investigation. By continuously analyzing credential events across the full site network and correlating them by distance and timing, organizations gain a powerful, automated early-warning capability that human operators monitoring individual sites could never replicate at scale. | G44: Required | H44: ea. | I44: =+'Proposal Form Tier 2-12'!$B$6 -> 1 | J44: =IF('Proposal Form Tier 2-12'!$B$5<>"Tier - 1 - 10",VLOOKUP('Proposal Form Tier 2-12'!$B$5,Tiers_list!$A:$BC,MATCH($A44,Tiers_list!$2:$2,0),FALSE)*I44,VLOOKUP('Proposal Form Tier 2-12'!$B$5,Tiers_list!$A:$BC,MATCH($A44,Tiers_list!$2:$2,0),FALSE)*I44/10)*(1-'Proposal Form Tier 2-12'!$B$16-'Proposal Form Tier 2-12'!$B$14) -> 356.25 | K44: =IF('Proposal Form Tier 2-12'!$B$5<>"Tier - 1 - 10",VLOOKUP('Proposal Form Tier 2-12'!$B$5,Tiers_list!$A:$BC,MATCH($A44,Tiers_list!$2:$2,0),FALSE)*L44*'Proposal Form Tier 2-12'!B$12,VLOOKUP('Proposal Form Tier 2-12'!$B$5,Tiers_list!$A:$BC,MATCH($A44,Tiers_list!$2:$2,0),FALSE)*'Proposal Form Tier 2-12'!B$12*L44/10)*(1-'Proposal Form Tier 2-12'!$B$16-'Proposal Form Tier 2-12'!$B$14) -> 178.125 | L44: =SUM(M44:O44) -> 1 | M44: =IF($I44>0,'Proposal Form Tier 2-12'!$B$8,0) -> 1 | N44: =IF($I44>0,'Proposal Form Tier 2-12'!$B$9,0) -> 0 | O44: =IF($I44>0,'Proposal Form Tier 2-12'!$B$10,0) -> 0 | P44: =+(J44/(1-'Proposal Form Tier 2-12'!$B$16-'Proposal Form Tier 2-12'!$B$14))+(K44/(1-'Proposal Form Tier 2-12'!$B$16-'Proposal Form Tier 2-12'!$B$14)) -> 712.5
A45: 200-50068 | B45: ACS Software | C45: Annual ACS Cloud Enterprise Ecosystem, Hardware, Facility Sensors, Reader Monitoring UI features | D45: =_xlfn.XLOOKUP(A45,Tiers_list!$2:$2,Tiers_list!$1:$1,,0) -> ACS Controller Software Integrations DB Ecosystem Supervision Module | E45: =+'Detail_Proposal_tier 1'!E45 -> Light Sensor monitoring, Presence, Loitering and Single Access Detection, Door Ajar, Door Unsecure and Door opening excessively and Customer Can't Enter or Exit a facility | F45: =+'Detail_Proposal_tier 1'!F45 -> ACS Cloud Enterprise monitors a rich set of facility sensor inputs — including light sensors, presence detection, loitering patterns, single-access violations, and door ajar conditions — turning raw hardware signals into actionable operational intelligence that security teams can act on in real time. Configurable thresholds, automated alerts, and event correlation with access control activity give operators a comprehensive picture of what is happening at every entrance and in every monitored space, enabling faster response to anomalies and stronger overall facility security posture. | G45: Optional | H45: ea. | I45: =_xlfn.XLOOKUP($A45,'Proposal Form Tier 2-12'!$C:$C,'Proposal Form Tier 2-12'!$B:$B,0,0) -> 0 | J45: =IF('Proposal Form Tier 2-12'!$B$5<>"Tier - 1 - 10",VLOOKUP('Proposal Form Tier 2-12'!$B$5,Tiers_list!$A:$BC,MATCH($A45,Tiers_list!$2:$2,0),FALSE)*I45,VLOOKUP('Proposal Form Tier 2-12'!$B$5,Tiers_list!$A:$BC,MATCH($A45,Tiers_list!$2:$2,0),FALSE)*I45/10)*(1-'Proposal Form Tier 2-12'!$B$16-'Proposal Form Tier 2-12'!$B$14) -> 0 | K45: =IF('Proposal Form Tier 2-12'!$B$5<>"Tier - 1 - 10",VLOOKUP('Proposal Form Tier 2-12'!$B$5,Tiers_list!$A:$BC,MATCH($A45,Tiers_list!$2:$2,0),FALSE)*L45*'Proposal Form Tier 2-12'!B$12,VLOOKUP('Proposal Form Tier 2-12'!$B$5,Tiers_list!$A:$BC,MATCH($A45,Tiers_list!$2:$2,0),FALSE)*'Proposal Form Tier 2-12'!B$12*L45/10)*(1-'Proposal Form Tier 2-12'!$B$16-'Proposal Form Tier 2-12'!$B$14) -> 0 | L45: =SUM(M45:O45) -> 0 | M45: =IF($I45>0,'Proposal Form Tier 2-12'!$B$8,0) -> 0 | N45: =IF($I45>0,'Proposal Form Tier 2-12'!$B$9,0) -> 0 | O45: =IF($I45>0,'Proposal Form Tier 2-12'!$B$10,0) -> 0 | P45: =+(J45/(1-'Proposal Form Tier 2-12'!$B$16-'Proposal Form Tier 2-12'!$B$14))+(K45/(1-'Proposal Form Tier 2-12'!$B$16-'Proposal Form Tier 2-12'!$B$14)) -> 0
A46: 200-50069 | B46: ACS Software | C46: Annual ACS Cloud Enterprise Ecosystem, Hardware, Facility Sensors, Reader Monitoring UI features | D46: =_xlfn.XLOOKUP(A46,Tiers_list!$2:$2,Tiers_list!$1:$1,,0) -> Reader Credentials Accepted and Rejected Supervision Module | E46: =+'Detail_Proposal_tier 1'!E45 -> Light Sensor monitoring, Presence, Loitering and Single Access Detection, Door Ajar, Door Unsecure and Door opening excessively and Customer Can't Enter or Exit a facility | F46: =+'Detail_Proposal_tier 1'!F45 -> ACS Cloud Enterprise monitors a rich set of facility sensor inputs — including light sensors, presence detection, loitering patterns, single-access violations, and door ajar conditions — turning raw hardware signals into actionable operational intelligence that security teams can act on in real time. Configurable thresholds, automated alerts, and event correlation with access control activity give operators a comprehensive picture of what is happening at every entrance and in every monitored space, enabling faster response to anomalies and stronger overall facility security posture. | G46: Required | H46: ea. | I46: 1 | J46: =IF('Proposal Form Tier 2-12'!$B$5<>"Tier - 1 - 10",VLOOKUP('Proposal Form Tier 2-12'!$B$5,Tiers_list!$A:$BC,MATCH($A46,Tiers_list!$2:$2,0),FALSE)*I46,VLOOKUP('Proposal Form Tier 2-12'!$B$5,Tiers_list!$A:$BC,MATCH($A46,Tiers_list!$2:$2,0),FALSE)*I46/10)*(1-'Proposal Form Tier 2-12'!$B$16-'Proposal Form Tier 2-12'!$B$14) -> 534.375 | K46: =IF('Proposal Form Tier 2-12'!$B$5<>"Tier - 1 - 10",VLOOKUP('Proposal Form Tier 2-12'!$B$5,Tiers_list!$A:$BC,MATCH($A46,Tiers_list!$2:$2,0),FALSE)*L46*'Proposal Form Tier 2-12'!B$12,VLOOKUP('Proposal Form Tier 2-12'!$B$5,Tiers_list!$A:$BC,MATCH($A46,Tiers_list!$2:$2,0),FALSE)*'Proposal Form Tier 2-12'!B$12*L46/10)*(1-'Proposal Form Tier 2-12'!$B$16-'Proposal Form Tier 2-12'!$B$14) -> 267.1875 | L46: =SUM(M46:O46) -> 1 | M46: =IF($I46>0,'Proposal Form Tier 2-12'!$B$8,0) -> 1 | N46: =IF($I46>0,'Proposal Form Tier 2-12'!$B$9,0) -> 0 | O46: =IF($I46>0,'Proposal Form Tier 2-12'!$B$10,0) -> 0 | P46: =+(J46/(1-'Proposal Form Tier 2-12'!$B$16-'Proposal Form Tier 2-12'!$B$14))+(K46/(1-'Proposal Form Tier 2-12'!$B$16-'Proposal Form Tier 2-12'!$B$14)) -> 1068.75
A47: =+'Detail_Proposal_tier 1'!A47 -> 200-50071 | B47: =+'Detail_Proposal_tier 1'!B47 -> ACS Enterprise Integrations | C47: =+'Detail_Proposal_tier 1'!C47 -> Annual ACS Cloud Enterprise Ecosystem, Hardware, Facility Sensors, Reader Monitoring UI features | D47: =+'Detail_Proposal_tier 1'!D47 -> ACS controller Reader Remote Credential Lookup with Local learn Module | E47: =+'Detail_Proposal_tier 1'!E47 -> Remote lookup of Accepted, Rejected and Suspect Credentials stored on the ACS controller EEPROM with an until date/time for future local Credential lookups. | F47: =+'Detail_Proposal_tier 1'!F47 -> When a credential is presented at a reader configured for external match validation, ACS Cloud Enterprise forwards the request to a designated external server in real time, retrieves the allow or reject decision, and acts on it immediately — with the response cached at the controller to maintain performance even during brief connectivity interruptions. This enables organizations to maintain centralized, organization-wide credential authority in an external system (such as a financial institution's BIN database) while still leveraging the speed and resilience of local controller enforcement. | G47: =+'Detail_Proposal_tier 1'!G47 -> Optional | H47: ea. | I47: =_xlfn.XLOOKUP($A47,'Proposal Form Tier 2-12'!$C:$C,'Proposal Form Tier 2-12'!$B:$B,0,0) -> 0 | J47: =IF('Proposal Form Tier 2-12'!$B$5<>"Tier - 1 - 10",VLOOKUP('Proposal Form Tier 2-12'!$B$5,Tiers_list!$A:$BC,MATCH($A47,Tiers_list!$2:$2,0),FALSE)*I47,VLOOKUP('Proposal Form Tier 2-12'!$B$5,Tiers_list!$A:$BC,MATCH($A47,Tiers_list!$2:$2,0),FALSE)*I47/10)*(1-'Proposal Form Tier 2-12'!$B$16-'Proposal Form Tier 2-12'!$B$14) -> 0 | K47: =IF('Proposal Form Tier 2-12'!$B$5<>"Tier - 1 - 10",VLOOKUP('Proposal Form Tier 2-12'!$B$5,Tiers_list!$A:$BC,MATCH($A47,Tiers_list!$2:$2,0),FALSE)*L47*'Proposal Form Tier 2-12'!B$12,VLOOKUP('Proposal Form Tier 2-12'!$B$5,Tiers_list!$A:$BC,MATCH($A47,Tiers_list!$2:$2,0),FALSE)*'Proposal Form Tier 2-12'!B$12*L47/10)*(1-'Proposal Form Tier 2-12'!$B$16-'Proposal Form Tier 2-12'!$B$14) -> 0 | L47: =SUM(M47:O47) -> 0 | M47: =IF($I47>0,'Proposal Form Tier 2-12'!$B$8,0) -> 0 | N47: =IF($I47>0,'Proposal Form Tier 2-12'!$B$9,0) -> 0 | O47: =IF($I47>0,'Proposal Form Tier 2-12'!$B$10,0) -> 0 | P47: =+(J47/(1-'Proposal Form Tier 2-12'!$B$16-'Proposal Form Tier 2-12'!$B$14))+(K47/(1-'Proposal Form Tier 2-12'!$B$16-'Proposal Form Tier 2-12'!$B$14)) -> 0
A48: =+'Detail_Proposal_tier 1'!A48 -> 200-50072 | B48: =+'Detail_Proposal_tier 1'!B48 -> ACS Enterprise Integrations | C48: =+'Detail_Proposal_tier 1'!C48 -> Annual ACS Cloud Enterprise Ecosystem, Hardware, Facility Sensors, Reader Monitoring UI features | D48: =+'Detail_Proposal_tier 1'!D48 -> ACS controller Reader Remote Credential Lookup with Local learn Module | E48: =+'Detail_Proposal_tier 1'!E48 -> Configure reader type, access by Credential holder and by Access Schedule. i.e., HID, Wave Lynx, Elactec, etc. Prox and/or keypad reader, Bio Reader, Wearable Tech NFC, Mobile with NFC card, Bluetooth Local with Bluetooth Cloud, etc. | F48: =+'Detail_Proposal_tier 1'!F48 -> Operators can configure every reader in the system — defining the credential types accepted (magnetic stripe, NFC, Bluetooth, biometric, and more), assigning the appropriate access schedules, and linking readers to specific user groups — all from a centralized interface without a site visit. This ensures that every entrance behaves exactly as intended, that the right people have access at the right times, and that configuration changes are applied instantly and consistently across all locations. | G48: =+'Detail_Proposal_tier 1'!G48 -> Optional | H48: ea. | I48: =_xlfn.XLOOKUP($A48,'Proposal Form Tier 2-12'!$C:$C,'Proposal Form Tier 2-12'!$B:$B,0,0) -> 0 | J48: =IF('Proposal Form Tier 2-12'!$B$5<>"Tier - 1 - 10",VLOOKUP('Proposal Form Tier 2-12'!$B$5,Tiers_list!$A:$BC,MATCH($A48,Tiers_list!$2:$2,0),FALSE)*I48,VLOOKUP('Proposal Form Tier 2-12'!$B$5,Tiers_list!$A:$BC,MATCH($A48,Tiers_list!$2:$2,0),FALSE)*I48/10)*(1-'Proposal Form Tier 2-12'!$B$16-'Proposal Form Tier 2-12'!$B$14) -> 0 | K48: =IF('Proposal Form Tier 2-12'!$B$5<>"Tier - 1 - 10",VLOOKUP('Proposal Form Tier 2-12'!$B$5,Tiers_list!$A:$BC,MATCH($A48,Tiers_list!$2:$2,0),FALSE)*L48*'Proposal Form Tier 2-12'!B$12,VLOOKUP('Proposal Form Tier 2-12'!$B$5,Tiers_list!$A:$BC,MATCH($A48,Tiers_list!$2:$2,0),FALSE)*'Proposal Form Tier 2-12'!B$12*L48/10)*(1-'Proposal Form Tier 2-12'!$B$16-'Proposal Form Tier 2-12'!$B$14) -> 0 | L48: =SUM(M48:O48) -> 0 | M48: =IF($I48>0,'Proposal Form Tier 2-12'!$B$8,0) -> 0 | N48: =IF($I48>0,'Proposal Form Tier 2-12'!$B$9,0) -> 0 | O48: =IF($I48>0,'Proposal Form Tier 2-12'!$B$10,0) -> 0 | P48: =+(J48/(1-'Proposal Form Tier 2-12'!$B$16-'Proposal Form Tier 2-12'!$B$14))+(K48/(1-'Proposal Form Tier 2-12'!$B$16-'Proposal Form Tier 2-12'!$B$14)) -> 0
A49: =+'Detail_Proposal_tier 1'!A49 -> 200-50073 | B49: =+'Detail_Proposal_tier 1'!B49 -> ACS Enterprise Integrations | C49: =+'Detail_Proposal_tier 1'!C49 -> Annual ACS Cloud Enterprise Ecosystem, Hardware, Facility Sensors, Reader Monitoring UI features | D49: =+'Detail_Proposal_tier 1'!D49 -> Export & Reporting | E49: =+'Detail_Proposal_tier 1'!E49 -> Adds an Export action to data grids across the Site, Access Point, Login, and Log modules — Sites, Site Tags, Suspect Files, Match Files, User Management, Authorization Resources, Audit Logs, System Logs, Infrastructure Logs, Device Messages, Credential Events, Device Diagnostics Logs, and Service Diagnostics — producing a structured file of the currently displayed dataset. | F49: =+'Detail_Proposal_tier 1'!F49 -> ACS Cloud Enterprise lets operators download any data grid in the system to a structured file for offline review, compliance reporting, or long-term archiving, without needing direct database access or a separate reporting tool. This turns every grid in the platform into a self-service reporting source, reducing the time security and compliance teams spend assembling audit packages or sharing data with auditors and regulators. | G49: =+'Detail_Proposal_tier 1'!G49 -> Optional | H49: ea. | I49: =_xlfn.XLOOKUP($A49,'Proposal Form Tier 2-12'!$C:$C,'Proposal Form Tier 2-12'!$B:$B,0,0) -> 0 | J49: =IF('Proposal Form Tier 2-12'!$B$5<>"Tier - 1 - 10",VLOOKUP('Proposal Form Tier 2-12'!$B$5,Tiers_list!$A:$BC,MATCH($A49,Tiers_list!$2:$2,0),FALSE)*I49,VLOOKUP('Proposal Form Tier 2-12'!$B$5,Tiers_list!$A:$BC,MATCH($A49,Tiers_list!$2:$2,0),FALSE)*I49/10)*(1-'Proposal Form Tier 2-12'!$B$16-'Proposal Form Tier 2-12'!$B$14) -> 0 | K49: =IF('Proposal Form Tier 2-12'!$B$5<>"Tier - 1 - 10",VLOOKUP('Proposal Form Tier 2-12'!$B$5,Tiers_list!$A:$BC,MATCH($A49,Tiers_list!$2:$2,0),FALSE)*L49*'Proposal Form Tier 2-12'!B$12,VLOOKUP('Proposal Form Tier 2-12'!$B$5,Tiers_list!$A:$BC,MATCH($A49,Tiers_list!$2:$2,0),FALSE)*'Proposal Form Tier 2-12'!B$12*L49/10)*(1-'Proposal Form Tier 2-12'!$B$16-'Proposal Form Tier 2-12'!$B$14) -> 0 | L49: =SUM(M49:O49) -> 0 | M49: =IF($I49>0,'Proposal Form Tier 2-12'!$B$8,0) -> 0 | N49: =IF($I49>0,'Proposal Form Tier 2-12'!$B$9,0) -> 0 | O49: =IF($I49>0,'Proposal Form Tier 2-12'!$B$10,0) -> 0 | P49: =+(J49/(1-'Proposal Form Tier 2-12'!$B$16-'Proposal Form Tier 2-12'!$B$14))+(K49/(1-'Proposal Form Tier 2-12'!$B$16-'Proposal Form Tier 2-12'!$B$14)) -> 0
A50: =+'Detail_Proposal_tier 1'!A50 -> 200-50074 | B50: =+'Detail_Proposal_tier 1'!B50 -> ACS Enterprise Integrations | C50: =+'Detail_Proposal_tier 1'!C50 -> Annual ACS Cloud Enterprise Ecosystem, Hardware, Facility Sensors, Reader Monitoring UI features | D50: =+'Detail_Proposal_tier 1'!D50 -> Bulk Synchronisation ans Scheduling | E50: =+'Detail_Proposal_tier 1'!E50 -> Adds a Schedule Sync action to Access Point Mgmt configuration grids — Access Point Configuration, Match Configuration, Match File, Suspect File, AP IO Configuration, Controller IO Configuration, Weekly Schedule Management, Holiday Schedule Management, and Controller config-mismatch jobs — allowing a configuration push to be queued and applied automatically at a defined date/time rather than immediately. | F50: =+'Detail_Proposal_tier 1'!F50 -> ACS Cloud Enterprise lets operators schedule configuration pushes to groups of devices for a future date and time instead of applying every change manually and immediately. This allows large rollouts — new schedules, credential lists, or controller settings — to be staged during a maintenance window and propagate automatically across many sites without an operator present at the time of the sync. | G50: =+'Detail_Proposal_tier 1'!G50 -> Optional | H50: ea. | I50: =_xlfn.XLOOKUP($A50,'Proposal Form Tier 2-12'!$C:$C,'Proposal Form Tier 2-12'!$B:$B,0,0) -> 0 | J50: =IF('Proposal Form Tier 2-12'!$B$5<>"Tier - 1 - 10",VLOOKUP('Proposal Form Tier 2-12'!$B$5,Tiers_list!$A:$BC,MATCH($A50,Tiers_list!$2:$2,0),FALSE)*I50,VLOOKUP('Proposal Form Tier 2-12'!$B$5,Tiers_list!$A:$BC,MATCH($A50,Tiers_list!$2:$2,0),FALSE)*I50/10)*(1-'Proposal Form Tier 2-12'!$B$16-'Proposal Form Tier 2-12'!$B$14) -> 0 | K50: =IF('Proposal Form Tier 2-12'!$B$5<>"Tier - 1 - 10",VLOOKUP('Proposal Form Tier 2-12'!$B$5,Tiers_list!$A:$BC,MATCH($A50,Tiers_list!$2:$2,0),FALSE)*L50*'Proposal Form Tier 2-12'!B$12,VLOOKUP('Proposal Form Tier 2-12'!$B$5,Tiers_list!$A:$BC,MATCH($A50,Tiers_list!$2:$2,0),FALSE)*'Proposal Form Tier 2-12'!B$12*L50/10)*(1-'Proposal Form Tier 2-12'!$B$16-'Proposal Form Tier 2-12'!$B$14) -> 0 | L50: =SUM(M50:O50) -> 0 | M50: =IF($I50>0,'Proposal Form Tier 2-12'!$B$8,0) -> 0 | N50: =IF($I50>0,'Proposal Form Tier 2-12'!$B$9,0) -> 0 | O50: =IF($I50>0,'Proposal Form Tier 2-12'!$B$10,0) -> 0 | P50: =+(J50/(1-'Proposal Form Tier 2-12'!$B$16-'Proposal Form Tier 2-12'!$B$14))+(K50/(1-'Proposal Form Tier 2-12'!$B$16-'Proposal Form Tier 2-12'!$B$14)) -> 0
A51: =+'Detail_Proposal_tier 1'!A51 -> 200-50075 | B51: =+'Detail_Proposal_tier 1'!B51 -> ACS Enterprise Integrations | C51: =+'Detail_Proposal_tier 1'!C51 -> Annual ACS Cloud Enterprise Ecosystem, Hardware, Facility Sensors, Reader Monitoring UI features | D51: =+'Detail_Proposal_tier 1'!D51 -> Clone & Templates | E51: =+'Detail_Proposal_tier 1'!E51 -> Adds a Clone action to Access Point Mgmt and Login Mgmt configuration entities — Match Configuration, Match File, AP IO Configuration, Controller IO Configuration, Weekly Schedule Management, Holiday Schedule Management, and Authorization Resources — creating a duplicate of an existing configuration record that can be assigned to a new site, controller, or user as a starting point. | F51: =+'Detail_Proposal_tier 1'!F51 -> ACS Cloud Enterprise lets operators copy an existing, already-tested configuration as a template instead of building every new site, controller, or access profile from scratch. This shortens rollout time for multi-site deployments and reduces configuration drift, since new entities start from a known-good baseline rather than manual re-entry. | G51: =+'Detail_Proposal_tier 1'!G51 -> Optional | H51: ea. | I51: =_xlfn.XLOOKUP($A51,'Proposal Form Tier 2-12'!$C:$C,'Proposal Form Tier 2-12'!$B:$B,0,0) -> 0 | J51: =IF('Proposal Form Tier 2-12'!$B$5<>"Tier - 1 - 10",VLOOKUP('Proposal Form Tier 2-12'!$B$5,Tiers_list!$A:$BC,MATCH($A51,Tiers_list!$2:$2,0),FALSE)*I51,VLOOKUP('Proposal Form Tier 2-12'!$B$5,Tiers_list!$A:$BC,MATCH($A51,Tiers_list!$2:$2,0),FALSE)*I51/10)*(1-'Proposal Form Tier 2-12'!$B$16-'Proposal Form Tier 2-12'!$B$14) -> 0 | K51: =IF('Proposal Form Tier 2-12'!$B$5<>"Tier - 1 - 10",VLOOKUP('Proposal Form Tier 2-12'!$B$5,Tiers_list!$A:$BC,MATCH($A51,Tiers_list!$2:$2,0),FALSE)*L51*'Proposal Form Tier 2-12'!B$12,VLOOKUP('Proposal Form Tier 2-12'!$B$5,Tiers_list!$A:$BC,MATCH($A51,Tiers_list!$2:$2,0),FALSE)*'Proposal Form Tier 2-12'!B$12*L51/10)*(1-'Proposal Form Tier 2-12'!$B$16-'Proposal Form Tier 2-12'!$B$14) -> 0 | L51: =SUM(M51:O51) -> 0 | M51: =IF($I51>0,'Proposal Form Tier 2-12'!$B$8,0) -> 0 | N51: =IF($I51>0,'Proposal Form Tier 2-12'!$B$9,0) -> 0 | O51: =IF($I51>0,'Proposal Form Tier 2-12'!$B$10,0) -> 0 | P51: =+(J51/(1-'Proposal Form Tier 2-12'!$B$16-'Proposal Form Tier 2-12'!$B$14))+(K51/(1-'Proposal Form Tier 2-12'!$B$16-'Proposal Form Tier 2-12'!$B$14)) -> 0
A52: =+'Detail_Proposal_tier 1'!A52 -> 200-50076 | B52: =+'Detail_Proposal_tier 1'!B52 -> ACS Enterprise Integrations | C52: =+'Detail_Proposal_tier 1'!C52 -> Annual ACS Cloud Enterprise Ecosystem, Hardware, Facility Sensors, Reader Monitoring UI features | D52: =+'Detail_Proposal_tier 1'!D52 -> Merge Operations | E52: =+'Detail_Proposal_tier 1'!E52 -> Adds a Merge action to the Access Point Mgmt Match File grid, combining two or more existing match files into a single consolidated file rather than requiring operators to manage them separately. | F52: =+'Detail_Proposal_tier 1'!F52 -> ACS Cloud Enterprise lets operators consolidate multiple match file datasets — for example, lists built independently at different sites — into one unified file for centralized credential management. This removes the manual reconciliation work of comparing and merging credential lists by hand, reducing the risk of duplicate or conflicting entries across sites. | G52: =+'Detail_Proposal_tier 1'!G52 -> Optional | H52: ea. | I52: =_xlfn.XLOOKUP($A52,'Proposal Form Tier 2-12'!$C:$C,'Proposal Form Tier 2-12'!$B:$B,0,0) -> 0 | J52: =IF('Proposal Form Tier 2-12'!$B$5<>"Tier - 1 - 10",VLOOKUP('Proposal Form Tier 2-12'!$B$5,Tiers_list!$A:$BC,MATCH($A52,Tiers_list!$2:$2,0),FALSE)*I52,VLOOKUP('Proposal Form Tier 2-12'!$B$5,Tiers_list!$A:$BC,MATCH($A52,Tiers_list!$2:$2,0),FALSE)*I52/10)*(1-'Proposal Form Tier 2-12'!$B$16-'Proposal Form Tier 2-12'!$B$14) -> 0 | K52: =IF('Proposal Form Tier 2-12'!$B$5<>"Tier - 1 - 10",VLOOKUP('Proposal Form Tier 2-12'!$B$5,Tiers_list!$A:$BC,MATCH($A52,Tiers_list!$2:$2,0),FALSE)*L52*'Proposal Form Tier 2-12'!B$12,VLOOKUP('Proposal Form Tier 2-12'!$B$5,Tiers_list!$A:$BC,MATCH($A52,Tiers_list!$2:$2,0),FALSE)*'Proposal Form Tier 2-12'!B$12*L52/10)*(1-'Proposal Form Tier 2-12'!$B$16-'Proposal Form Tier 2-12'!$B$14) -> 0 | L52: =SUM(M52:O52) -> 0 | M52: =IF($I52>0,'Proposal Form Tier 2-12'!$B$8,0) -> 0 | N52: =IF($I52>0,'Proposal Form Tier 2-12'!$B$9,0) -> 0 | O52: =IF($I52>0,'Proposal Form Tier 2-12'!$B$10,0) -> 0 | P52: =+(J52/(1-'Proposal Form Tier 2-12'!$B$16-'Proposal Form Tier 2-12'!$B$14))+(K52/(1-'Proposal Form Tier 2-12'!$B$16-'Proposal Form Tier 2-12'!$B$14)) -> 0
